Workbook

Sheet Summary
A1: Sheets decomp_review queue: the 50 live tasks
A2: Source: tsip_prd via Metabase (db id 2), snapshot 2026-09-02 00:08 UTC. Every count below is a formula over the Tasks sheet.
A3: Legend: green = approve to generating_prompt; yellow = regenerate once; red = hold, needs an engineering fix. Blue text = hardcoded input.
A5: Headline | B5: Count | C5: What it means
A6: Live tasks in decomp_review (sheets) | B6: =COUNTA(Tasks!A2:A51) | C6: Reconciles to the 45 visible in the app.
A7: Have a task outline now | B7: =COUNTIF(Tasks!P2:P51,TRUE) | C7: Ready for a sense check and APPROVE. 37 were regenerated after the admin overrides, 6 are new arrivals.
A8: Still have no outline | B8: =COUNTIF(Tasks!P2:P51,FALSE) | C8: Outline agent ran with empty context on every attempt (about 5,380 input tokens instead of 100k-1.8M).
A9: of which workbook > 4MB | B9: =COUNTIFS(Tasks!P2:P51,FALSE,Tasks!AA2:AA51,TRUE) | C9: Every task in the queue with a >4MB workbook has failed every run. Re-running will not help; hold for an engineering fix or write the outline by hand.
A10: of which small workbook | B10: =COUNTIFS(Tasks!P2:P51,FALSE,Tasks!AA2:AA51,FALSE) | C10: Worth one more regeneration (25613ef5 failed twice; 437756ce is a brand-new arrival whose first run was empty).
A11: Recommended: APPROVE | B11: =COUNTIF(Tasks!C2:C51,"APPROVE*")
A12: Recommended: regenerate once | B12: =COUNTIF(Tasks!C2:C51,"Regenerate*")
A13: Recommended: HOLD | B13: =COUNTIF(Tasks!C2:C51,"HOLD*")
A14: Approvals that need summary bullets stripped first | B14: =COUNTIF(Tasks!C2:C51,"*Strip*") | C14: The generator emitted a tab list or change summary above the real build steps (2a63059e, 0e3f0394, fa5950c9, 95606585, d75d1c87, 5961c436).
A15: Approvals flagged too-easy risk | B15: =COUNTIF(Tasks!D2:D51,"*Too-easy risk*")+COUNTIF(Tasks!D2:D51,"*Foundational risk*") | C15: Under 350 unique formulas and mostly link pulls. Likely to come back Foundational or Intermediate from SOTA.
A16: Tasks written by decompers with >= 80% too-easy history | B16: =COUNTIF(Tasks!H2:H51,">=0.8") | C16: wangche2532, infinitearbitrage, mshuriah2702, nimisha. Not a blocker, but expect SOTA to cancel a good share.
A17: Clones | B17: =COUNTIF(Tasks!V2:V51,TRUE)
A18: Output workbook smaller than input | B18: =COUNTIF(Tasks!AB2:AB51,TRUE) | C18: 95606585 only. Worth a glance; not a blocker.
A19: Input and output workbook identical | B19: =COUNTIF(Tasks!AC2:AC51,TRUE) | C19: Never happens.
A21: Agent runs | B21: Value | C21: Note
A22: Total outline-agent runs for these 45 tasks | B22: =SUM(Tasks!AD2:AD51)
A23: Runs with empty context (< 10k input tokens) | B23: =SUM(Tasks!AE2:AE51)
A24: Empty-context share | B24: =B23/B22 | C24: Platform-wide since 08-26 the rate is 12% for files under 1MB, rising to 38% for files over 6MB.
A25: Tasks whose first run was empty and second run succeeded | B25: =COUNTIFS(Tasks!AE2:AE51,1,Tasks!AD2:AD51,2,Tasks!P2:P51,TRUE) | C25: The retry worked for these. The failure is intermittent for normal-sized files.
A27: Decomper | B27: Tasks in queue | C27: With outline | D27: Approve | E27: Avg unique formulas | F27: Too-easy prior (60d)
A28: wangche2532@gmail.com | B28: =COUNTIF(Tasks!G2:G51,A28) | C28: =COUNTIFS(Tasks!G2:G51,A28,Tasks!P2:P51,TRUE) | D28: =COUNTIFS(Tasks!G2:G51,A28,Tasks!C2:C51,"APPROVE*") | E28: =IFERROR(AVERAGEIF(Tasks!G2:G51,A28,Tasks!U2:U51),"-") | F28: 0.857
A29: apathy@uchicago.edu | B29: =COUNTIF(Tasks!G2:G51,A29) | C29: =COUNTIFS(Tasks!G2:G51,A29,Tasks!P2:P51,TRUE) | D29: =COUNTIFS(Tasks!G2:G51,A29,Tasks!C2:C51,"APPROVE*") | E29: =IFERROR(AVERAGEIF(Tasks!G2:G51,A29,Tasks!U2:U51),"-") | F29: 0.556
A30: mshuriah2702@gmail.com | B30: =COUNTIF(Tasks!G2:G51,A30) | C30: =COUNTIFS(Tasks!G2:G51,A30,Tasks!P2:P51,TRUE) | D30: =COUNTIFS(Tasks!G2:G51,A30,Tasks!C2:C51,"APPROVE*") | E30: =IFERROR(AVERAGEIF(Tasks!G2:G51,A30,Tasks!U2:U51),"-") | F30: 1
A31: alec.tseung@toptal.com | B31: =COUNTIF(Tasks!G2:G51,A31) | C31: =COUNTIFS(Tasks!G2:G51,A31,Tasks!P2:P51,TRUE) | D31: =COUNTIFS(Tasks!G2:G51,A31,Tasks!C2:C51,"APPROVE*") | E31: =IFERROR(AVERAGEIF(Tasks!G2:G51,A31,Tasks!U2:U51),"-") | F31: no data
A32: infinitearbitrage@gmail.com | B32: =COUNTIF(Tasks!G2:G51,A32) | C32: =COUNTIFS(Tasks!G2:G51,A32,Tasks!P2:P51,TRUE) | D32: =COUNTIFS(Tasks!G2:G51,A32,Tasks!C2:C51,"APPROVE*") | E32: =IFERROR(AVERAGEIF(Tasks!G2:G51,A32,Tasks!U2:U51),"-") | F32: 0.875
A33: nimisha.mekala2021@gmail.com | B33: =COUNTIF(Tasks!G2:G51,A33) | C33: =COUNTIFS(Tasks!G2:G51,A33,Tasks!P2:P51,TRUE) | D33: =COUNTIFS(Tasks!G2:G51,A33,Tasks!C2:C51,"APPROVE*") | E33: =IFERROR(AVERAGEIF(Tasks!G2:G51,A33,Tasks!U2:U51),"-") | F33: 1
A34: sophie.xiao@toptal.com | B34: =COUNTIF(Tasks!G2:G51,A34) | C34: =COUNTIFS(Tasks!G2:G51,A34,Tasks!P2:P51,TRUE) | D34: =COUNTIFS(Tasks!G2:G51,A34,Tasks!C2:C51,"APPROVE*") | E34: =IFERROR(AVERAGEIF(Tasks!G2:G51,A34,Tasks!U2:U51),"-") | F34: 0
A35: Too-easy prior = share of the decomper's SOTA-scored sheets tasks (last 60 days) bucketed Foundational or Intermediate. Hardcoded from sota_priors.md.
A37: What happened today (UTC)
A38: 21:58-23:00 ali@meridian.ai pushed the 40 leftover tasks (32 no-outline + 8 thin/truncated) back through generating_outline via ADMIN_OVERRIDE.
A39: The regeneration produced an outline for 34 of them. The 6 that still failed are the five >4MB workbooks plus 25613ef5.
A40: 22:45-00:03 7 new tasks arrived from decompers (a0b42bc7, f09e7718, fdfd6024, d75d1c87, 8f99bcd7, f3efbb17, 437756ce). All but 437756ce have outlines.
A41: 00:01 The 5 tasks parked in failed_generating_outline were overridden back to generating_outline; 3 (c4ed90cb, f925d988, 5961c436) came back with outlines by 00:08, 2 (9f656c96, 4c77fbdb) were still running.
A42: 23:24-23:26 The 133 tasks approved earlier left the queue. 14 of them failed prompt generation within 5 minutes (11% vs a 0.5-2% daily norm); release the next batch in groups of about 20.
A43: Every one of the 45 tasks sits at "generating_outline -> decomp_review (SUBMIT_TASK_OUTLINE)" as its last transition. Nobody has reviewed them; the pool is disabled for this state.

Sheet Tasks
A1: Task | B1: Diagnosis | C1: Recommended action | D1: Quality flags (from reading the outline) | E1: Evidence | F1: Bucket in 09-01 triage | G1: Decomper | H1: Decomper too-easy prior | I1: Decomper SOTA-scored (n) | J1: Entered decomp_review (UTC) | K1: Days waiting | L1: decomp_review visits | M1: Outline generations | N1: Admin overrides | O1: Override by | P1: Has outline | Q1: Outline chars (now) | R1: Outline chars (09-01 snapshot) | S1: Bullets | T1: Transition chars | U1: Unique formulas | V1: Is clone | W1: Input workbook | X1: Input KB | Y1: Output workbook | Z1: Output KB | AA1: Largest file > 4MB | AB1: Output smaller than input | AC1: Files identical | AD1: Agent runs | AE1: Empty-context runs | AF1: Last run status | AG1: Last run input tokens | AH1: Last run output tokens | AI1: Source file (decomper upload) | AJ1: Cloned from task | AK1: Task ID
A2: 7215fd35 | B2: NO OUTLINE - agent ran with empty context on every attempt | C2: HOLD. Do not re-run. Workbook is over 4MB and has failed 2 of 2 runs (5,38x input tokens = workbook never loaded). Needs an engineering fix to the outline agent, or a manual outline. | E2: 2 agent runs, 2 with empty context (last run: 5384 in / 1 out). Workbooks 4614KB in / 6416KB out. | F2: A1_no_outline | G2: alec.tseung@toptal.com | I2: 0 | J2: 46266.916 | K2: 0.1 | L2: 2 | M2: 2 | N2: 1 | O2: ali@meridian.ai | P2: FALSE | Q2: 0 | S2: 0 | T2: 226 | U2: 220747 | V2: FALSE | W2: 08.27_139_N-3.xlsx | X2: 4614 | Y2: 08.27_139_N-2.xlsx | Z2: 6417 | AA2: TRUE | AB2: FALSE | AC2: FALSE | AD2: 2 | AE2: 2 | AF2: completed | AG2: 5384 | AH2: 1 | AK2: 7215fd35-f477-44af-b6f1-b38348ebe264
A3: 3d3b229e | B3: NO OUTLINE - agent ran with empty context on every attempt | C3: HOLD. Do not re-run. Workbook is over 4MB and has failed 2 of 2 runs (5,38x input tokens = workbook never loaded). Needs an engineering fix to the outline agent, or a manual outline. | E3: 2 agent runs, 2 with empty context (last run: 5387 in / 7 out). Workbooks 4161KB in / 4446KB out. | F3: A1_no_outline | G3: alec.tseung@toptal.com | I3: 0 | J3: 46266.918 | K3: 0.1 | L3: 2 | M3: 2 | N3: 1 | O3: ali@meridian.ai | P3: FALSE | Q3: 0 | S3: 0 | T3: 42 | U3: 22547 | V3: FALSE | W3: 08.27_139_N-5.xlsx | X3: 4162 | Y3: 08.27_139_N-4.xlsx | Z3: 4446 | AA3: TRUE | AB3: FALSE | AC3: FALSE | AD3: 2 | AE3: 2 | AF3: completed | AG3: 5387 | AH3: 7 | AK3: 3d3b229e-0507-4539-8343-193a679d5f5c
A4: 337252e6 | B4: NO OUTLINE - agent ran with empty context on every attempt | C4: HOLD. Do not re-run. Workbook is over 4MB and has failed 2 of 2 runs (5,38x input tokens = workbook never loaded). Needs an engineering fix to the outline agent, or a manual outline. | E4: 2 agent runs, 2 with empty context (last run: 5387 in / 1 out). Workbooks 6416KB in / 6852KB out. | F4: A1_no_outline | G4: alec.tseung@toptal.com | I4: 0 | J4: 46266.925 | K4: 0.1 | L4: 2 | M4: 2 | N4: 1 | O4: ali@meridian.ai | P4: FALSE | Q4: 0 | S4: 0 | T4: 61 | U4: 17725 | V4: FALSE | W4: 08.27_139_N-2.xlsx | X4: 6417 | Y4: 08.27_139_N-1.xlsx | Z4: 6852 | AA4: TRUE | AB4: FALSE | AC4: FALSE | AD4: 2 | AE4: 2 | AF4: completed | AG4: 5387 | AH4: 1 | AK4: 337252e6-80dc-4b36-b284-7b83b4e5617f
A5: 8a8066ff | B5: NO OUTLINE - agent ran with empty context on every attempt | C5: HOLD. Do not re-run. Workbook is over 4MB and has failed 2 of 2 runs (5,38x input tokens = workbook never loaded). Needs an engineering fix to the outline agent, or a manual outline. | E5: 2 agent runs, 2 with empty context (last run: 5390 in / 5 out). Workbooks 4446KB in / 4614KB out. | F5: A1_no_outline | G5: alec.tseung@toptal.com | I5: 0 | J5: 46266.922 | K5: 0.1 | L5: 2 | M5: 2 | N5: 1 | O5: ali@meridian.ai | P5: FALSE | Q5: 0 | S5: 0 | T5: 152 | U5: 14594 | V5: FALSE | W5: 08.27_139_N-4.xlsx | X5: 4446 | Y5: 08.27_139_N-3.xlsx | Z5: 4614 | AA5: TRUE | AB5: FALSE | AC5: FALSE | AD5: 2 | AE5: 2 | AF5: completed | AG5: 5390 | AH5: 5 | AK5: 8a8066ff-7624-4fc5-981f-52a666b28967
A6: 906892cf | B6: NO OUTLINE - agent ran with empty context on every attempt | C6: HOLD. Do not re-run. Workbook is over 4MB and has failed 2 of 2 runs (5,38x input tokens = workbook never loaded). Needs an engineering fix to the outline agent, or a manual outline. | E6: 2 agent runs, 2 with empty context (last run: 5386 in / 4 out). Workbooks 7602KB in / 7681KB out. | F6: A1_no_outline | G6: infinitearbitrage@gmail.com | H6: 0.875 | I6: 16 | J6: 46266.918 | K6: 0.1 | L6: 2 | M6: 2 | N6: 1 | O6: ali@meridian.ai | P6: FALSE | Q6: 0 | S6: 0 | T6: 91 | U6: 1847 | V6: FALSE | W6: 08.29_117 N-5.xlsx | X6: 7602 | Y6: 08.29_117 N-4.xlsx | Z6: 7682 | AA6: TRUE | AB6: FALSE | AC6: FALSE | AD6: 2 | AE6: 2 | AF6: completed | AG6: 5386 | AH6: 4 | AK6: 906892cf-1049-4c2d-99ef-404e461c776f
A7: 25613ef5 | B7: NO OUTLINE - agent ran with empty context on every attempt | C7: Regenerate outline once more. File is small (405KB / 481KB) and has had 2 empty run(s); if it keeps failing treat like the large-file cases. | E7: 2 agent runs, 2 with empty context (last run: 5391 in / 4 out). Workbooks 405KB in / 481KB out. | F7: A1_no_outline | G7: wangche2532@gmail.com | H7: 0.857 | I7: 28 | J7: 46266.925 | K7: 0.1 | L7: 2 | M7: 2 | N7: 1 | O7: ali@meridian.ai | P7: FALSE | Q7: 0 | S7: 0 | T7: 196 | U7: 8528 | V7: FALSE | W7: 08.30_48 N-6.xlsx | X7: 406 | Y7: 08.30_48 N-5.xlsx | Z7: 481 | AA7: FALSE | AB7: FALSE | AC7: FALSE | AD7: 2 | AE7: 2 | AF7: completed | AG7: 5391 | AH7: 4 | AK7: 25613ef5-50aa-4ab2-b49a-4ea4b4dc519a
A8: 437756ce | B8: NO OUTLINE - agent ran with empty context on every attempt | C8: Regenerate outline once more. File is small (249KB / 259KB) and has had 1 empty run(s); if it keeps failing treat like the large-file cases. | E8: 1 agent runs, 1 with empty context (last run: 5391 in / 1 out). Workbooks 249KB in / 259KB out. | F8: NEW (arrived after the triage snapshot) | G8: wangche2532@gmail.com | H8: 0.857 | I8: 28 | J8: 46267.002 | K8: 0 | L8: 1 | M8: 1 | N8: 0 | P8: FALSE | Q8: 0 | S8: 0 | T8: 117 | U8: 211 | V8: FALSE | W8: 08.31_47 N-2.xlsx | X8: 250 | Y8: 08.31_47 N-1.xlsx | Z8: 260 | AA8: FALSE | AB8: FALSE | AC8: FALSE | AD8: 1 | AE8: 1 | AF8: completed | AG8: 5391 | AH8: 1 | AK8: 437756ce-b81b-403d-8a2d-be439ba78b4a
A9: a5f013b8 | B9: Regenerated today - outline now present (first run was empty context, second run healthy) | C9: APPROVE to generating_prompt. | E9: 19 bullets, 12065 chars. Last run 1,689,428 in / 19,764 out. | F9: A1_no_outline | G9: apathy@uchicago.edu | H9: 0.556 | I9: 9 | J9: 46266.923 | K9: 0.1 | L9: 2 | M9: 3 | N9: 1 | O9: ali@meridian.ai | P9: TRUE | Q9: 12065 | S9: 19 | T9: 172 | U9: 20166 | V9: FALSE | W9: 67a-N-3.xlsx | X9: 321 | Y9: 67a-N-2.xlsx | Z9: 538 | AA9: FALSE | AB9: FALSE | AC9: FALSE | AD9: 2 | AE9: 1 | AF9: completed | AG9: 1689428 | AH9: 19764 | AK9: a5f013b8-ef14-4437-bea0-630504093c40
A10: 4f56a4bf | B10: Regenerated today - outline now present (first run was empty context, second run healthy) | C10: APPROVE to generating_prompt. | E10: 13 bullets, 13635 chars. Last run 1,787,806 in / 13,833 out. | F10: A1_no_outline | G10: apathy@uchicago.edu | H10: 0.556 | I10: 9 | J10: 46266.923 | K10: 0.1 | L10: 2 | M10: 3 | N10: 1 | O10: ali@meridian.ai | P10: TRUE | Q10: 13635 | S10: 13 | T10: 206 | U10: 18080 | V10: FALSE | W10: 1b1-N-3.xlsx | X10: 2465 | Y10: 1b1-N-2.xlsx | Z10: 2704 | AA10: FALSE | AB10: FALSE | AC10: FALSE | AD10: 2 | AE10: 1 | AF10: completed | AG10: 1787806 | AH10: 13833 | AK10: 4f56a4bf-a1c1-4a5a-a04b-0002394e52c8
A11: e8ad8af9 | B11: Regenerated today - outline now present (first run was empty context, second run healthy) | C11: APPROVE to generating_prompt. | D11: Decomper prior: 88% of their SOTA-scored tasks came back too easy (n=16). | E11: 18 bullets, 10819 chars. Last run 661,231 in / 6,654 out. | F11: A1_no_outline | G11: infinitearbitrage@gmail.com | H11: 0.875 | I11: 16 | J11: 46266.916 | K11: 0.1 | L11: 2 | M11: 3 | N11: 1 | O11: ali@meridian.ai | P11: TRUE | Q11: 10819 | S11: 18 | T11: 54 | U11: 15492 | V11: FALSE | W11: 08.31_39 N-3.xlsx | X11: 37 | Y11: 08.31_39 N-2.xlsx | Z11: 273 | AA11: FALSE | AB11: FALSE | AC11: FALSE | AD11: 2 | AE11: 1 | AF11: completed | AG11: 661231 | AH11: 6654 | AK11: e8ad8af9-0dc2-4a47-915d-69799551aad9
A12: 15a0ebf7 | B12: Regenerated today - outline now present (first run was empty context, second run healthy) | C12: APPROVE to generating_prompt. | D12: Decomper prior: 100% of their SOTA-scored tasks came back too easy (n=2). | E12: 12 bullets, 6847 chars. Last run 902,266 in / 16,002 out. | F12: A1_no_outline | G12: nimisha.mekala2021@gmail.com | H12: 1 | I12: 2 | J12: 46266.919 | K12: 0.1 | L12: 2 | M12: 3 | N12: 1 | O12: ali@meridian.ai | P12: TRUE | Q12: 6847 | S12: 12 | T12: 87 | U12: 12659 | V12: FALSE | W12: MFESC_-_Model.redacted-hygiene_N-4.xlsx | X12: 1268 | Y12: MFESC_-_Model.redacted-hygiene_N-3.xlsx | Z12: 1390 | AA12: FALSE | AB12: FALSE | AC12: FALSE | AD12: 2 | AE12: 1 | AF12: completed | AG12: 902266 | AH12: 16002 | AK12: 15a0ebf7-8354-4e97-bdfd-764a03bef9ee
A13: f925d988 | B13: Regenerated twice today (failed loudly at 22:59, succeeded at 00:02) - outline now 8221 chars (was 5989) | C13: APPROVE to generating_prompt. | D13: One agent run from 22:55 is still marked running with empty context (a stuck record); the 00:02 run completed healthy and produced this outline. | E13: 17 bullets, 8221 chars. Last run 320,505 in / 10,551 out. | F13: D_thin_transition | G13: apathy@uchicago.edu | H13: 0.556 | I13: 9 | J13: 46267.004 | K13: 0 | L13: 2 | M13: 5 | N13: 2 | O13: ali@meridian.ai | P13: TRUE | Q13: 8221 | R13: 5989 | S13: 17 | T13: 12 | U13: 12113 | V13: FALSE | W13: fa9-N-4.xlsx | X13: 985 | Y13: fa9-N-3.xlsx | Z13: 1084 | AA13: FALSE | AB13: FALSE | AC13: FALSE | AD13: 3 | AE13: 1 | AF13: completed | AG13: 320505 | AH13: 10551 | AK13: f925d988-87c3-4cb0-a396-b583b2949382
A14: 21d534e3 | B14: Regenerated today - outline now present (first run was empty context, second run healthy) | C14: APPROVE to generating_prompt. | E14: 15 bullets, 11075 chars. Last run 617,199 in / 14,519 out. | F14: A1_no_outline | G14: apathy@uchicago.edu | H14: 0.556 | I14: 9 | J14: 46266.918 | K14: 0.1 | L14: 2 | M14: 3 | N14: 1 | O14: ali@meridian.ai | P14: TRUE | Q14: 11075 | S14: 15 | T14: 128 | U14: 10061 | V14: FALSE | W14: bbe-N-5.xlsx | X14: 666 | Y14: bbe-N-4.xlsx | Z14: 817 | AA14: FALSE | AB14: FALSE | AC14: FALSE | AD14: 2 | AE14: 1 | AF14: completed | AG14: 617199 | AH14: 14519 | AK14: 21d534e3-8c09-46e5-8a5d-b5c55c8522a2
A15: 552a9578 | B15: Regenerated today - outline now present (first run was empty context, second run healthy) | C15: APPROVE to generating_prompt. | D15: Decomper prior: 86% of their SOTA-scored tasks came back too easy (n=28). | E15: 23 bullets, 11303 chars. Last run 1,252,033 in / 15,059 out. | F15: A1_no_outline | G15: wangche2532@gmail.com | H15: 0.857 | I15: 28 | J15: 46266.92 | K15: 0.1 | L15: 2 | M15: 3 | N15: 1 | O15: ali@meridian.ai | P15: TRUE | Q15: 11303 | S15: 23 | T15: 181 | U15: 8568 | V15: FALSE | W15: 08.30_59 N-3.xlsx | X15: 393 | Y15: 08.30_59 N-2.xlsx | Z15: 511 | AA15: FALSE | AB15: FALSE | AC15: FALSE | AD15: 2 | AE15: 1 | AF15: completed | AG15: 1252033 | AH15: 15059 | AK15: 552a9578-aaf8-453b-8f58-e85a1ed40315
A16: a0b42bc7 | B16: New arrival - first visit, healthy agent run, outline present | C16: APPROVE to generating_prompt. | D16: Decomper prior: 86% of their SOTA-scored tasks came back too easy (n=28). | E16: 19 bullets, 7699 chars. Last run 1,245,622 in / 10,184 out. | F16: NEW (arrived after the triage snapshot) | G16: wangche2532@gmail.com | H16: 0.857 | I16: 28 | J16: 46266.948 | K16: 0.1 | L16: 1 | M16: 2 | N16: 0 | P16: TRUE | Q16: 7699 | S16: 19 | T16: 39 | U16: 8208 | V16: FALSE | W16: 08.31_78 N-3.xlsx | X16: 122 | Y16: 08.31_78 N-2.xlsx | Z16: 431 | AA16: FALSE | AB16: FALSE | AC16: FALSE | AD16: 1 | AE16: 0 | AF16: completed | AG16: 1245622 | AH16: 10184 | AK16: a0b42bc7-af28-40a5-80c2-7a103169a005
A17: 41fbe12c | B17: Regenerated twice today (failed loudly at 22:59, succeeded at 00:02) - outline now 14756 chars (was 0) | C17: APPROVE to generating_prompt. | E17: 32 bullets, 14756 chars. Last run 805,080 in / 13,754 out. | F17: A2_no_outline_looping | G17: apathy@uchicago.edu | H17: 0.556 | I17: 9 | J17: 46266.958 | K17: 0 | L17: 4 | M17: 5 | N17: 3 | O17: ali@meridian.ai, rishi@meridian.ai | P17: TRUE | Q17: 14756 | S17: 32 | T17: 156 | U17: 8187 | V17: TRUE | W17: 049-N-1.xlsx | X17: 323 | Y17: 049-N-0.xlsx | Z17: 468 | AA17: FALSE | AB17: FALSE | AC17: FALSE | AD17: 4 | AE17: 3 | AF17: completed | AG17: 805080 | AH17: 13754 | AJ17: 513b9b3f-fddb-4889-b6f2-ab71b1535791 | AK17: 41fbe12c-7c20-463d-96e8-4ae8700d1c0d
A18: 7b4c773f | B18: Regenerated today - outline now present (first run was empty context, second run healthy) | C18: APPROVE to generating_prompt. | E18: 19 bullets, 6881 chars. Last run 302,515 in / 8,875 out. | F18: A1_no_outline | G18: apathy@uchicago.edu | H18: 0.556 | I18: 9 | J18: 46266.917 | K18: 0.1 | L18: 2 | M18: 3 | N18: 1 | O18: ali@meridian.ai | P18: TRUE | Q18: 6881 | S18: 19 | T18: 33 | U18: 7637 | V18: FALSE | W18: bbe-N-3.xlsx | X18: 874 | Y18: bbe-N-2.xlsx | Z18: 927 | AA18: FALSE | AB18: FALSE | AC18: FALSE | AD18: 2 | AE18: 1 | AF18: completed | AG18: 302515 | AH18: 8875 | AK18: 7b4c773f-02c0-42cf-a37b-04b6773b86c0
A19: 62d0dff1 | B19: Regenerated today - outline now present (first run was empty context, second run healthy) | C19: APPROVE to generating_prompt. | D19: Decomper prior: 86% of their SOTA-scored tasks came back too easy (n=28). | E19: 14 bullets, 5587 chars. Last run 130,516 in / 6,365 out. | F19: A1_no_outline | G19: wangche2532@gmail.com | H19: 0.857 | I19: 28 | J19: 46266.916 | K19: 0.1 | L19: 2 | M19: 3 | N19: 1 | O19: ali@meridian.ai | P19: TRUE | Q19: 5587 | S19: 14 | T19: 45 | U19: 7131 | V19: FALSE | W19: 08.30_59 N-2.xlsx | X19: 511 | Y19: 08.30_59 N-1.xlsx | Z19: 601 | AA19: FALSE | AB19: FALSE | AC19: FALSE | AD19: 2 | AE19: 1 | AF19: completed | AG19: 130516 | AH19: 6365 | AK19: 62d0dff1-ef18-40ae-879c-f7dd0fc7a67e
A20: 443385cc | B20: Regenerated today - outline now present (first run was empty context, second run healthy) | C20: APPROVE to generating_prompt. | D20: Decomper prior: 86% of their SOTA-scored tasks came back too easy (n=28). | E20: 16 bullets, 7623 chars. Last run 246,647 in / 8,273 out. | F20: A1_no_outline | G20: wangche2532@gmail.com | H20: 0.857 | I20: 28 | J20: 46266.917 | K20: 0.1 | L20: 2 | M20: 3 | N20: 1 | O20: ali@meridian.ai | P20: TRUE | Q20: 7623 | S20: 16 | T20: 33 | U20: 5573 | V20: FALSE | W20: 08.30_59 N-4.xlsx | X20: 325 | Y20: 08.30_59 N-3.xlsx | Z20: 393 | AA20: FALSE | AB20: FALSE | AC20: FALSE | AD20: 2 | AE20: 1 | AF20: completed | AG20: 246647 | AH20: 8273 | AK20: 443385cc-42c6-486b-ac8e-fd8724d99160
A21: 69633abd | B21: Regenerated twice today (failed loudly at 22:59, succeeded at 00:02) - outline now 5529 chars (was 8361) | C21: APPROVE to generating_prompt. | D21: Last bullet is stray hardcode fragments (36/156, 164.7/158.7-1). History is churny: 4 decomp_review visits, 7 outline generations. | E21: 15 bullets, 5529 chars. Last run 284,605 in / 9,151 out. | F21: D_thin_transition | G21: apathy@uchicago.edu | H21: 0.556 | I21: 9 | J21: 46266.957 | K21: 0 | L21: 4 | M21: 7 | N21: 3 | O21: ali@meridian.ai, leo@meridian.ai, rishi@meridian.ai | P21: TRUE | Q21: 5529 | R21: 8361 | S21: 15 | T21: 16 | U21: 3137 | V21: FALSE | W21: c3b-N-3.xlsx | X21: 275 | Y21: c3b-N-2.xlsx | Z21: 329 | AA21: FALSE | AB21: FALSE | AC21: FALSE | AD21: 4 | AE21: 2 | AF21: completed | AG21: 284605 | AH21: 9151 | AK21: 69633abd-f051-404b-81ac-eff6a9593427
A22: d010dfa4 | B22: Regenerated today - outline now present (first run was empty context, second run healthy) | C22: APPROVE to generating_prompt. | D22: Decomper prior: 100% of their SOTA-scored tasks came back too easy (n=4). | E22: 19 bullets, 9371 chars. Last run 547,503 in / 11,701 out. | F22: A1_no_outline | G22: mshuriah2702@gmail.com | H22: 1 | I22: 4 | J22: 46266.923 | K22: 0.1 | L22: 2 | M22: 3 | N22: 1 | O22: ali@meridian.ai | P22: TRUE | Q22: 9371 | S22: 19 | T22: 1068 | U22: 3059 | V22: TRUE | W22: 6a9e8983 N-1.xlsx | X22: 1399 | Y22: 6a9e8983.xlsx | Z22: 1509 | AA22: FALSE | AB22: FALSE | AC22: FALSE | AD22: 2 | AE22: 1 | AF22: completed | AG22: 547503 | AH22: 11701 | AJ22: 218a5a0c-0db0-42ac-83bf-a147c71a322f | AK22: d010dfa4-e4d0-42a5-a7f6-a3ef1e58e0e9
A23: c4ed90cb | B23: Regenerated twice today (failed loudly at 22:59, succeeded at 00:02) - outline now 6005 chars (was 46) | C23: APPROVE to generating_prompt. | E23: 18 bullets, 6005 chars. Last run 177,709 in / 7,916 out. | F23: B_thin_outline | G23: apathy@uchicago.edu | H23: 0.556 | I23: 9 | J23: 46267.004 | K23: 0 | L23: 2 | M23: 5 | N23: 2 | O23: ali@meridian.ai | P23: TRUE | Q23: 6005 | R23: 46 | S23: 18 | T23: 44 | U23: 2828 | V23: FALSE | W23: bbe-N-4.xlsx | X23: 817 | Y23: bbe-N-3.xlsx | Z23: 874 | AA23: FALSE | AB23: FALSE | AC23: FALSE | AD23: 3 | AE23: 1 | AF23: completed | AG23: 177709 | AH23: 7916 | AK23: c4ed90cb-4e82-408b-82fa-f52a782f72d3
A24: cfb56338 | B24: Regenerated today - outline now present (first run was empty context, second run healthy) | C24: APPROVE to generating_prompt. | D24: Decomper prior: 100% of their SOTA-scored tasks came back too easy (n=4). | E24: 9 bullets, 5506 chars. Last run 468,970 in / 11,380 out. | F24: A1_no_outline | G24: mshuriah2702@gmail.com | H24: 1 | I24: 4 | J24: 46266.919 | K24: 0.1 | L24: 2 | M24: 3 | N24: 1 | O24: ali@meridian.ai | P24: TRUE | Q24: 5506 | S24: 9 | T24: 220 | U24: 2606 | V24: FALSE | W24: 6a9e8983 N-3.xlsx | X24: 1331 | Y24: 6a9e8983 N-2.xlsx | Z24: 1372 | AA24: FALSE | AB24: FALSE | AC24: FALSE | AD24: 2 | AE24: 1 | AF24: completed | AG24: 468970 | AH24: 11380 | AK24: cfb56338-4a27-42d5-9e0d-9e59b2fa8640
A25: 1998a617 | B25: Regenerated today - outline now present (first run was empty context, second run healthy) | C25: APPROVE to generating_prompt. | D25: Decomper prior: 100% of their SOTA-scored tasks came back too easy (n=2). | E25: 17 bullets, 8355 chars. Last run 590,320 in / 10,687 out. | F25: A1_no_outline | G25: nimisha.mekala2021@gmail.com | H25: 1 | I25: 2 | J25: 46266.918 | K25: 0.1 | L25: 2 | M25: 3 | N25: 1 | O25: ali@meridian.ai | P25: TRUE | Q25: 8355 | S25: 17 | T25: 255 | U25: 1856 | V25: FALSE | W25: Fremont_ASCs_Merger_Model_v7.redacted-hygiene_N-4.xlsx | X25: 606 | Y25: Fremont_ASCs_Merger_Model_v7.redacted-hygiene_N-3.xlsx | Z25: 658 | AA25: FALSE | AB25: FALSE | AC25: FALSE | AD25: 2 | AE25: 1 | AF25: completed | AG25: 590320 | AH25: 10687 | AK25: 1998a617-9037-46d2-912b-adfdb4441444
A26: 5da033e5 | B26: Regenerated today - outline now present (first run was empty context, second run healthy) | C26: APPROVE to generating_prompt. | D26: Decomper prior: 86% of their SOTA-scored tasks came back too easy (n=28). | E26: 9 bullets, 4421 chars. Last run 228,189 in / 4,614 out. | F26: A1_no_outline | G26: wangche2532@gmail.com | H26: 0.857 | I26: 28 | J26: 46266.916 | K26: 0.1 | L26: 2 | M26: 3 | N26: 1 | O26: ali@meridian.ai | P26: TRUE | Q26: 4421 | S26: 9 | T26: 151 | U26: 1645 | V26: FALSE | W26: 08.30_40 N-4.xlsx | X26: 188 | Y26: 08.30_40 N-3.xlsx | Z26: 231 | AA26: FALSE | AB26: FALSE | AC26: FALSE | AD26: 2 | AE26: 1 | AF26: completed | AG26: 228189 | AH26: 4614 | AK26: 5da033e5-0b26-4526-afaf-8e71e57612a4
A27: 27b833b2 | B27: Regenerated today - outline now present (first run was empty context, second run healthy) | C27: APPROVE to generating_prompt. | D27: Decomper prior: 100% of their SOTA-scored tasks came back too easy (n=4). | E27: 22 bullets, 6379 chars. Last run 364,933 in / 10,263 out. | F27: A1_no_outline | G27: mshuriah2702@gmail.com | H27: 1 | I27: 4 | J27: 46266.918 | K27: 0.1 | L27: 2 | M27: 3 | N27: 1 | O27: ali@meridian.ai | P27: TRUE | Q27: 6379 | S27: 22 | T27: 286 | U27: 1645 | V27: FALSE | W27: 6a9e8983 N-2.xlsx | X27: 1372 | Y27: 6a9e8983 N-1.xlsx | Z27: 1399 | AA27: FALSE | AB27: FALSE | AC27: FALSE | AD27: 2 | AE27: 1 | AF27: completed | AG27: 364933 | AH27: 10263 | AK27: 27b833b2-b759-439b-aa91-db78616e22b8
A28: c4ba7c97 | B28: Regenerated today - outline now present (first run was empty context, second run healthy) | C28: APPROVE to generating_prompt. | D28: Decomper prior: 86% of their SOTA-scored tasks came back too easy (n=28). | E28: 11 bullets, 6347 chars. Last run 186,191 in / 7,049 out. | F28: A1_no_outline | G28: wangche2532@gmail.com | H28: 0.857 | I28: 28 | J28: 46266.916 | K28: 0.1 | L28: 2 | M28: 3 | N28: 1 | O28: ali@meridian.ai | P28: TRUE | Q28: 6347 | S28: 11 | T28: 56 | U28: 1635 | V28: TRUE | W28: 08.30_24 N-1.xlsx | X28: 263 | Y28: 08.30_24 N.xlsx | Z28: 282 | AA28: FALSE | AB28: FALSE | AC28: FALSE | AD28: 2 | AE28: 1 | AF28: completed | AG28: 186191 | AH28: 7049 | AJ28: 6fe4dc2b-58b3-490f-a9fe-d87c28bf0273 | AK28: c4ba7c97-5f2e-4e3e-8f63-3d68539868bc
A29: 92b20cff | B29: Regenerated today - outline now present (first run was empty context, second run healthy) | C29: APPROVE to generating_prompt. | D29: Decomper prior: 88% of their SOTA-scored tasks came back too easy (n=16). | E29: 22 bullets, 9093 chars. Last run 488,250 in / 11,776 out. | F29: A1_no_outline | G29: infinitearbitrage@gmail.com | H29: 0.875 | I29: 16 | J29: 46266.917 | K29: 0.1 | L29: 2 | M29: 3 | N29: 1 | O29: ali@meridian.ai | P29: TRUE | Q29: 9093 | S29: 22 | T29: 84 | U29: 1598 | V29: TRUE | W29: 08.29_28 N-1.xlsx | X29: 274 | Y29: 08.29_28.xlsx | Z29: 320 | AA29: FALSE | AB29: FALSE | AC29: FALSE | AD29: 2 | AE29: 1 | AF29: completed | AG29: 488250 | AH29: 11776 | AJ29: 54b24e89-72a3-4a17-aacf-2160406784d8 | AK29: 92b20cff-2188-474c-b966-e33ada1437ee
A30: 5961c436 | B30: Regenerated twice today (failed loudly at 22:59, succeeded at 00:02) - outline now 10121 chars (was 892) | C30: APPROVE to generating_prompt. Strip the summary/meta bullets first. | D30: 4 summary bullets at the top (tab list, per-tab change notes) before the build steps; strip them. One bullet lists 46 hardcoded monthly seed values verbatim; harmless but long. Decomper prior: 86% of their SOTA-scored tasks came back too easy (n=28). | E30: 13 bullets, 10121 chars. Last run 382,469 in / 10,257 out. | F30: B_thin_outline | G30: wangche2532@gmail.com | H30: 0.857 | I30: 28 | J30: 46267.006 | K30: 0 | L30: 2 | M30: 5 | N30: 2 | O30: ali@meridian.ai | P30: TRUE | Q30: 10121 | R30: 892 | S30: 13 | T30: 195 | U30: 1330 | V30: TRUE | W30: 08.30_21 N-1.xlsx | X30: 1397 | Y30: 08.30_21 N.xlsx | Z30: 1446 | AA30: FALSE | AB30: FALSE | AC30: FALSE | AD30: 3 | AE30: 1 | AF30: completed | AG30: 382469 | AH30: 10257 | AJ30: 33471211-ec23-4812-aea8-b2f3c7fba27d | AK30: 5961c436-e583-4000-ad25-cc8e11a634ae
A31: 0e3f0394 | B31: Regenerated today - outline now present (first run was empty context, second run healthy) | C31: APPROVE to generating_prompt. Strip the summary/meta bullets first. | D31: 5 summary bullets at the top (per-tab change notes) before the build steps; strip them. | E31: 16 bullets, 9135 chars. Last run 231,844 in / 8,360 out. | F31: A1_no_outline | G31: sophie.xiao@toptal.com | H31: 0 | I31: 8 | J31: 46266.917 | K31: 0.1 | L31: 2 | M31: 3 | N31: 1 | O31: ali@meridian.ai | P31: TRUE | Q31: 9135 | S31: 16 | T31: 80 | U31: 1221 | V31: FALSE | W31: 08.31_50 N-3.xlsx | X31: 430 | Y31: 08.31_50 N-2 new.xlsx | Z31: 451 | AA31: FALSE | AB31: FALSE | AC31: FALSE | AD31: 2 | AE31: 1 | AF31: completed | AG31: 231844 | AH31: 8360 | AK31: 0e3f0394-b3e2-4e6c-836e-704eff6c48e2
A32: f3efbb17 | B32: New arrival - first visit, healthy agent run, outline present | C32: APPROVE to generating_prompt. | D32: Decomper prior: 86% of their SOTA-scored tasks came back too easy (n=28). | E32: 12 bullets, 9869 chars. Last run 144,623 in / 8,132 out. | F32: NEW (arrived after the triage snapshot) | G32: wangche2532@gmail.com | H32: 0.857 | I32: 28 | J32: 46266.999 | K32: 0 | L32: 1 | M32: 2 | N32: 0 | P32: TRUE | Q32: 9869 | S32: 12 | T32: 331 | U32: 1206 | V32: TRUE | W32: 08.31_47 N-1.xlsx | X32: 260 | Y32: 08.31_47 N.xlsx | Z32: 307 | AA32: FALSE | AB32: FALSE | AC32: FALSE | AD32: 1 | AE32: 0 | AF32: completed | AG32: 144623 | AH32: 8132 | AJ32: 2e65b7ae-9888-4bf7-99e7-ee2f3541c122 | AK32: f3efbb17-561b-44a2-8f87-28e2abf47f9f
A33: fa5950c9 | B33: Regenerated twice today (failed loudly at 22:59, succeeded at 00:02) - outline now 7081 chars (was 517) | C33: APPROVE to generating_prompt. Strip the summary/meta bullets first. | D33: 6 summary bullets at the top (tab list tagged "(heavy)") before the build steps; strip them. Decomper prior: 86% of their SOTA-scored tasks came back too easy (n=28). | E33: 15 bullets, 7081 chars. Last run 314,331 in / 8,762 out. | F33: B_thin_outline | G33: wangche2532@gmail.com | H33: 0.857 | I33: 28 | J33: 46266.958 | K33: 0 | L33: 2 | M33: 4 | N33: 1 | O33: ali@meridian.ai | P33: TRUE | Q33: 7081 | R33: 517 | S33: 15 | T33: 154 | U33: 1106 | V33: TRUE | W33: 08.30_37 N-1.xlsx | X33: 565 | Y33: 08.30_37 N.xlsx | Z33: 585 | AA33: FALSE | AB33: FALSE | AC33: FALSE | AD33: 2 | AE33: 1 | AF33: completed | AG33: 314331 | AH33: 8762 | AJ33: e2ee0dfe-ea7c-4a12-9941-7407a0e86152 | AK33: fa5950c9-4c71-4406-83bf-8fd81fc6ff67
A34: 79036bd8 | B34: Regenerated twice today (failed loudly at 22:59, succeeded at 00:02) - outline now 8908 chars (was 5975) | C34: APPROVE to generating_prompt. | E34: 14 bullets, 8908 chars. Last run 172,748 in / 7,165 out. | F34: C_truncated_outline | G34: alec.tseung@toptal.com | I34: 0 | J34: 46266.957 | K34: 0 | L34: 2 | M34: 4 | N34: 1 | O34: ali@meridian.ai | P34: TRUE | Q34: 8908 | R34: 5975 | S34: 14 | T34: 52 | U34: 1061 | V34: FALSE | W34: 08.27_141_N-2.xlsx | X34: 32 | Y34: 08.27_141_N-1.xlsx | Z34: 48 | AA34: FALSE | AB34: FALSE | AC34: FALSE | AD34: 2 | AE34: 1 | AF34: completed | AG34: 172748 | AH34: 7165 | AK34: 79036bd8-09a6-44ef-a84d-8985ace5476e
A35: 2a63059e | B35: Regenerated today - outline now present (first run was empty context, second run healthy) | C35: APPROVE to generating_prompt. Strip the summary/meta bullets first. | D35: 2 summary bullets at the top (tab list, hardcode list) before the build steps; strip them. Decomper prior: 86% of their SOTA-scored tasks came back too easy (n=28). | E35: 16 bullets, 5820 chars. Last run 201,784 in / 7,610 out. | F35: A1_no_outline | G35: wangche2532@gmail.com | H35: 0.857 | I35: 28 | J35: 46266.916 | K35: 0.1 | L35: 2 | M35: 3 | N35: 1 | O35: ali@meridian.ai | P35: TRUE | Q35: 5820 | S35: 16 | T35: 57 | U35: 1009 | V35: FALSE | W35: 08.31_63 N-4.xlsx | X35: 415 | Y35: 08.31_63 N-3.xlsx | Z35: 450 | AA35: FALSE | AB35: FALSE | AC35: FALSE | AD35: 2 | AE35: 1 | AF35: completed | AG35: 201784 | AH35: 7610 | AK35: 2a63059e-b08b-495f-90df-23bb38eccd3f
A36: 8c19520c | B36: Regenerated today - outline now present (first run was empty context, second run healthy) | C36: APPROVE to generating_prompt. | D36: Decomper prior: 86% of their SOTA-scored tasks came back too easy (n=28). | E36: 14 bullets, 5089 chars. Last run 523,608 in / 11,560 out. | F36: A1_no_outline | G36: wangche2532@gmail.com | H36: 0.857 | I36: 28 | J36: 46266.92 | K36: 0.1 | L36: 2 | M36: 3 | N36: 1 | O36: ali@meridian.ai | P36: TRUE | Q36: 5089 | S36: 14 | T36: 302 | U36: 950 | V36: FALSE | W36: 08.30_21 N-4.xlsx | X36: 996 | Y36: 08.30_21 N-3.xlsx | Z36: 1310 | AA36: FALSE | AB36: FALSE | AC36: FALSE | AD36: 2 | AE36: 1 | AF36: completed | AG36: 523608 | AH36: 11560 | AK36: 8c19520c-b2d2-449b-a1f8-b426e81df053
A37: 95606585 | B37: Regenerated twice today (failed loudly at 22:59, succeeded at 00:02) - outline now 7449 chars (was 7398) | C37: APPROVE to generating_prompt. Strip the summary/meta bullets first. | D37: 2 meta bullets at the top ("input_workbook_url = earlier = less built"); strip them. Output workbook is smaller than input (395KB vs 440KB), unusual for a forward build. Decomper prior: 86% of their SOTA-scored tasks came back too easy (n=28). | E37: 15 bullets, 7449 chars. Last run 395,365 in / 10,629 out. | F37: C_truncated_outline | G37: wangche2532@gmail.com | H37: 0.857 | I37: 28 | J37: 46266.958 | K37: 0 | L37: 2 | M37: 4 | N37: 1 | O37: ali@meridian.ai | P37: TRUE | Q37: 7449 | R37: 7398 | S37: 15 | T37: 123 | U37: 800 | V37: FALSE | W37: 08.31_44 N-4.xlsx | X37: 441 | Y37: 08.31_44 N-3.xlsx | Z37: 396 | AA37: FALSE | AB37: TRUE | AC37: FALSE | AD37: 2 | AE37: 1 | AF37: completed | AG37: 395365 | AH37: 10629 | AK37: 95606585-8665-475b-ac9c-eb5fae04a8f6
A38: 1ef09f14 | B38: Regenerated today - outline now present (first run was empty context, second run healthy) | C38: APPROVE to generating_prompt. | E38: 19 bullets, 7866 chars. Last run 80,859 in / 5,771 out. | F38: A1_no_outline | G38: sophie.xiao@toptal.com | H38: 0 | I38: 8 | J38: 46266.916 | K38: 0.1 | L38: 2 | M38: 3 | N38: 1 | O38: ali@meridian.ai | P38: TRUE | Q38: 7866 | S38: 19 | T38: 51 | U38: 681 | V38: FALSE | W38: 08.31_50 N-1.xlsx | X38: 451 | Y38: 08.31_50.xlsx | Z38: 932 | AA38: FALSE | AB38: FALSE | AC38: FALSE | AD38: 2 | AE38: 1 | AF38: completed | AG38: 80859 | AH38: 5771 | AK38: 1ef09f14-3119-434f-b561-884e196c6caa
A39: 40827f51 | B39: Regenerated twice today (failed loudly at 22:59, succeeded at 00:02) - outline now 9279 chars (was 2052) | C39: APPROVE to generating_prompt. | E39: 14 bullets, 9279 chars. Last run 111,708 in / 5,540 out. | F39: B_thin_outline | G39: apathy@uchicago.edu | H39: 0.556 | I39: 9 | J39: 46266.957 | K39: 0 | L39: 2 | M39: 4 | N39: 1 | O39: ali@meridian.ai | P39: TRUE | Q39: 9279 | R39: 2052 | S39: 14 | T39: 15 | U39: 661 | V39: FALSE | W39: 08.31_21-N-2.xlsx | X39: 27 | Y39: 08.31_21-N-1.xlsx | Z39: 45 | AA39: FALSE | AB39: FALSE | AC39: FALSE | AD39: 2 | AE39: 1 | AF39: completed | AG39: 111708 | AH39: 5540 | AK39: 40827f51-9058-4a34-aa53-cffedf1af118
A40: 8f99bcd7 | B40: New arrival - first visit, healthy agent run, outline present | C40: APPROVE to generating_prompt. | D40: Decomper prior: 100% of their SOTA-scored tasks came back too easy (n=4). | E40: 16 bullets, 6592 chars. Last run 152,153 in / 5,778 out. | F40: NEW (arrived after the triage snapshot) | G40: mshuriah2702@gmail.com | H40: 1 | I40: 4 | J40: 46266.973 | K40: 0 | L40: 1 | M40: 2 | N40: 0 | P40: TRUE | Q40: 6592 | S40: 16 | T40: 21 | U40: 638 | V40: FALSE | W40: 08.31_116 N-7.xlsx | X40: 766 | Y40: 08.31_116 N-6.xlsx | Z40: 805 | AA40: FALSE | AB40: FALSE | AC40: FALSE | AD40: 1 | AE40: 0 | AF40: completed | AG40: 152153 | AH40: 5778 | AK40: 8f99bcd7-fca6-4752-bf71-04ad795bf50d
A41: 29ea5ad8 | B41: Regenerated today - outline now present (first run was empty context, second run healthy) | C41: APPROVE to generating_prompt. | D41: Decomper prior: 86% of their SOTA-scored tasks came back too easy (n=28). | E41: 31 bullets, 10095 chars. Last run 325,845 in / 7,793 out. | F41: A1_no_outline | G41: wangche2532@gmail.com | H41: 0.857 | I41: 28 | J41: 46266.916 | K41: 0.1 | L41: 2 | M41: 3 | N41: 1 | O41: ali@meridian.ai | P41: TRUE | Q41: 10095 | S41: 31 | T41: 118 | U41: 635 | V41: FALSE | W41: 08.30_50 N-3.xlsx | X41: 92 | Y41: 08.30_50 N-2.xlsx | Z41: 102 | AA41: FALSE | AB41: FALSE | AC41: FALSE | AD41: 2 | AE41: 1 | AF41: completed | AG41: 325845 | AH41: 7793 | AK41: 29ea5ad8-04b1-4dc4-8220-ae9df37ae12d
A42: f09e7718 | B42: New arrival - first visit, healthy agent run, outline present | C42: APPROVE to generating_prompt. | D42: Decomper prior: 100% of their SOTA-scored tasks came back too easy (n=4). | E42: 22 bullets, 5638 chars. Last run 142,290 in / 6,764 out. | F42: NEW (arrived after the triage snapshot) | G42: mshuriah2702@gmail.com | H42: 1 | I42: 4 | J42: 46266.972 | K42: 0 | L42: 1 | M42: 2 | N42: 0 | P42: TRUE | Q42: 5638 | S42: 22 | T42: 18 | U42: 565 | V42: FALSE | W42: 08.31_116 N-5.xlsx | X42: 814 | Y42: 08.31_116 N-4.xlsx | Z42: 835 | AA42: FALSE | AB42: FALSE | AC42: FALSE | AD42: 1 | AE42: 0 | AF42: completed | AG42: 142290 | AH42: 6764 | AK42: f09e7718-c4bf-4bb1-964a-5a914acc6ee4
A43: 4073b29f | B43: Regenerated today - outline now present (first run was empty context, second run healthy) | C43: APPROVE to generating_prompt. | D43: Decomper prior: 100% of their SOTA-scored tasks came back too easy (n=2). | E43: 25 bullets, 10237 chars. Last run 550,448 in / 11,856 out. | F43: A1_no_outline | G43: nimisha.mekala2021@gmail.com | H43: 1 | I43: 2 | J43: 46266.918 | K43: 0.1 | L43: 2 | M43: 3 | N43: 1 | O43: ali@meridian.ai | P43: TRUE | Q43: 10237 | S43: 25 | T43: 214 | U43: 467 | V43: TRUE | W43: MFESC_-_Model.redacted-hygiene_N-1.xlsx | X43: 1409 | Y43: MFESC_-_Model.redacted-hygiene_N.xlsx | Z43: 1417 | AA43: FALSE | AB43: FALSE | AC43: FALSE | AD43: 2 | AE43: 1 | AF43: completed | AG43: 550448 | AH43: 11856 | AJ43: 1197babd-28a8-42f6-a8f4-de30e057789e | AK43: 4073b29f-25e1-4432-8bf5-0b7c4be497db
A44: d75d1c87 | B44: New arrival - first visit, healthy agent run, outline present | C44: APPROVE to generating_prompt. Strip the summary/meta bullets first. | D44: 2 summary bullets at the top (NEW tab / Modified tabs list) before the build steps; strip them. Decomper prior: 100% of their SOTA-scored tasks came back too easy (n=4). | E44: 9 bullets, 7338 chars. Last run 992,393 in / 18,689 out. | F44: NEW (arrived after the triage snapshot) | G44: mshuriah2702@gmail.com | H44: 1 | I44: 4 | J44: 46266.973 | K44: 0 | L44: 1 | M44: 2 | N44: 0 | P44: TRUE | Q44: 7338 | S44: 9 | T44: 583 | U44: 458 | V44: TRUE | W44: 08.31_116 N-1.xlsx | X44: 980 | Y44: 08.31_116.xlsx | Z44: 996 | AA44: FALSE | AB44: FALSE | AC44: FALSE | AD44: 1 | AE44: 0 | AF44: completed | AG44: 992393 | AH44: 18689 | AJ44: 64a502f4-bd86-4ae1-b889-8547eedfd676 | AK44: d75d1c87-cc80-461b-a894-47ea156cad3f
A45: f776f992 | B45: Regenerated today - outline now present (first run was empty context, second run healthy) | C45: APPROVE to generating_prompt. | D45: 397 unique formulas; cash flow and loan runoff, real logic. Moderate. | E45: 13 bullets, 5294 chars. Last run 60,334 in / 3,964 out. | F45: A1_no_outline | G45: infinitearbitrage@gmail.com | H45: 0.875 | I45: 16 | J45: 46266.916 | K45: 0.1 | L45: 2 | M45: 3 | N45: 1 | O45: ali@meridian.ai | P45: TRUE | Q45: 5294 | S45: 13 | T45: 59 | U45: 397 | V45: FALSE | W45: 08.31_39 N-2.xlsx | X45: 273 | Y45: 08.31_39 N-1.xlsx | Z45: 288 | AA45: FALSE | AB45: FALSE | AC45: FALSE | AD45: 2 | AE45: 1 | AF45: completed | AG45: 60334 | AH45: 3964 | AK45: f776f992-cd34-452b-adfe-e65148c3c247
A46: 87a8cf29 | B46: Regenerated today - outline now present (first run was empty context, second run healthy) | C46: APPROVE to generating_prompt. | D46: 340 unique formulas; four output tabs that are almost entirely direct links. Too-easy risk. | E46: 11 bullets, 5682 chars. Last run 241,183 in / 8,920 out. | F46: A1_no_outline | G46: apathy@uchicago.edu | H46: 0.556 | I46: 9 | J46: 46266.917 | K46: 0.1 | L46: 2 | M46: 3 | N46: 1 | O46: ali@meridian.ai | P46: TRUE | Q46: 5682 | S46: 11 | T46: 90 | U46: 340 | V46: FALSE | W46: fa9-N-2.xlsx | X46: 1129 | Y46: fa9-N-1.xlsx | Z46: 1142 | AA46: FALSE | AB46: FALSE | AC46: FALSE | AD46: 2 | AE46: 1 | AF46: completed | AG46: 241183 | AH46: 8920 | AK46: 87a8cf29-f488-4921-98df-9fbb785aa0b0
A47: fdfd6024 | B47: New arrival - first visit, healthy agent run, outline present | C47: APPROVE to generating_prompt. | D47: 265 unique formulas; output blocks that are link pulls and simple ratios. Too-easy risk. | E47: 17 bullets, 6067 chars. Last run 101,233 in / 6,225 out. | F47: NEW (arrived after the triage snapshot) | G47: mshuriah2702@gmail.com | H47: 1 | I47: 4 | J47: 46266.973 | K47: 0 | L47: 1 | M47: 2 | N47: 0 | P47: TRUE | Q47: 6067 | S47: 17 | T47: 730 | U47: 265 | V47: FALSE | W47: 08.31_116 N-6.xlsx | X47: 805 | Y47: 08.31_116 N-5.xlsx | Z47: 814 | AA47: FALSE | AB47: FALSE | AC47: FALSE | AD47: 1 | AE47: 0 | AF47: completed | AG47: 101233 | AH47: 6225 | AK47: fdfd6024-51d6-49c8-93c8-39d033b1bd8d
A48: f7e83778 | B48: Regenerated today - outline now present (first run was empty context, second run healthy) | C48: APPROVE to generating_prompt. | D48: 232 unique formulas; acquisition-assumptions block plus a cloned debt schedule. Too-easy risk. | E48: 14 bullets, 6773 chars. Last run 218,468 in / 7,875 out. | F48: A1_no_outline | G48: wangche2532@gmail.com | H48: 0.857 | I48: 28 | J48: 46266.917 | K48: 0.1 | L48: 2 | M48: 3 | N48: 1 | O48: ali@meridian.ai | P48: TRUE | Q48: 6773 | S48: 14 | T48: 129 | U48: 232 | V48: FALSE | W48: 08.31_44 N-2.xlsx | X48: 421 | Y48: 08.31_44 N-1.xlsx | Z48: 437 | AA48: FALSE | AB48: FALSE | AC48: FALSE | AD48: 2 | AE48: 1 | AF48: completed | AG48: 218468 | AH48: 7875 | AK48: f7e83778-a8c1-4c8a-a43a-f2c40548cdf6
A49: 018939a8 | B49: Regenerated twice today (failed loudly at 22:59, succeeded at 00:02) - outline now 5807 chars (was 6523) | C49: APPROVE to generating_prompt. | D49: 198 unique formulas, but a genuine DCF + WACC build with data tables. Moderate. | E49: 15 bullets, 5807 chars. Last run 87,390 in / 3,542 out. | F49: D_thin_transition | G49: apathy@uchicago.edu | H49: 0.556 | I49: 9 | J49: 46266.956 | K49: 0 | L49: 2 | M49: 4 | N49: 1 | O49: ali@meridian.ai | P49: TRUE | Q49: 5807 | R49: 6523 | S49: 15 | T49: 17 | U49: 198 | V49: TRUE | W49: 08.31_21-N-1.xlsx | X49: 45 | Y49: 08.31_21-N-0.xlsx | Z49: 55 | AA49: FALSE | AB49: FALSE | AC49: FALSE | AD49: 2 | AE49: 0 | AF49: completed | AG49: 87390 | AH49: 3542 | AJ49: 8fcddd24-23ed-44f3-bd64-0a632be28688 | AK49: 018939a8-5f2a-46e7-9f5b-309a20147f37
A50: 5a1f3794 | B50: Regenerated twice today (failed loudly at 22:59, succeeded at 00:02) - outline now 7117 chars (was 194) | C50: APPROVE to generating_prompt. | D50: 180 unique formulas; mostly ratio rows and a small valuation-views tab. Too-easy risk. | E50: 15 bullets, 7117 chars. Last run 93,690 in / 5,995 out. | F50: B_thin_outline | G50: wangche2532@gmail.com | H50: 0.857 | I50: 28 | J50: 46266.957 | K50: 0 | L50: 2 | M50: 4 | N50: 1 | O50: ali@meridian.ai | P50: TRUE | Q50: 7117 | R50: 194 | S50: 15 | T50: 130 | U50: 180 | V50: FALSE | W50: 08.30_38 N-2.xlsx | X50: 225 | Y50: 08.30_38 N-1.xlsx | Z50: 233 | AA50: FALSE | AB50: FALSE | AC50: FALSE | AD50: 2 | AE50: 1 | AF50: completed | AG50: 93690 | AH50: 5995 | AK50: 5a1f3794-1251-431a-b97d-4cf2107ffed8
A51: 3d458c2a | B51: Regenerated today - outline now present (first run was empty context, second run healthy) | C51: APPROVE to generating_prompt. | D51: Mechanical: Dynamo import header rows and direct cell links, 131 unique formulas. High Foundational risk. | E51: 12 bullets, 6602 chars. Last run 75,099 in / 5,726 out. | F51: A1_no_outline | G51: apathy@uchicago.edu | H51: 0.556 | I51: 9 | J51: 46266.916 | K51: 0.1 | L51: 2 | M51: 3 | N51: 1 | O51: ali@meridian.ai | P51: TRUE | Q51: 6602 | S51: 12 | T51: 69 | U51: 131 | V51: TRUE | W51: bbe-N-1.xlsx | X51: 981 | Y51: bbe-N-0.xlsx | Z51: 986 | AA51: FALSE | AB51: FALSE | AC51: FALSE | AD51: 2 | AE51: 1 | AF51: completed | AG51: 75099 | AH51: 5726 | AJ51: b8b1b057-079f-4115-9bfc-a24d646eca43 | AK51: 3d458c2a-cfe5-4a22-9f35-1c48780f5a38

Sheet No-outline detail
A1: Task | B1: Decomper | C1: Input workbook | D1: Input KB | E1: Output workbook | F1: Output KB | G1: Largest > 4MB | H1: Unique formulas | I1: Agent runs | J1: Empty-context runs | K1: Run times (UTC) and tokens in/out | L1: Transition description (what the decomper removed) | M1: Recommended action | N1: Task ID
A2: 7215fd35 | B2: alec.tseung@toptal.com | C2: 08.27_139_N-3.xlsx | D2: 4614 | E2: 08.27_139_N-2.xlsx | F2: 6417 | G2: TRUE | H2: 220747 | I2: 2 | J2: 2 | K2: 2026-09-01T18:22 completed 5392/1 | 2026-09-01T21:57 completed 5384/1 | L2: Cleared formulae across Provider Summary, P&L Summary, QE2 Provider by Modality, QE5b Provider Comp, Industry Benchmark Source, Management Fee, Physician Detail, CSC Vol & Fin Inputs, BCSC Vol & Fin Inputs, and IT Amounts tabs | M2: HOLD. Do not re-run. Workbook is over 4MB and has failed 2 of 2 runs (5,38x input tokens = workbook never loaded). Needs an engineering fix to the outline agent, or a manual outline. | N2: 7215fd35-f477-44af-b6f1-b38348ebe264
A3: 3d3b229e | B3: alec.tseung@toptal.com | C3: 08.27_139_N-5.xlsx | D3: 4162 | E3: 08.27_139_N-4.xlsx | F3: 4446 | G3: TRUE | H3: 22547 | I3: 2 | J3: 2 | K3: 2026-09-01T18:32 completed 5391/4 | 2026-09-01T21:57 completed 5387/7 | L3: Cleared remaining formulae in the workbook | M3: HOLD. Do not re-run. Workbook is over 4MB and has failed 2 of 2 runs (5,38x input tokens = workbook never loaded). Needs an engineering fix to the outline agent, or a manual outline. | N3: 3d3b229e-0507-4539-8343-193a679d5f5c
A4: 337252e6 | B4: alec.tseung@toptal.com | C4: 08.27_139_N-2.xlsx | D4: 6417 | E4: 08.27_139_N-1.xlsx | F4: 6852 | G4: TRUE | H4: 17725 | I4: 2 | J4: 2 | K4: 2026-09-01T18:17 completed 5389/4 | 2026-09-01T21:57 completed 5387/1 | L4: Cleared formulae across the key calculation tabs of the model | M4: HOLD. Do not re-run. Workbook is over 4MB and has failed 2 of 2 runs (5,38x input tokens = workbook never loaded). Needs an engineering fix to the outline agent, or a manual outline. | N4: 337252e6-80dc-4b36-b284-7b83b4e5617f
A5: 8a8066ff | B5: alec.tseung@toptal.com | C5: 08.27_139_N-4.xlsx | D5: 4446 | E5: 08.27_139_N-3.xlsx | F5: 4614 | G5: TRUE | H5: 14594 | I5: 2 | J5: 2 | K5: 2026-09-01T18:27 completed 5390/1 | 2026-09-01T21:57 completed 5390/5 | L5: Cleared formulae mainly across Fin Stage, Monthly TB - Entity, Adjustments Base Case/Valuation, Integrated Valuation, INT|MSO, 6. Int – MSO, 8. R&M tabs | M5: HOLD. Do not re-run. Workbook is over 4MB and has failed 2 of 2 runs (5,38x input tokens = workbook never loaded). Needs an engineering fix to the outline agent, or a manual outline. | N5: 8a8066ff-7624-4fc5-981f-52a666b28967
A6: 906892cf | B6: infinitearbitrage@gmail.com | C6: 08.29_117 N-5.xlsx | D6: 7602 | E6: 08.29_117 N-4.xlsx | F6: 7682 | G6: TRUE | H6: 1847 | I6: 2 | J6: 2 | K6: 2026-09-01T10:24 completed 5385/1 | 2026-09-01T21:57 completed 5386/4 | L6: maintenance analysis tab entirely and bandwidth tab and ratio tab with its dependent cells | M6: HOLD. Do not re-run. Workbook is over 4MB and has failed 2 of 2 runs (5,38x input tokens = workbook never loaded). Needs an engineering fix to the outline agent, or a manual outline. | N6: 906892cf-1049-4c2d-99ef-404e461c776f
A7: 25613ef5 | B7: wangche2532@gmail.com | C7: 08.30_48 N-6.xlsx | D7: 406 | E7: 08.30_48 N-5.xlsx | F7: 481 | G7: FALSE | H7: 8528 | I7: 2 | J7: 2 | K7: 2026-09-01T13:25 completed 5389/1 | 2026-09-01T21:57 completed 5391/4 | L7: Delete tabs: INT - Incr Vol Build, Deprec. Calc, Calculator, Summary Output, 4. Profile Clear content: 'INT - P&L'!A18:BF281, 'INT - Val & Returns'!A3:PK113, Amortization!A15:CE236, Inputs!A2:AE54 | M7: Regenerate outline once more. File is small (405KB / 481KB) and has had 2 empty run(s); if it keeps failing treat like the large-file cases. | N7: 25613ef5-50aa-4ab2-b49a-4ea4b4dc519a
A8: 437756ce | B8: wangche2532@gmail.com | C8: 08.31_47 N-2.xlsx | D8: 250 | E8: 08.31_47 N-1.xlsx | F8: 260 | G8: FALSE | H8: 211 | I8: 1 | J8: 1 | K8: 2026-09-02T00:01 completed 5391/1 | L8: Delete tabs: Northstar Partners Cash Flow & Clear content: Inputs & Assumptions!F74:K78, Inputs & Assumptions!D80:K99 | M8: Regenerate outline once more. File is small (249KB / 259KB) and has had 1 empty run(s); if it keeps failing treat like the large-file cases. | N8: 437756ce-b81b-403d-8a2d-be439ba78b4a
A10: Why "empty context": a healthy outline run reads the two workbooks and shows 60k-1.8M input tokens. These runs show ~5,384 input tokens and 1-7 output tokens: the prompt scaffolding with no workbook attached. The agent still reports status=completed, the python step strips the non-bullet output to nothing, and the backfill writes an empty task_outline.
A11: Size evidence (all sheets tasks since 08-26, from Metabase): empty-run share is 12% under 1MB, 24% at 1-2MB, 30% at 2-4MB, 32% at 4-6MB, 38% over 6MB. In this queue every >4MB task failed both attempts.

Sheet Outlines
A1: Task | B1: Recommended action | C1: Decomper | D1: Unique formulas | E1: Outline chars | F1: Transition description | G1: Task outline (as stored) | H1: Task ID
A2: 7215fd35 | B2: HOLD. Do not re-run. Workbook is over 4MB and has failed 2 of 2 runs (5,38x input tokens = workbook never loaded). Needs an engineering fix to the outline agent, or a manual outline. | C2: alec.tseung@toptal.com | D2: 220747 | E2: 0 | F2: Cleared formulae across Provider Summary, P&L Summary, QE2 Provider by Modality, QE5b Provider Comp, Industry Benchmark Source, Management Fee, Physician Detail, CSC Vol & Fin Inputs, BCSC Vol & Fin Inputs, and IT Amounts tabs | H2: 7215fd35-f477-44af-b6f1-b38348ebe264
A3: 3d3b229e | B3: HOLD. Do not re-run. Workbook is over 4MB and has failed 2 of 2 runs (5,38x input tokens = workbook never loaded). Needs an engineering fix to the outline agent, or a manual outline. | C3: alec.tseung@toptal.com | D3: 22547 | E3: 0 | F3: Cleared remaining formulae in the workbook | H3: 3d3b229e-0507-4539-8343-193a679d5f5c
A4: 337252e6 | B4: HOLD. Do not re-run. Workbook is over 4MB and has failed 2 of 2 runs (5,38x input tokens = workbook never loaded). Needs an engineering fix to the outline agent, or a manual outline. | C4: alec.tseung@toptal.com | D4: 17725 | E4: 0 | F4: Cleared formulae across the key calculation tabs of the model | H4: 337252e6-80dc-4b36-b284-7b83b4e5617f
A5: 8a8066ff | B5: HOLD. Do not re-run. Workbook is over 4MB and has failed 2 of 2 runs (5,38x input tokens = workbook never loaded). Needs an engineering fix to the outline agent, or a manual outline. | C5: alec.tseung@toptal.com | D5: 14594 | E5: 0 | F5: Cleared formulae mainly across Fin Stage, Monthly TB - Entity, Adjustments Base Case/Valuation, Integrated Valuation, INT|MSO, 6. Int – MSO, 8. R&M tabs | H5: 8a8066ff-7624-4fc5-981f-52a666b28967
A6: 906892cf | B6: HOLD. Do not re-run. Workbook is over 4MB and has failed 2 of 2 runs (5,38x input tokens = workbook never loaded). Needs an engineering fix to the outline agent, or a manual outline. | C6: infinitearbitrage@gmail.com | D6: 1847 | E6: 0 | F6: maintenance analysis tab entirely and bandwidth tab and ratio tab with its dependent cells | H6: 906892cf-1049-4c2d-99ef-404e461c776f
A7: 25613ef5 | B7: Regenerate outline once more. File is small (405KB / 481KB) and has had 2 empty run(s); if it keeps failing treat like the large-file cases. | C7: wangche2532@gmail.com | D7: 8528 | E7: 0 | F7: Delete tabs: INT - Incr Vol Build, Deprec. Calc, Calculator, Summary Output, 4. Profile Clear content: 'INT - P&L'!A18:BF281, 'INT - Val & Returns'!A3:PK113, Amortization!A15:CE236, Inputs!A2:AE54 | H7: 25613ef5-50aa-4ab2-b49a-4ea4b4dc519a
A8: 437756ce | B8: Regenerate outline once more. File is small (249KB / 259KB) and has had 1 empty run(s); if it keeps failing treat like the large-file cases. | C8: wangche2532@gmail.com | D8: 211 | E8: 0 | F8: Delete tabs: Northstar Partners Cash Flow & Clear content: Inputs & Assumptions!F74:K78, Inputs & Assumptions!D80:K99 | H8: 437756ce-b81b-403d-8a2d-be439ba78b4a
A9: a5f013b8 | B9: APPROVE to generating_prompt. | C9: apathy@uchicago.edu | D9: 20166 | E9: 12065 | F9: Cleared Pro Forma, D&A & Debt Schedules, DCF & IRR, Intangible Asset Amortization, Physician Inputs, Volume & Financial Inputs, Inputs & Assumptions, Valuation Assumptions. | G9: - Build the Volume & Financial Inputs tab as the historical TTM aggregator: create the FY/YTD/TTM column headers with the reporting date pulled from Inputs & Assumptions!E14, then pull each P&L line (Net Patient Revenue, Other Revenue, Supplies, SWB, Other Variable Direct/Indirect, Rent, Other Fixed, Bad Debt, Mgmt Fees, Depreciation, Interest, Other Expense/Income, UL and FL facility cash) from the corresponding TTM Dec17 and Apr18 TTM cells, and compute TTM = FY − YTD + partial-year, with EBITDA and Net Income subtotals plus OK/CHECK reconciliations against the sums. Add a Surgical Cases row linked from MD Summary Center and Physician Inputs, then a per-case metrics block dividing each cost/revenue line by cases for FY, partial-year, and TTM columns. - Build the Physician Inputs tab: (a) a KPIs & Volume by Physician block with monthly columns whose dates roll back from Inputs & Assumptions!E14 via EOMONTH, physician names pulled from MD Summary Center rows 6–79, monthly volumes pulled from MD Summary Center columns L–W, a TTM volume SUM across the 12 months, and a TTM Revenue column computed as NPR/Case × TTM volume; (b) a Total row using SUBTOTAL(109,...) and a per-IS tie-out to Volume & Financial Inputs!K37 and K11; (c) a KPIs & Volume by Specialty block using COUNTIF to count MDs and SUMIF to aggregate the monthly and TTM volumes/revenues by specialty, with a total row; (d) a Center Specific Seasonality block that MONTHs each column header, uses INDEX/MATCH against the Working Days Database to fetch working days per month, computes volume/day, then computes seasonality index vs. TTM average; (e) populate the month-date column B in the Working Days Database (rows 115–270) via EOMONTH stepping from a January-2014 seed while leaving the working-day counts already in column C intact. - On the Inputs & Assumptions tab, extend the CapEx schedule row (E95:I95) so year 1 pulls from Volume & Financial Inputs!K26 and each subsequent year references the prior year, and add the SUM total row (E97:I97); wire Modeled Year 1 Non-Compete and Mgmt Agmt amortization inputs to the Intangible Asset Amortization outputs (B22 and B20). - Build the Intangible Asset Amortization tab: pull Year 1 Revenue, EBIT (= EBITDA − Modeled Year 1 Dep), and Estimated Mgmt Fees from Pro Forma column CD; pull growth rate, discount rate, and tax rate from DCF & IRR; pull non-compete term from Inputs & Assumptions!E107 and Mgmt Expense per center from Inputs & Assumptions!G79. Add hardcodes: probability-adjusted impact of competition (increase from 15% to 25%), synergy discount rate override IF(B8=14%,20%,18%), and multipliers 0.85 and 1/3. Compute Management Agreement value as (($B$6*B12/3)*(1-$B$9))/(1+$D$8)*0.85 and Non-Compete value as ((($B$5*$B$11)*(1-$B$9))/($B$8-$B$7))*(1-((1+$B$7)/(1+$B$8))^$B$10)*(1+$D$8)*0.85; divide each by its life (from Inputs & Assumptions E110 and E107) to get amortization/year, then total and add an OK/CHECK against the D&A & Debt Schedules amortization row. - Build the D&A & Debt Schedules tab: (a) an assumptions block that pulls TTM Dep and Post-Close Dep from Inputs & Assumptions rows 102/103, non-compete and mgmt-agmt amortization amounts and lives from Inputs & Assumptions rows 106/107/109/110, and Facility Debt and Capital Lease terms from Inputs & Assumptions rows 114–119 and J114–J119, including a payment computed via −PMT(rate/12,months,principal,0) when terms = "Principal & Interest" and an "In Use?" flag = D29>0; (b) a monthly time header (H:CA) that references Pro Forma row 1/2/3/4; (c) monthly rows for CapEx (HLOOKUP against Inputs & Assumptions!$E$94:$I$97), Pre-Close and Post-Close Existing Depreciation, straight-line Depreciation on New Assets from the cumulative CapEx / period, Post-Close Amortization = non-compete/life/12 + mgmt-agmt/life/12, a fully-depreciated write-off via SUMIF against the CapEx history offset by the depreciation period, and Total D&A summing rows 8–12; (d) a Facility Debt amortization roll (Starting = prior Ending, Principal = MAX(Payment−Interest,0), Interest = rate/12 × Starting, Ending = Start−Principal); (e) a Capital Lease schedule with an escalating annual payment (=$D$34*POWER(1+$D$33,ceil(month/12)−1)) capped by starting balance, plus Straight-line Depreciation = Principal/Term. - Build the Pro Forma tab spine: header rows for month date (F4:BY4 via EOMONTH from Inputs & Assumptions!E14), year label (row 3 = YEAR), Post-Close period counter (row 2 = "Pre-Close" until the close date then E2+1), and year-of-close index (row 1 = ROUNDUP(period/12,0)). Add a right-side summary block: Avg TTM Month column (E), TTM totals column (CC) pulling from Volume & Financial Inputs, annual roll-up columns CD:CH using SUMIFS by row 1 year index, a CAGR column (CI) using POWER(CH/CC,1/5)−1, a Calendar Year block (CM:CT) linked directly to Volume & Financial Inputs plus CO = CN+1 propagation, and a Stub Periods block (CW:CY) built as TTM anchor from Volume & Financial Inputs!I column, YTD-to-Close as SUMIFS where row 2 = "Pre-Close" AND row 3 = YEAR(close), and Close-Dec as SUMIFS where row 3 = YEAR(close) AND row 2 > 0. - Build the Pro Forma Volume & Contribution Build section (rows 5–41): Base Cases from prior month × (1 + Organic Case Growth), Base Revenue/Supplies/SWB per Case each rolled from prior period × (1 + organic and inorganic growth pulled via SUMIFS against Inputs & Assumptions growth grids in rows 33–36 and 83–89); Decremental and Incremental cases/revenue/supplies/SWB via SUMIFS against Inputs & Assumptions rows 40–56 (matched on row 2 period); Total Cases/Revenue/Supplies/SWB summing base + inc + dec; Working Days adjustment via VLOOKUP into Physician Inputs Working Days Database controlled by an ON/OFF switch, Seasonality adjustment (SUMIF into Physician Inputs seasonality row) also switch-controlled, and Total Adjusted Cases = Total × (1+WD) × (1+Seasonality). - Build the Pro Forma monthly P&L (rows 43–58): Surgical Cases = adjusted cases, Surgical Revenue = cases × NPR/Case, Other Revenue = prior × (1 + Other Revenue growth from Inputs & Assumptions row 36), Supplies/SWB/Variable Direct = cases × per-case, Variable Indirect/Rent/Fixed = prior × (1 + growth from Inputs & Assumptions rows 83–89) with Rent zeroed when lease is Capital, Bad Debt = Revenue × Bad Debt %, RBO Fee = Inputs & Assumptions!E73 × (Revenue − Bad Debt) suppressed pre-close, Integration Expenses = Inputs & Assumptions!E76 for months ≤ E76 cutoff, EBITDAM = Revenue − sum(costs). - Build the Pro Forma Management Fee scenario block (rows 60–70): three scenario rows pulling scenario names from Inputs & Assumptions rows 69–71, monthly fee formulas per scenario (Scenario 1 = fee% × (Surgical Revenue − Bad Debt); Scenario 2 = MIN(Scenario 1, cap × POWER(1+esc, year−1) minus prior YTD); Scenario 3 = fixed × POWER(1+esc, year−1)/12), % of NPR-BD and Northstar % of Fee driven via CHOOSE from Inputs & Assumptions row 66, Active Scenario = CHOOSE(scenario#, S1, S2, S3), Northstar Mgmt Fee = Active × Northstar%, Other Mgmt Fee = Active × (1−Northstar%), EBITDA = EBITDAM − mgmt fees. - Build the Pro Forma below-the-line rows (72–91): Depreciation & Amortization, Interest Expense (facility + cap-lease) linked from D&A & Debt Schedules, Other Expense held flat from TTM, Net Income = EBITDA − D&A − Interest − Other, NOPAT = (NI × Northstar% + (Mgmt Fee + Overhead)) × (1−tax); KPI block for per-case metrics (rows 80–86); Northstar/MD/Other equity % rows driven by pre-close vs. post-close columns of Inputs & Assumptions rows 8–10; Bad Debt % of NPR; and a Growth block (rows 94–102) computing year-over-year change for each KPI plus SUMIF pulls of Other Revenue, Variable Direct/Indirect, Rent, and Fixed growth from Inputs & Assumptions. - Build the Pro Forma Unlevered Cash Flow section (rows 105–117): EBITDA link, LESS Rent if Cap Lease (from D&A schedule row 31), LESS CapEx via HLOOKUP into Inputs & Assumptions capex row/12, LESS ∆WC placeholder, UL Facility Cash sum; then Northstar layer: Northstar Distributions = UL Cash × Northstar%, LESS Northstar Taxes on Facility Earnings = MIN(−(NI+Interest) × Northstar% × tax, 0), ADD Northstar Mgmt Fee, LESS Northstar Overhead = Inputs & Assumptions!G79/12 post-close, LESS Northstar Taxes on Mgmt Fee = MIN(−(Fee+Overhead) × tax, 0), UL AT Northstar Cash. - Build the Pro Forma Facility Levered Cash Flow section (rows 119–137): EBITDA − Debt Principal (facility and cap lease from D&A schedule rows 21/29) − Interest (rows 22/30) − CapEx − ∆WC = Facility Levered Cash, then MD/Other Distributions = FL Cash × their %; Northstar block mirrors the UL layer except taxes exclude Interest addback (uses only Net Income) — FL AT Northstar Cash sum. - Build the Pro Forma IOI/E-NCI section (rows 139–173): switch on Inputs & Assumptions!$E$12 = "Consolidated" vs. Equity to select the reporting basis; Consolidated IOI = EBITDA + Mgmt Fee − D&A, Equity IOI = Net Income − Non-Controlling Income + Mgmt Fee, both zeroed when Northstar % = 0 and suppressed pre-close; parallel Consolidated E-NCI = EBITDAM − Other Mgmt Fee − NCI and Equity E-NCI = AT Northstar Cash − NCI + Mgmt Fee; Pre-Overhead and Post-Overhead lines that add/subtract the Northstar Overhead row. - On the Valuation Assumptions tab, populate Multiple on Existing Fees (F9/Volume & Financial Inputs!K22), the Unlevered valuation column H (TTM EBITDA from Volume & Financial Inputs!K23 × Seller Multiple = EV, minus zero for existing debt/leases, times Northstar Equity % from Inputs & Assumptions!K8, plus Mgmt Fee Buyout and Deal Costs = Northstar Cash Outlay; Pro Rata Debt Assumption = 0; Total Capital Outlay), and the Facility Levered column J with the same structure except Existing Facility Debt and Capital Leases pulled from Inputs & Assumptions!E114 and J114 and Pro Rata Debt Assumption = Northstar % × (Debt + Leases). - Build the DCF & IRR tab Unlevered DCF (rows 5–32): assumption block pulling Income Tax from Inputs & Assumptions!E92, hardcoded Working Capital % = 2.5%, close date pulled from Inputs & Assumptions!E13, Discount Rate = 10%, Perpetuity Growth = 3%. Time header pulled from Pro Forma calendar-year block CO–CT with a Pre-Close/Close/Proj. classifier. Northstar AT Unlevered Cash pulled from Pro Forma row 117 across CO:CT, LESS ∆WC × Northstar %, Terminal Value in the final column = Cash × (1+g)/(r−g), Year Fraction via YEARFRAC to year-end capped at 1, Discount Period stepping (Close = YF/2, subsequent = prior + 1 half-year), PV Factor = 1/(1+r)^period, PV of CF and PV of TV, sum to Enterprise Value (Northstar Portion), LESS Northstar Debt from Valuation Assumptions!J35, Equity Value. - Build the DCF & IRR Unlevered IRR ladder (rows 34–42): a purchase-price row anchored at close date whose columns walk out one half-year then annual thereafter (DATE(YEAR(prior)+1,6,30)), five discount tiers (Current = −(Northstar Equity + Mgmt Fee Buyout) from Valuation Assumptions H30+H31, plus ±5% and ±10% and an At-LOI copy), each column populated via SUMIFS of the AT Unlevered Cash rows keyed on year (else grown by the perpetuity growth rate), and XIRR against the date row; add a DCF check row that compares implied XIRR to the discount rate. - Build the DCF & IRR Levered DCF and Levered IRR (rows 44–72) mirroring the Unlevered structure but pulling Northstar AT Levered Cash from Pro Forma row 137 and pricing Current from Valuation Assumptions J30+J31. - Build the DCF & IRR DCF Sensitivity two-way data table (rows 74–92): row headers = perpetuity growth ±0.5% around K9 (rows 78), column headers = discount rate ±1% around K8 (col D), with an Enterprise Value block and an E-NCI Multiple block that divides EV by Pro Forma!$CQ$159 to convert to multiple. - Build the DCF & IRR ROIC block (rows 94–105): year headers walking forward from YEAR(K7), NOPAT row pulled from Pro Forma row 77 (with a perpetuity extension via prior × (1+g)), and a matrix that divides cumulative NOPAT by each purchase-price scenario (−D101…−D105) to yield ROIC per year per price scenario. | H9: a5f013b8-ef14-4437-bea0-630504093c40
A10: 4f56a4bf | B10: APPROVE to generating_prompt. | C10: apathy@uchicago.edu | D10: 18080 | E10: 13635 | F10: Cleared BASE - Incr Vol Build, BASE - P&L, BASE - Val & Returns, INT - Incr Vol Build, INT - P&L, INT - Val & Returns, Amortization, Deprec. Calc, IT Amounts, Inputs, Calculator, Summary Output, 4. Profile. | G10: - On the "4. Profile" tab, add the facility-name banner cell in B1 as a pull from `'Vol & Fin Inputs'!B1` so the facility name flows through downstream tabs. - Build the "IT Amounts" reference table by adding the header row (Unit of Measure / Service Description / Unit Price / Verification), an annualized "Verification" column that multiplies each monthly per-unit price by 12 (with the local-server row carrying its own already-annualized figure), and a bundled-annual subtotal covering the facility/teammate/computer/mailbox/server/network/VPN lines. Then add a "One Time" section further down with subtotal formulas for Network Configuration (=SUM of firewall/switch/access-point/configuration line items, each computed as unit cost × quantity with quantities 1, 2, 5, 1), VoIP Vendor 001 Phone System (=SUM of two hardcoded components), Server Hardware/Support (=SUM of two components), Workstation (=SUM of workstation line = unit cost × 15), and HIPAA Assessment (=SUM), plus an aggregate one-time line "Ancellary Work" hardcoded as =2000+1000+1300. - Build the "Inputs" tab: add the header/labels block (title "Operating Model v2025.01", Facility Information section with Facility Name pulled from `'4. Profile'!B1`, Facility Address "Street 123", Group "Acela"). Add the Management Services Agreement Fee line calculated as `=AVERAGE('INT - P&L'!$AM$131:$AN$131)` with a floor-warning IF against the "Selected floor" cell that switches between 200000 / 250000 / 350000 based on the Calculator's framework selection (I7 = 1/2/3). Add the RCO Coding block (Estimated Annual Case Volume pulled as `=AVERAGE('INT - P&L'!$AM$44:$AN$44)`, Case Mix % rows for Cataract/Spine/Other/GI-Assisted/IP+Obs, a "Case Mix Total" =SUM check, an Estimated Coding Annual Cost driven by cases × case-mix % × rates per case type with rate table hardcodes 6.1 / 8.9 / 2.3 / 7.5 / 19.1, and a validation message when the mix doesn't equal 100%). Add the IT Expense block driving off `IT Amounts` unit prices — annual services grouped by Facility (flat fee), Teammate (× # teammates from D9), Computer (× # PCs), Mailbox (60/40 license split via M30=0.6 / O30=0.4 × teammates), VPN (10% adoption via M31=0.1 rounded up × teammates), Local Server (× # servers), and Network Vendor 001 Equipment (× 8 devices) — plus recurring Internet/Phone/VoIP Management pulled from IT Amounts, an Annual Cost total (=K34+K40) and a One-Time Cost total that sums the IT Amounts one-time subtotals. Include hardcoded facility defaults: # Teammates = 15, # PCs derived from teammates, # Servers = 2, New Phone System = 1, Operations Costs 30636, Finance Costs 20215, Risk Management 0. - Build the "Calculator" tab as the ASC services selection matrix: framework selector at I7 (values 1/2/3 = Standard / Standard + BD / Bundle), then rows per Support Service Lane (PAS & Claims Clearinghouse, HR sub-items including Time Keeping and Payroll, Accounting, Treasury, Tax, Risk Management, Supply Chain, Clinical sub-items, Marketing & Comms, Regulatory Compliance, Payer Engagement, RCO/CBO sub-items) with three columns of nested IFs mapping the selected option and framework tier to (J) Partnership annual cost, (K) Partnership one-time cost, and (L) MSA-included annual cost. Each row has an Option A/B/X selector at column D, an option-description echo at column I, and pass-through display columns F=J / G=K / H=L. Embed the pricing hardcodes: PAS Standard 32400; HR Standard 17448 (frameworks 1–2) / 27708 (framework 3); Time Keeping $6 per teammate per month; Time Keeping web app one-time 2000; Timeclock one-time 4915; Payroll $6.50 per teammate × 26 periods; Accounting Local 23900, Restricted 32700; Treasury MSA 2800 or Local 18000 annual + 300 one-time; Tax Standard 13460 annual + 22000 one-time; Clinical bundle 10000 MSA plus MCN 500/1000, RL Datix 800, SCT Core Compli 726, Survey Vendor 693, OAS CAHPS 3135, AORN 157; Marketing Templatized Website 2532 + 8500 one-time, Collaterals 500, Online Reputation 509 + 350 one-time, Monthly Optimization 1800, Website Improvements 2010; Regulatory Compliance 7000 MSA + 500 Extension of Practice; Payer Engagement Full Scope 31500. Then add the "Included in Framework" block with Operations pulling `Inputs!D12`, Finance pulling `Inputs!D13`, IT pulling `Inputs!D31` (annual) and `Inputs!H31` (one-time), Credentialing framework-3 driver = `Inputs!D10*31*12` annual and `Inputs!D10*30` one-time, and Business Development framework-1 = 43000. Add the "Sold Separately" block for Coding (pulls `Inputs!D24` when selected, else 5000 audit fallback), Credentialing (frameworks 1–2 pull provider-driven 31×12 / 30 costs, framework 3 zero), and Business Development (43000 when framework 1 selected). Close with grand totals F/G/H = SUM of all rows. - Build the "Summary Output" tab as the printable summary of Calculator selections. For each Support Service row (OM Framework, PAS & Claims Clearinghouse, HR, Accounting, Treasury, Tax, Risk Management, Supply Chain, Clinical, Marketing, Regulatory Compliance, Payer Engagement, RCO, Legal Platforms, Operational Dashboard, Operations, Finance, IT, Coding, Credentialing, Business Development): pull the description via CHOOSE against Calculator's selection index, and pull the annual/one-time/MSA columns via COUNTIF-guarded SUM ranges from Calculator (COUNTIF for "TBD" that short-circuits to "TBD" instead of a numeric sum). Sub-total row 29 sums D/E/F. Add the compliance check block: Management Services Agreement Fee pulled from `Inputs!D11` with a "BELOW MINIMUM FLOOR" warning against `Inputs!J12`, Total Services Costs = F29, Margin $ = fee − costs, Margin % with an "MARGIN DOES NOT MEET COMPLIANCE MINIMUM OF 20%" warning (hardcoded 0.2 threshold). - Build the "INT - P&L" tab (Integrated Case). Populate the Assumptions header (TTM Date, Close Date hardcoded 2/1/2027, Northstar Ownership 0.6, Accounting Treatment "Consolidated", stub-year YEARFRAC calc, "TTM" build start) and Long-Term Debt Assumptions (Principal 590000, Term 7 years, Rate 0, Payment=-PMT()). Build the forecast columns with monthly Norm-Date/Period counters starting January 2027. Populate the volume/revenue/cost stack: Existing Volume, Incremental Volume, working-day variance adjustment, Total Cases, Existing Net Patient Revenue pulled from `Vol & Fin Inputs`, NPR-per-case, Incremental NPR, Total NPR, Other Revenue, Total Revenue. Cost rows for Existing SWB, New SWB, Medical Supplies, Anesthesia, Other Variable Expense, Rent, Other Fixed, Bad Debt, and RBO Fee — each drawn from `Vol & Fin Inputs` for the base column and grown by per-case × total-cases logic in forecast columns. Add Base EBITDA, Less One-Time Integration Expense, Integrated EBITDAM, Integrated EBITDA, Depreciation/Amortization/Interest/Other Expense (from `Vol & Fin Inputs`), Facility Operating Earnings, Non-Controlling Interest, Northstar Mgmt. Fee, Northstar Overhead, and Pre-Tax Mgmt. Fee Profit lines with %-growth and %-margin ratios in each block. - Build the "INT - Incr Vol Build" tab as five specialty blocks that each carry monthly incremental cases (pulled from `Summary Vol Migration 6.5.26` blended-avg case counts / 12), incremental revenue, SWB, and supplies computed per-case × case count, growing forward on hardcoded growth-rate rows. Roll all five blocks into totals for Incremental Cases, Incremental NPR (with per-case and growth), Incremental SWB, Incremental Supplies, and Incremental Direct Margin (with per-case, % margin, and % growth). These totals become the Incremental Volume feed for the INT - P&L. - Build the "BASE - P&L" tab as the counterpart to INT - P&L for the Base Case, driving off the same `Vol & Fin Inputs` for existing volume/NPR/expense lines but with the incremental block sourced from `BASE - Incr Vol Build` and no integration/management-fee overlay. - Build the "BASE - Incr Vol Build" tab with the same five-specialty structure as INT - Incr Vol Build but keyed to Base-Case growth rates so it feeds the BASE - P&L. - Build the "INT - Val & Returns" tab as the Integrated DCF. Add DCF operating assumptions (Close Date, First Northstar CYE, Northstar Ownership from `INT - P&L!H11`, Tax Rate), a PAYER 004 Dissynergies mini-schedule (fully/self-insured detection), and the annual Cash Flow columns pulling Total Cases/Total Revenue/Integrated Facility EBITDA from INT - P&L. Compute Depreciation, Amortization (Stubbed), EBIT, Income Tax, After-Tax Operating Income, add back D&A less CapEx and working-capital change, apply stub-year and amortization adjustments, split Northstar vs Non-Northstar ownership, then layer Northstar Mgmt. Fee / Overhead / Taxes / RBO Profit / Parentco Dissynergies to reach the Northstar After-Tax Cash Flow. Discount via period YEARFRAC / discount-factor / PV rows and add Terminal Value + Discounted TV. Build the Investment Value & Multiples block (EBITDA multiple → Implied EV → Less Debt from P&L H18 → Implied Equity × Northstar Ownership + Mgmt. Fee Buyout → Northstar Cash Outlay Unlevered/Levered). Add the DCF Sensitivity Tables (Purchase Price and Integrated IRR against Perpetuity Growth Rate × discount steps) and an Unlevered IRR calculator using XIRR of Northstar Unlevered Cash Flows against a discounting date row. - Build the "BASE - Val & Returns" tab as the Base-Case parallel DCF, with the same cash-flow, terminal-value, valuation-multiple, sensitivity and IRR structure, but driven off BASE - P&L values and its own case-specific cash flow ranges. - Build the "Amortization" tab. Populate the General Assumptions header pulling Close Date from `INT - P&L`, First CYE = year-end derived from close, Tax Rate from `INT - Val & Returns`, Stub-Year Adjustment from `INT - P&L`, Discount Rate and Perpetuity Growth Rate from `INT - Val & Returns`, TTM Depreciation and TTM Amortization from `Vol & Fin Inputs`, and Post-Close Depreciation/Amortization periods. Add Non-Compete Assumptions block with Intangible Asset Life = 5, Amortization Life = 1/5, Probability of Competition table by age/weight (ages 50/55… weights 0.3/0.2/0.1) and Management Agreement Assumptions block with Intangible Asset Life = 15, Amortization Life = 1/15, Renewal Term = 5, Renewal Adjustment = 0.1. Build the Non-Compete Detail table (Name/Specialty/Age/Investor Status/Ownership/TTM NPR-per-Case/TTM Volume rows with TOTAL row of counts and sums). Build the Integrated Cash Flows section (rows 50–103): year headers keyed off G24 date driver, per-year Revenue / EBITDA (with non-compete) via XLOOKUP into `INT - Val & Returns` row 23/28/31/35/46/48 with fallback = prior year × (1+F13); compute EBIT, Provision for Income Tax (× F8), EBIAT, add-back D&A less CapEx & change-in-WC (WC ratio pulled from `INT - Val & Returns!T8`), Unlevered FCF (with Non-Compete) and PV using YEARFRAC period and 1/(1+F12)^period discount factor. Repeat the block for FCF without Non-Compete (rows 72–90), then Tax Benefit = discount × Amortization Life, Amortization Step-Up Factor = 1/(1−F8×SUM(tax benefit))−1, Value of Non-Compete = Total PV(w/) − Total PV(w/o), Indicated Fair Value = value × (1+step-up), Non-Compete Amortization Term = L6, Amortization Per Year (straight-line with stub adjustment via F9 in the first year), and rolling Amortization Base. Repeat the identical Non-Compete valuation waterfall for the Base Case (rows 105–157) sourcing from `BASE - Val & Returns`. Build the Management Agreement Detail section (rows 159–223): Integrated case pulling Northstar Mgmt. Fee and Northstar Overhead from `INT - Val & Returns` rows 58–59, applying a renewal adjustment (subtract L17 every L16+1 periods across five renewal windows), computing Mgmt Fee Profit after Taxes, PV via period/discount factor, Tax Benefit and Step-Up, Value of Mgmt. Agreement, Indicated Fair Value, Term = L14, and straight-line Amortization Per Year. Repeat the same Mgmt. Agreement waterfall for the Base Case (rows 193–223). Finally roll the two intangibles into the "Total Amortization" summary block at rows 26–34 (New Amortization Integrated = INT non-compete + INT mgmt fee amort, capped at L16+1 renewal window; Base equivalent; plus Existing Amortization pulled from `Deprec. Calc`). - Build the "Deprec. Calc" tab. Add a monthly grid from S8 forward (=DATE(YEAR(Amortization!$F$6),1,31) then chained EOMONTH), with derived Year (row 5), Post-Close Month index (row 6 = ROUNDUP((period-1)/12) with "Close" flag), and Post-Close/Pre-Close labeling row (row 7 based on comparing month vs Amortization!$F$6). Build the annualized summary columns D:M with: Existing D&A (Pre-Close) = SUMIF of Amortization row 14 monthly cells, Existing Depreciation (Post-Close) = SUMIF of monthly row 15, Depreciation (New Assets) = SUMIF of monthly row 11, Total Depreciation summed for each year, Total Existing Amortization = SUMIF of monthly row 20. Build the monthly per-cell driver rows: row 10 (New Asset CapEx per month = XLOOKUP CapEx-year value / (12 × useful life), zero pre-close), row 11 (New Asset Depreciation with same shape), row 14 (Pre-Close Existing D&A = Amortization!$F$14/12 when pre-close), row 15 (Post-Close Existing Depreciation = MAX((F16 − F16×(month-1)/F17)/12,0)), row 18 (Pre-Close Existing Amortization), row 19 (Post-Close Existing Amortization following the same declining formula against F18), row 20 = SUM of 18–19. Add the "New Assets Depreciation Waterfall" mini-schedule (rows 22–42): pull CapEx per year from `INT - Val & Returns!I46:R46`, useful life = `Amortization!F17`, per-year straight-line spread across future years capped by useful life, and Total Depreciation row = SUM of the per-year cohort spreads. | H10: 4f56a4bf-a1c1-4a5a-a04b-0002394e52c8
A11: e8ad8af9 | B11: APPROVE to generating_prompt. | C11: infinitearbitrage@gmail.com | D11: 15492 | E11: 10819 | F11: Assumption Sheet is removed along with its dependents | G11: - Set up the Assumption Sheet inventory master table by zone (Zone 1, Zone 2, Zone 3), listing every unit type with number of units, average area m², and total BUA calculated as units × area, plus the "as of 30-06-2022" original price per meter (hardcodes 21000.8, 18888.7, 56568, 40627, 0, 34693.7, 22078, 22078, 26621, 22243.1 for Zone 1 residential; 81478.8 flat for Service Apartments; 19831.5, 21720.7, 15702, 21190, 16190.6 and 22243.1 total for Zone 2; 18831.1, 24703, 24329.6, 22369.2, 35641.6 and 22243.1 total for Zone 3) and "% of type from total units" calculated relative to grand totals excluding service apartments (or relative to service total for the service block); include a Zone 3 grand-total average price hardcode 22243.1 and grand-total roll-up combining all four sub-totals. - Add the new-price and sales-to-date columns to the inventory table capturing the January 2023 price list (44905.9, 36766.8, 118269.2, 118269.2, 161666, 81748.4, 79132.4, 85297.4, 90426.7 for Zone 1; 68431.9, 64708, 54993.3, 68267.6 for Service; 38610, 31313.6, 29513, 38423.2, 44905.9, 30694.1, 46826.7, 52841 for Zone 2; 54083.3, 53203.6, 78413.3, 58886, 50877.7, 62809.7, 44756, 46826.7, 52841, 90108.3, 76446.5, 39483.9 for Zone 3), meters sold, expected total sales (hardcodes including 55268389.52 subtracted in Zone 1 first row; 418377910.1, 95070278.3, 84506146, 0, 130345820.8, 81291567.2, 81291567.2, 247201248 for the remaining Zone 1 rows; 129142500.8, 170985472, 122042240, 200151908.8, 58293524.8 for Zone 2; 17017648, 18379054.5, 27625428.7, 46001606.7, 26516832 for Zone 3), sold units, remaining units as units minus sold, % sold, % unsold as 1 − % sold, and price-escalation % as new price / old price − 1; add a Zone 3 average escalation formula spanning selected rows, a Grand Total row summing all zones, and a Remaining BUA line calculating total BUA minus meters sold. - Build the Sold Units Assumption timeline: create annual header row (Base Year 2022 through 2035) followed by a monthly date row starting 30-06-2022 using EOMONTH to roll forward across all months through 2035, and add a "% of units sold" driver row keyed by year (hardcodes 0 in 2022, 0.1 in 2023, 0.1 in 2024, 0.1 in 2025, 0.2 in 2026, 0.2 in 2027, 0.1 in 2028, plus a "no. of units sold" line equal to % × total remaining units, split into Residential and Service subtotals derived from the by-unit sales schedule below. - Populate the by-unit sales pacing table (Zone 1 residential, Service Apartments, Zone 2, Zone 3) where each row starts with remaining units from the inventory master, then contains hardcoded monthly unit sales values across the horizon (values 1.6, 3.2, 4.8, 6.4, 8, 9.6 etc. and per-row month-by-month allocations) with a "Remaining Units" formula at each year boundary equal to prior-year remaining minus that year's SUM, plus per-zone TOTAL rows, a full grand TOTAL summing every column, an annualized total row summing 12 months per year, and a running "Remaining units" line stepping down by each period's total. - Build the Cost per Unit escalation driver: base year hardcode "Cost to selling price" equal to 10366.65 × 1.2, then chain year-on-year escalations (× 1.35 to 2023, × 1.2 to 2024, × 1.16 to 2025, × 1.14 to 2026, × 1.15 to 2027, × 1.14 to 2028, × 1.13 to 2029), compute Cost Escalation % as current/prior − 1, and derive per-year cost-per-meter as the 4-year rolling average of the cost-to-selling series; replicate this cost-per-meter across all unit-type rows with Service Apartments carrying a 1.10 uplift multiplier. - Add the annual and monthly Cost Prices per Units date grid (year headers 2022–2035 with month index 1–174) mirroring the sales assumption grid to serve as the calendar for the cost-value schedule. - Build the Cost Value schedule by unit type as monthly cost = cost-per-meter (base column for pre-escalation, then year-specific rate) × units sold in month × average area m², with year-boundary sum columns collecting the 12 preceding months, per-zone TOTAL rows and a grand Total Cost row that further adds a one-time "Total Cost after last escalation" = Total Cost × 1.2; include a Zone 3 hardcode adjustment of −272000 on the Chalet 2 bedrooms (105/110/115/120) base row and note the per-year cost-to-sales ratio formula for later use. - Add the sales-escalation driver block: Residential Sales Escalation till 2025 hardcode 0.2 with thereafter hardcode 0.2, and Service Sales Escalation till 2025 hardcode 0.2 with thereafter hardcode 0.2. - Build the Sold Prices Assumption table on the same date grid: for each unit type input the "prices as of 30-06-2022" base hardcodes (39463.2, 34940.7, 76366.8, 54846.5, 54846.5, 48184.2, 45231.8, 43587.5, 47121.8 for Zone 1; 64797.3 flat for the four Service types; 40866.2, 43110, 42183.5 and formula 5524787.25/112.5 for Zone 2, then Zone 2 Penthouse = B200 × 1.4, Chalet 2 bedroom + Roof = B200 × 1.3, Loft 2 bedroom = B200 × 1.2, Loft 3 bedroom = B200 × 1.25; 31153.8, 35152.3 for Zone 3, Chalet 2 bedrooms + Roof = B208 × 1.15, 20596.6, 25315.7, Chalet 3 bedrooms LO1B = B211 × 1.15, 40662, Loft 2 = B207, Loft 3 = B208, 61921.1, 65784.5, 35376.3 for the remaining Zone 3 rows), then chain forward with (1 + Residential escalation) for residential rows and (1 + Service escalation) for service rows, with 2025-onward columns using the "thereafter" escalation; add TOTAL AVERAGE rows per zone and an overall Average price line averaging across the mixed residential and service unit rows. - Build the Sold Value schedule mirroring the cost schedule structure: monthly value = period sold-price × units sold × average area m², with year-sum columns, per-zone TOTAL, a grand TOTAL, and summary lines for Total Achieved (with Zone 1 base hardcodes 2168040599.9 and 55268389.5 and Zone 1 2023 hardcode 362076515.3), Total Service Apartments (with Service Apartments 2023 hardcode built as 2665472.128 + 463022.272 + 4167201.6 and Hotel base year hardcode 4167201.6), Total Residential Apartments = Total − Service, Total Target Residential, Total Revenue, Gross Profit = Revenue − Total Cost, GPM, and per-period COGS-to-Sales ratios split by Service, Zone 1, Zone 2, and Zone 3, plus a Total COGS-to-Sales. - Add the Soft Cost block: Marketing (5%) driven off % of sales with base hardcode 0.10 and per-year overrides 0 for 2027, 0 for 2028, 0.10 for 2029, 0 for 2030 (with 2023 override 0.08 as a fixed multiplier on total residential value); Sales (5%) driven off % of generated sales with base 0 and 2027 = 0, 2028 = 0.10, 2029 = 0.10; G&A (3%) with a 2023 seed = paid G&A base / 4 and then growth of 1.10 per year across every year through 2033; label the "Fixed cost grow by 12% every year" note; sum into a Soft Cost Total. - Add the Total Cash out (Excl land payments) line summing Total Cost + Marketing + Sales + G&A for every period, and a Payment Plan label capturing the 10-year 10% down + quarterly installments term. - Build the Revenue Recognition schedule: "Revenue from delivered units for old sales" hardcodes 269979545.6 in 2024, 840674711.9 in 2025, 693399993 in 2026, 357582517.7 in 2027, 6403831.6 in 2028; "for new sales" wires each future-year total revenue into a delivery year (I267 → 2026, V267 → 2027, AI267 → 2028, AV267 → 2029, BI267 → 2030, BV267 → 2031, CI267 → 2032, CV267 → 2033); Total = old + new; Cost Recognition = Total × delivery-year cost ratio with hardcodes 0.22, 0.23, 0.20, 0.23, 0.22, 0.22, 0.22, 0.35, 0.35, 0.42; SG&A = Total × ratio with hardcodes 5%, 5%, 5%, 5%, 5%, 5%, 5%, 4%, 4%, 8.73%; NOP = Total − Cost Recognition − SG&A; Taxes = NOP × 0.225; NI = NOP − Taxes. - Build the Construction Cost detail schedule: Residential construction with hardcodes Mobilization 17735787.6, Excavation/settlements/gravitational walls 261004363.8, Building Works 1713630787, Service buildings/pools/bridges 582939955.3, Gates and fence 12832846.8, Landscaping/roads/K-STONE/transformers/desalination/fire tanks 762605882 summed to Residential total; Brand Residence construction with Construction & Finished = 888819866.88 + 176000000, Parking (Under Ground) 38936050.6, Parking (Exterior) 4172213.8, Technical Services Fees 8839670.4, Professional & Other Fees 93192813.1, Contingency = 90191702.1214587 + 69577979.8496727 summed to Brand Residence total; Total Cost of Construction = both totals, and Total Cost after Escalation = link to "Total Cost after last escalation" line above. - Add the Project Total Cost / Paid-to-Date block: "Paid out until 30-06-2022 (including land payment)" broken down by Land 124382457.6, Construction 203344856.4, G&A 136701689.4, Sales 80158881.8, Marketing 175614706.2 with Total = SUM; Paid out from company internal resources 120000000, Paid out from cash inflow = collected cash from receivables, plus Total; add Total Land Cost (remaining amount) = 973897207.883984 − paid Land − next-year land payment, Annual Payment = remaining ÷ 6, and Collected Cash from Receivables 600270052.8 with date stamp "As of 30-06-2022". - Build the Residential Collections schedule on the extended calendar (2022 through 2038 with monthly EOMONTH date row): Down-payment driver 10% (hardcode 0.10) generating Down Pmt column = residential sales × 10%, followed by New Collections (annualized) per vintage year where each remaining 90% is amortized as (sales − down pmt) × 10% per year and rolled forward 12 columns at a time (2022, 2023, 2024, 2025, 2026, 2027, 2028, 2029 vintages), each with a "Remaining Principal" step-down row; add Old Collections hardcodes 232206626.1 (2023), 261112653.1 (2024), 228470069.3 (2025), 221873120.8 (2026), 200945794 (2027), 119835822.9 (2028), 71905674.7 (2029), 54763189.9 (2030), 27669824.2 (2031), 3671577.1 (2032), with 2022 vintage tied to Model Update C4 and a 2023 subtraction adjustment of 101140141.088; add per-year Total collection lines and Remaining Receivables lines and a checker line total minus total residential. - Build a parallel Service Apartments Collections schedule with identical structure — 10% down-payment driver (hardcode 0.10 and monthly formulas across the full calendar), vintage new-collection amortization blocks with remaining-principal step-downs, per-year totals, remaining receivables, and combined Total Remaining Receivables = residential remaining + service remaining, plus a checker; annual totals link to Model Update C5 for 2022 and reference DH399/DH372, DT399/DT372 aggregations at horizon boundaries. - In the Model Update tab, wire in two new formulas that pull from the new Assumption Sheet: cell F10 = Assumption Sheet Total Cost after Escalation minus Model Update B63 (delta between escalated cost and paid construction), and cell B64 = Model Update B63 divided by Assumption Sheet Total Cost of Construction (paid construction as % of total construction cost). | H11: e8ad8af9-0dc2-4a47-915d-69799551aad9
A12: 15a0ebf7 | B12: APPROVE to generating_prompt. | C12: nimisha.mekala2021@gmail.com | D12: 12659 | E12: 6847 | F12: Builds the granular LAR revenue engine that the consolidated P&Ls draw on for topline. | G12: - On `LAR - I&A`, populate the "Managed Care Inputs" summary block (rows 22–26) by pulling TTM Volume, TTM NPR/Case, TTM NPR, Total Lift $ Amount, and Blended Final NPR/Case from the corresponding cells on `NPR x Payer` (E36, F36, C22×C23, L36, I36), and pull Close Date and TTM Date from `INT - P&L` H7 and H6. - On `LAR - I&A`, build the per-payor Managed Care TTM table (rows 24–31, cols E–N) with each payor row (Aetna, BCBS, Cigna, MRDNC, BCBS MCR, MRDNC/Aetna MCR) doing XLOOKUP against `NPR x Payer` D23:D35 to bring in TTM Volume (col E), TTM NPR/Case (col F), TTM NPR = F×G, PF Vol allocated by TTM-volume share of total (I$31 × F/F$31), PF NPR allocated by TTM-NPR share (J$31 × H/H$31), PF NPR/Case = J/I, Proposed NPR/Case via XLOOKUP to `NPR x Payer` I23:I35, and $ Lift NPR/Case allocated using the payor's share of ((L-G)×F) over the total lift, plus a $ Lift NPR column = F×L; add the "Other Payors" plug row that solves for the residual against C22/C23/C24 totals, and total row that ties back to those TTM anchors and pulls PF Vol / PF NPR from `INT - P&L` H30:L30 / H34:L47 via XLOOKUP on the case-count driver in H14. - On `LAR - I&A`, populate the First Tranche cell (C19) as an XLOOKUP that finds the payor with the maximum $ Lift NPR (INDEX/MATCH over M24:M29) and returns its Tranche 1 reimbursement month from the payor-assumption table B52:N54. - On `LAR - I&A`, wire the Volume Escalator and NPR/Case Escalator tables (rows 29–34 and rows 39–46) so column C pulls annual `BASE - P&L` values (Volume from N31:S31, NPR/Case from N44:S44), and expand the Base-Case NPR/Case per-payor grid (rows 39–46, cols F–N) to compute Effective NPR/Case = J − ABS((J − H) × L) with L (haircut %) hardcoded to 0 for every payor and every year, blending back to a Total row via SUMPRODUCT of effective NPR/Case × TTM Volume divided by total volume, with the "MC Final NPR" vs "MC Growth %" toggle at C6 switching between the L-column and N-column proposed NPR sources; then propagate C-column payor growth rates and years into the columnar Case Volume Escalator (rows 68–73) and NPR/Case Growth Rate (rows 79–84) tables per payor. - On `LAR Summary`, add the annual summary rollup at the top (cols C–S, rows 9, 17–24, 27–34, 37–45, 49–58, 60): populate the Blended NPR/Case Growth Rate row as =C45:S45 pass-through; use SUMIFS across the AP:DU monthly grid with $AP$15:$DU$15 = TTM as the TTM aggregator, and XLOOKUP against the date row $BB$17:$DU$17 for each forecast-year total; row 17–22 pulls NPR per LAR payor from monthly rows 32/33/34/35/36/37, row 23 pulls Other Payors NPR from row 29, row 24 totals; rows 27–33 mirror the same lookups for Cases (from rows 42/43/44/45/46/47 and 21), row 34 totals; rows 37–43 compute NPR/Case per payor as row/row (IFERROR wrapper), row 44 is blended NPR/Case = C24/C34, row 45 is blended growth = current/prior−1. - On `LAR Summary`, add the Base Case comparison block (rows 47–58): NPR (row 49) and Volume (row 51) via the same SUMIFS-then-XLOOKUP pattern against monthly rows 62 and 55; Base NPR/Case (row 53) = C49/C51; Base NPR/Case Growth (row 54) = period-over-period; NPR/Case Delta (row 56) = C44 − C53; Revenue Delta (row 58) = C24 − C49. - On `LAR Summary`, add the LAR Effect trigger row 60 as IF(period13="TTM","", currentDelta − priorDelta), gated by the row-13 TTM flags. - On `LAR Summary`, build the monthly "Other Payors (non-LAR)" block in cols AP:DU rows 20–29: pull the label from `LAR - I&A` E45, drive Other Cases via XLOOKUP into `LAR - I&A` E38:E47/F38:F47 for the anchor and roll forward as (SUM(prior 12)/12)×(1+growth), with Volume Growth driven by an IF that at each year-boundary looks up the C-column organic growth from `LAR - I&A` (with the LAR-Effect toggle at C6 zeroing growth when ON), a Stubbed variant for the partial "End TTM Date" period (=(1−MONTH(date)/12)×growth), and Other Cases NPR/Case rolled forward analogously from `LAR - I&A` G38:G47/H38:H47 and its exp NPR/Case from N38:N47, culminating in Other Cases NPR = IF(period≥First-Tranche, Exp NPR/Case × Volume, TTM NPR/Case × Volume). - On `LAR Summary`, build the six identical per-payor LAR blocks (rows 68–94, 96–122, 124–150, 152–178, 180–206, 208–234), each anchored to `LAR - I&A` C52 / E52 / G52 / I52 / K52 / M52 respectively, in cols AP:DU: Volume with anchor XLOOKUP into `LAR - I&A` E38:E47/F38:F47 and roll-forward, Volume Growth with the same organic-growth toggle-aware IF, five Reimbursement Tranche rows (73–77) and five Reimbursement Tranche % rows (80–84) each computed via IF(XLOOKUP payor Tranche month in `LAR - I&A` B54:B58 vs C54:C58 against the period, tranche %, 0), Current NPR/Case from `LAR - I&A` G38:G47/H38:H47 rolled monthly by SUMPRODUCT/SUM × (1+organic growth), Proposed NPR/Case from `LAR - I&A` M39:M45/N39:N45 rolled by prior × (1+growth), Organic NPR/Case Growth with the same LAR-toggle IF and its stubbed partial-year variant, Base NPR = Volume × Current NPR/Case × (1 − sum of tranche %), LAR NPR = SUMPRODUCT(tranches, tranche %) × Volume × Proposed NPR/Case, and Proposed NPR = Base + LAR. - On `LAR Summary`, connect the payor-block subtotals to the AO-column "NPR x LAR Payor" and "Cases x LAR Payor" pass-through blocks (rows 32–37, 42–47) so each row equals the corresponding block's Proposed NPR row (94, 122, 150, 178, 206, 234) or Volume row (69, 97, 125, 153, 181, 209); add the Total NPR row (39) = SUM(payor NPRs) + Other NPR (row 29); Total Cases (row 49) = SUM(payor volumes) + Other Cases (row 21); Blended NPR/Case (row 51) and its growth (row 52); plus the Base Case NPR sub-block (rows 55–66): Base Case Volume from `LAR - I&A` F46/12 rolled forward, Total Cases NPR/Case from `LAR - I&A` H46 rolled forward, Base Case NPR = Volume × NPR/Case, Revenue Delta = Total NPR − Base NPR, Volume Check = Base Volume − Total Cases. - On `INT - Val & Returns`, add the new "Integrated IRR" sensitivity table (rows 125–132) modeled on the existing NRT DCF sensitivity table two rows above: header C127 = H146 (the new Unlevered IRR cell), row 127 axis populated across cols C:H as =+col-1 − $X$118, hard-anchor middle 0.03, =+col+$X$118 either side of center; row 128 col C = =+C129 − $X$120, rows 129–132 stepping the row axis around center 0 (net-new hardcode 0), and cols D:H rows 128–132 filled with 0 placeholders so Excel can treat the block as a two-variable data-table area. - On `INT - Val & Returns`, activate the previously blank IRR output cells H146 and H157: H146 = ROUND(XIRR(H145:OS145, H143:OS143), 4) as the Unlevered IRR, H157 = ROUND(XIRR(H156:OS156, H154:OS154), 4) as the Levered IRR, and I146 / I157 = H146/H157 − T6 for the delta-to-hurdle columns; these feed the new Integrated IRR sensitivity table above and propagate refreshed IRR / DCF values downstream through the linked `BASE - Val & Returns` sensitivity blocks. | H12: 15a0ebf7-8354-4e97-bdfd-764a03bef9ee
A13: f925d988 | B13: APPROVE to generating_prompt. | C13: apathy@uchicago.edu | D13: 12113 | E13: 8221 | F13: Cleared LAR. | G13: - Lay down the standing left-side row-label column for each of the ten per-payor blocks (rows 3–27, 30–54, 57–81, 84–108, 111–135, 138–162, 165–189, 192–216, 219–243, 246–270), with a repeating label stack in columns B/C/E containing: "Current NPR / Case" and "Proposed NPR / Case" headers, "Haircut", "Payor" / "Payor N" ID, "Location Appropriate Reimbursement Month" and "LAR %" tranche headers, then a right-side driver column labeled "Year Count", "Year", "Month", "Volume Growth", "Tranche 1 Flag" through "Tranche 5 Flag", "Base NPR Contribution", "Date", "Volume", "Current NPR / Case", "Proposed NPR / Case", "Base NPR", "Location Appropriate Reimbursement", "Effective NPR", "Effective NPR / Case", "Effective Incre. LAR / Case", "Effective Incre. LAR", plus a "Volume Escalator" label and a "Linked from P&L Organic Vol Growth^^" note. - In the "Location Appropriate Reimbursement Month" tranche input block (column B, rows 12–16 for Payor 1 and analogous rows for each payor), seed the month-count hardcodes 13, 100, 100, 100, 100 for the first five payor blocks (Payors 6–10 already carry only 100, 100, 100, 100, 100). In the "LAR %" column (column C, same rows), seed 1, 0, 0, 0, 0 for every payor. In the year-count lookup ladder just below (column B, rows 20–24 and analogous), seed 1, 2, 3, 4, 5 for every payor. Add a check total in column C summing the tranche % column (row 17 of each block). - For each payor block, place the top-of-tab MCR TTM Volume header row (row 4, "MCR TTM Volume" over the seeded monthly volume seed row and "Close Date" over the projection area). Below that, keep the "Current NPR / Case" / "Proposed NPR / Case" hardcode pair (row 6 = zeros in the seed) and build the haircut-adjusted proposed NPR as current × (1 − haircut) in column C of the payor row. - Populate the TTM seed grid in columns G:R for each payor: dates 1/1/2021 through 12/1/2021 across row 17 (repeat for all ten payors — only Payor 1 already had these) and copy the "MCR TTM Volume" seed forward across the row via each column equal to the prior column starting from a hardcoded first-month value (100 for Payor 1, 0 for Payors 2–10 as in the input). Populate the same G:R strip for "Current NPR / Case" and "Proposed NPR / Case" (rows 19 and 20 of each block) by referencing the block's B6 and C9 cells. - Build the monthly projection grid in columns T:CA for every payor block. Row 8 is the month counter (T8 seeded at 1, each subsequent column = prior + 1, with column R immediately to the left holding 0 as an anchor). From that, drive Year Count = ROUNDUP(month/12,0), Year = YEAR of the date row, Date = EDATE(close date, month−1) where the close date is pulled from `INT - P&L`!H7 in T5 of each block. Volume Growth (row 9) uses INDEX/MATCH against the payor's year-count ladder (B20:C24 for Payor 1, analogous ranges for others). - Add the five Tranche Flag rows (rows 10–14) as IF(month ≥ tranche-month input, 1, 0) referencing the block's B12:B16 tranche months. Add the Base NPR Contribution row (row 15) as IF(sum of tranche flags = 0, 1, 1 − SUMPRODUCT(tranche %, tranche flags)). - Build the monthly Volume row (row 18): for the first twelve projection columns (T:AE), pull from the TTM seed via array formula INDEX(seed,MATCH(MONTH(date), MONTH(seed dates),0)) × (1 + volume growth); from column AF onward, escalate against the same column of the prior year × (1 + volume growth). - Build the monthly NPR rows: Current NPR / Case (row 19) and Proposed NPR / Case (row 20) each equal to the block's B6 and C9. Base NPR (row 22) = current NPR × volume × base NPR contribution. Location Appropriate Reimbursement (row 23) = SUMPRODUCT(tranche %, tranche flags) × volume × proposed NPR. Effective NPR (row 24) = base NPR + LAR. Effective NPR / Case (row 25) = effective NPR / volume with IFERROR guard. Effective Incremental LAR / Case (row 26) = effective NPR / case − current NPR. Effective Incremental LAR (row 27) = per-case × volume. - At the top of each payor block (column A "x" spacer and B row 3/30/57/…), add the payor-name label formula IF(payor cell = 0, "", payor cell) so the payor name appears only when populated. - Build the "Summary" per-payor annual roll-up section in columns CC:CI (rows 17–27 for Payor 1, then in 11-row strides for each of the ten payors). Header row 5 = "Total" and years 1–5 (CE5 seeded at 1, then +1 across). For each payor, drive: payor name = block name; Volume = SUMIF(year-count row, year header, monthly volume row); Total NPR = SUMIF against monthly effective NPR row; NPR / Case = NPR / Volume; Incremental LAR = SUMIF against monthly incremental LAR row; Incremental LAR / Case = incremental / volume; Incremental LAR Realized = per-case / (proposed − current NPR); Max LAR / (Reduction) = MAX or MIN of incremental LAR row depending on sign of the sum. - Build the parallel "Total"-anchored summary block in columns CK:CS. Header row 5 pulls fiscal years from the `INT - P&L` date row (CL5 = YEAR('INT - P&L'!H25), CM5 = 'INT - P&L'!J24, CN5 = YEAR('INT - P&L'!Z25), then +1 across through CS5). Row 6 "Existing Revenue" uses an IF against the LAR flag to either pull `INT - P&L` revenue directly (H39, J39, Z39, AM39, AN39, AO39, AP39, AQ39 by column) or rebuild it as volume × PF NPR / case + cumulative applied LAR. Row 7 "Volume - Total" links to `INT - P&L` volume row 28 (H, J, Z, AM–AQ). Row 8 "NPR / Case" = existing revenue / volume. - Add the tab-level driver stack in columns CU:CV: "Location Appropriate Reimbursement Start Yr" hardcoded to 2024 with note "<< when BL13:BQ13 begins 1"; "Anchor Column" = MATCH(start year, header row, 0); "Pre-RL Volume" and "Pre-RL NPR" pull from the summary via INDEX one column left of the anchor (array formulas); a "check" row = SUM of realized LAR minus Max LAR. - Layer the LAR mechanics into the CK-block: "Volume - Location Appropriate Reimbursement" and "Total Incremental Location Appropriate Reimbursement" (rows 9 and 10) sum the corresponding per-payor summary rows across all ten payors (block rows 18/29/40/51/62/73/84/95/106/117 for volume; 26/37/48/59/70/81/92/103/114/125 for effective incremental LAR). Row 11 "Organic Growth Rate" is a hardcoded 0 across all years. Row 12 "Location Appropriate Reimbursement Flag" = IF(incremental > 0, 1, 0). Row 13 "Organic Growth PF NPR / Case" = IF(flag−1=0, Pre-RL NPR × (1+growth), 0) × IF(prior flag > 0, (1+growth), 1). Row 14 "Adj. NPR / Case Growth Rate" = current-year NPR / prior-year NPR − 1, guarded to 0% when no LAR. Row 15 "Total LAR Realized" = SUM of realized LAR row. - Add the CD-column "TTM" mirror of the summary logic (rows 6, 9, 10 in the CD column) so TTM incremental LAR = same year-sum construction against year-count row 6 of the payor blocks (CD9 sums payor Volume rows via SUMIF; CD10 sums payor Incremental LAR rows). - Below each payor's monthly-derived summary rows in CK:CS, add the "Max Location Appropriate Reimbursement / (Reduction)" cap and its running "Remaining LAR / (Reduction)" and "Effective Incremental Location Appropriate Reimbursement" schedule: max/min against incremental row depending on sign; remaining = MAX/MIN(cap − running sum, 0); effective = MIN/MAX(prior remaining, current incremental) based on cap sign. Repeat this three-row LAR-cap sub-block for every payor. - Build the "Integrated" vs. "Base" comparison table in columns DA:DE (rows 5–16). Header row 5 mirrors the CN:CQ years. Under "Integrated" pull Revenue = 'INT - P&L'!Z47/AM47/AN47/AO47, EBITDA = 'INT - P&L'!Z107/AM107/AN107/AO107, IOI = 'INT - P&L'!Z171/AM171/AN171/AO171. Under "Base" pull Revenue = 'BASE - P&L'!L45/M45/N45/O45, EBITDA = 'BASE - P&L'!L110/M110/N110/O110, IOI = 'BASE - P&L'!L171/M171/N171/O171. "Applied Location Appropriate Reimbursement" row = Integrated Revenue − Base Revenue. - Add the "View Summary" navigation label in B1, the tab title "Location Appropriate Reimbursement Schedule" in B2, and the section marker "Summary" in CC3, along with the scattered "x" spacers in column A (rows 3, 30, 57, 84, 111, 138, 165, 192, 219, 246), row 1 (T1, CB1, CT1, DF1), and the internal separators (CT16, CT27, CT38, CT49, CT60, CT71, CT82, CT93, CT104, CT115, DF18) that fence off each payor's blocks. | H13: f925d988-87c3-4cb0-a396-b583b2949382
A14: 21d534e3 | B14: APPROVE to generating_prompt. | C14: apathy@uchicago.edu | D14: 10061 | E14: 11075 | F14: Cleared Pro Forma, SWB Breakdown, Fee & Debt Schedules, Cash Collection & Distribution, Inputs, Calculator, Summary Output, I&A. | G14: - On the **I&A** tab, add the SWB build in rows 270–296: a position schedule (Administrator 86.6, DON 69.4, BO Manager 42.2, BO Scheduler 26.4, BO Receptionist 26.4, BO Billing/Collections 27.8, GI Tech 27.5, Radiology Tech driven off specialty triggers, RN – OR/PR 54, RN – Periop 54, Medical Assistant 21, Materials Mgmt/AP 35 with pre-1st-patient and Yr1–Yr5 FTE headcounts), Total FTE sum, Total Salaries Expense (SUMPRODUCT of rate × FTE × worked hours, prorated for Year 1 by months-pre-1st-patient/12), Total Benefits Expense = Salaries × benefits rate, Total SWB = Salaries + Benefits; Pro Forma Assumptions block with Worked Hours/Day of 8, Worked Days/Year pulled from Pro Forma annual working-day totals (Year 1 = average of Years 2–5), FTE Hours/Year = hours × days, and Benefits rate of 30%. - On the **I&A** tab, add the OR/PR capacity–utilization block in rows 214–222: rooms × hours/day × work-days/year to compute annual capacity, and case-volume-to-capacity utilization; then wire the Suggested-rooms cells at rows 72–73 to a ROUNDUP of required volume ÷ (capacity × 80% target utilization). - On the **I&A** tab, replace the working-capital "Calculated Requirement" cell with the running MAX of the Cash Collection & Distribution WCLOC beginning balance line; add the Cedarbrook Operating Model Overhead block at rows 410–419 (Total Overhead = Operating Overhead + Non-Standard; Operating Overhead switches on the "Bundle" toggle to pull Summary Output total services cost, else lookup a fixed overhead table with Multi-Specialty 200000, SXH 300000, Single (GST or Pain) 150000, Multi-Site 400000). - Build the **Pro Forma** monthly timeline: header row of period numbers 1–5 mapping months to year buckets (S–AD=1, AE–AP=2, AQ–BB=3, BC–BN=4, BO–BZ=5), a Pre-Ops column plus 60 monthly period numbers 1–60 across S:BZ, monthly date row daisy-chained from I&A "First Patient Date" (S3) via DATE(YEAR+1 month), and a year-summary block CB:CF for years 1–5 with SUMIF(period-header, year, monthly row) roll-ups. - Build the **Pro Forma** Volume Build section (rows 6–25): Base Volume = prior period's Unadjusted Total Cases (Year-1 seed from I&A base case count) grown by Standard Growth Assumptions (natural growth pulled from I&A KPI drivers); Incremental Cases from ramping physician build; Unadjusted Total Cases = Base + Incremental; parallel NPR/Case and Supply/Case rows with existing/incremental/blended tiers feeding revenue and supply totals. - Build the **Pro Forma** Volume Adjustments block (rows 27–37) as three toggled overlays (Seasonality Variance, Monthly Working Days, Facility Volume Ramp Up), each with a numeric switch (1, 2, 3), an "ON" text toggle in column D that gates the monthly application via IF($D$xx="ON", raw, 0), and monthly variance rows; also add the Working Days Database at rows 145–159 (Month labels January–December + Total) that the Monthly Working Days overlay reads from. - Build the **Pro Forma** Income Statement (rows 39–75): Total Volume with NPR/Case; Net Patient Revenue; Other Revenue (per-case × cases); Total Revenue; Operating Expenses stack (SWB from SWB Breakdown roll-up, Supplies from per-case × cases, Rent, Insurance, Other Variable Expenses, Bad Debt, Annual OM Expense from I&A overhead, CBO Fee); EBITDAM and EBITDAM Margin; Management Fees section (Cedarbrook Development Fee, Other Development Fee, Cedarbrook Mgmt Fee driven off Fee & Debt Schedules fee tier, Other Mgmt Fee); EBITDA and EBITDA Margin; Non-Operating stack (Depreciation New Assets, Depreciation Incremental CapEx, Amortization TI Allowance, Net Interest Expense) each drawn from Fee & Debt Schedules; Pre-Tax Income; NOPAT. - Build the **Pro Forma** E-NCI section (rows 77–100) and IOI section (rows 102–118): ownership percentages (Cedarbrook, MD, Other) applied to Pre-Tax; Consolidated E-NCI [C] = EBITDAM – Other Mgmt Fee – NCI with Buyer Multiple (Consolidated) driving Adjusted Pre-Tax Income; Equity E-NCI [E] = Cedarbrook Equity Income + Cedarbrook Mgmt Fee Income with Buyer Multiple (Non-Consolidated); labels dynamically flex on I&A cell E9 = "Consolidated"; IOI [C] = EBITDA + Cedarbrook Mgmt Fee – D&A; IOI [E] = Pre-Tax – NCI + Cedarbrook Mgmt Fee. - Build the **Pro Forma** KPI block (rows 120–127: Net Patient Revenue/Case, Other Revenue/Case, SWB/Case, Supplies/Case, Other Variable/Case, Bad Debt/Total Net Revenue, CBO Fee/Case) and the Growth driver block (rows 129–141) that stages all per-case and expense-growth rates by year from I&A source cells, with Year-1 seeding and cascading forward. - Build the **SWB Breakdown** tab as a monthly detail of every I&A position for months 1–12 plus each Year-2–Year-5 column: header row 1 as descending month counters back from Pro Forma month indices; each position row = IF(month > months-pre-1st-patient, 0, rate × FTE-hours × pre-1st-patient FTE × (1 + benefits load)/12) for Pre-Ops months, then Year-1 monthly = same formula with Year-1 FTE and rate escalators, then Years 2–5 as annualized rate × Yr-N FTE × hours × (1 + escalator); Column-O and Column-AB sum to annual/total. - Build the **Fee & Debt Schedules** tab: Management Fees table pulling Standard Fee/Fee Cap/Flat Fee tiers from I&A rows 406–408; Incremental CapEx Depreciation Schedule with period from I&A; Deferred Rent Amortization with period = I&A rent months / 12; New Asset Depreciation with Surgery Center Assets 10-year period and Equipment Assets 7-year period; three debt schedules (Construction Loan, Equipment Loan, Working Capital LOC), each with Principal, Repayment Terms, Amortization Period, Interest Rate, Interest-Only Period pulled from I&A, and a Payment cell computed as `-PMT(rate/12, amort, principal, 0)`; carry monthly interest and principal amortization out across the 60-month timeline. - Build the **Cash Collection & Distribution** tab: Cash Collections section (Surgical Revenue = Pro Forma R46 monthly; Less Bad Debt = Pro Forma R54; Net Patient Revenue = difference); Collections Timing block with six-month lag pattern (weights 10%, 10%, 40%, 40% distributed across months 1–6, adjusted for early-month ramp) and Total Monthly Collections = SUMPRODUCT of pattern × NPR history; Distributable Cash Flows three-section cash flow statement (Operating: Collections – Interest – OpEx ex-interest – TI Allowance amort; Investing: Purchase of Equipment; Financing: Working Capital Equity Contribution seed, Construction Loan Principal, Equipment Loan Principal); WCLOC roll (Beginning Balance = prior + draws – repayments, Payment-Type reference IF period ≤ interest-only period THEN "Interest-Only" ELSE "Principal & Interest", Cash from Working Capital Draw = IF net-cash-negative fund shortfall to zero, Principal Repayment = MAX(-Beg, -MIN(scheduled)) when cash positive); Net Cash Distributions ending with LESS `# Days Operating Expenses` reserve pulled from I&A and Net Distributable Cash Flow. - Build the **Calculator** tab as the ASC service-selection engine: an OM Framework selector at I7 (1 = Standard, 2 = Standard + BD, 3 = Bundle) plus per-lane option selectors (PAS/Clearinghouse I10; HR I13; Accounting I22; Treasury I25; Tax I28; Risk Management I30; Supply Chain I32; Clinical I35; Marketing I45; Regulatory Compliance I52; Payer Engagement I55; RCO CBO/Local/Non-Sponsor at I58 with yes/no add-ons D60/D61/D64/D67); each lane's F/G/H columns (Annual, One-Time, Included in MSA) is a nested IF driven off framework and option toggles, embedding the full price table — PAS Option A 32400; HR Cedarbrook 17448 / bundle 27708, Time Keeping 6/teammate/month × 12, Timeclock Web App one-time 2000, Timeclocks one-time 4915, Payroll 6.5/teammate × 26 pay periods; Accounting Option A 23900, Option B 32700; Treasury Option A 2800, Option X one-time 300 + annual 18000; Tax Option A annual 13460 + one-time 22000; Risk = Inputs!D14; Clinical Support 10000, Clinical Policies 500/1000, Risk Reporting 800, Compliance 726, NPS 693, OAS CAHPS 3135, AORN 157; Marketing Templatized Website 2532 + 8500 one-time, Reputation Platform 509 + 350 one-time, Monthly Optimization 1800, Website Improvements 2010, Collaterals 500; Regulatory 7000 + 500; Payer Engagement 31500; CBO Local Vendor 20000; Insurance Verification Training 3500; Legacy AR Fin Pack 4500; Payer Contracts Database 1500 + 2000 one-time; Vendor Database 8500; Charge Capture 750; Clearinghouse Conversion 1500; EMR Interface 5000. Then an Included-in-Framework block (Legal Platforms 1800, Insights Platform 3300, Operations pulled from Inputs!D12, Finance pulled from Inputs!D13, IT pulled from Inputs!D31/H31 with fallback 1350, an implicit BD row = IF I7=1 then 0 else 43000, Credentialing = IF I7≤2 then 0 else Inputs!D10×31×12), and a Sold-Separately block (Coding = Inputs!D24 if selected else 5000, Credentialing driven by teammate/practitioner counts, Business Development 43000). Totals SUM each column. - Build the **Inputs** tab as the facility-fact intake feeding Calculator: Facility Info (Name, Address, Group pulled from I&A E8/E15/D25); Number of Teammates 15; Number of Practitioners 5; Management Services Agreement Fee = AVERAGE of Pro Forma Cedarbrook Mgmt Fee Years 2–3, compared against the Selected Floor lookup (200000 if framework=1, 250000 if =2, 350000 else); Operations Costs 30636; Finance Costs 20215; Risk Management 0; Estimated Annual Case Volume = AVERAGE of Pro Forma cases Years 2–3; Case Mix % inputs (Cataract, Spine, GI Assisted, Other, IP/Obs; sum-check must = 100%) with rate table Cataract 6.1, Spine 8.9, GI Assisted 2.3, Other 7.5, IP/Obs 19.1 (K17:K21); Estimated Coding Annual Cost = SUMPRODUCT of volume × mix × rate; RCO Budgeted Coding = coding cost if mix sums to 100%; IT Expense section (# Teammates = D9, # PCs = D27, # Servers 2, New Phone System toggle 1) driving an IT Services Detail table that pulls unit rates from IT Amounts (Facility flat, Teammate support, Computer support, Mailbox split 60%/40% via M30/O30, VPN 10% via M31, Local Server, Network Equipment × 8) to compute Annual IT Cost D31 = K34+K40 and One-Time Cost H31 = SUM of IT Amounts one-time categories. - Build the **Summary Output** tab as the client-facing pricing summary: header pulls Facility Name and Address from Inputs; one row per Calculator lane (OM Framework, PAS, HR, Accounting, Treasury, Tax, Risk Management, Supply Chain, Clinical, Marketing, Regulatory, Payer Engagement, RCO, Legal Platforms, Insights Platform, Operations, Finance, IT, Coding, Credentialing, Business Development) with each row's Description column built from CONCATENATE(CHOOSE(selector, option-label list),": ",CHOOSE(selector, option-description list)) and D/E/F columns aggregating that lane's Annual, One-Time, and Included-in-MSA cost with COUNTIF("TBD") propagating "TBD" upward; a Totals row (D29:F29 = SUM of the lane rows); and a bottom compliance block: Management Services Agreement Fee = Inputs!D11 with a floor warning; Total Services Costs = F29; Margin $ = MSA Fee – Services Costs; Margin % = Margin $ / MSA Fee with a warning if below the 20% compliance minimum. | H14: 21d534e3-8c09-46e5-8a5d-b5c55c8522a2
A15: 552a9578 | B15: APPROVE to generating_prompt. | C15: wangche2532@gmail.com | D15: 8568 | E15: 11303 | F15: Delete tabs: Cash Collection & WCLOC, D&A & Debt Schedules Clear content: Pro Forma!E51:CZ51, Pro Forma!E76:CZ86, Pro Forma!CA97:CZ97, Pro Forma!B113:CZ200, Inputs & Assumptions!E85 | G15: - On the Inputs & Assumptions tab, add a single new WCLOC input row labeled "Maximum Draw:" whose value pulls from the WCLOC max-draw output on the Cash Collection & WCLOC tab. - Create the new "D&A & Debt Schedules" tab, with its header block linked from the Pro Forma tab (scenario, Pre/Post-Close flag, period date and year headers), a 72-column monthly time grid numbered 1–72, and a five-year annual roll-up block (years 1–5) plus a Checks column. - On the D&A & Debt Schedules tab, build the Cap Ex & Depreciation section: inputs referencing TTM D&A and Post-Close D&A from Inputs & Assumptions plus the depreciation period; a monthly CapEx driver row that HLOOKUPs the CapEx schedule on Inputs & Assumptions (rows 64–67) and defaults to the year-5 rate divided by 12; a monthly Existing Depreciation (Pre-Close) row that runs the TTM D&A base straight-line and only fires when the period flag equals "Pre-Close"; a monthly Existing Depreciation (Post-Close) row that straight-lines the Post-Close D&A base over the depreciation period and only fires post-close; a monthly Depreciation (New Assets) row that layers running-total CapEx divided by (12 × depreciation period); a LESS: Fully Depreciated Assets row that reverses new-asset depreciation once its age exceeds the depreciation period in months (SUMIF against the month index against `MAX(period − D×12, 0)`); and a Total D&A row summing all four monthly components. Each row rolls up into the annual columns via SUMIF on the year header. - On the D&A & Debt Schedules tab, build the Existing Facility Debt schedule: inputs pulled from Inputs & Assumptions (Principal, Repayment Terms, Months, Interest Rate) with a PMT-based Payment; then a monthly waterfall consisting of Starting Balance (equals principal at t=1, otherwise prior ending balance), a Total Payment capped at Starting Balance vs. the PMT, an Interest Payment computed as annual rate/12 × starting balance (zeroed once the balance is fully paid), a Principal Payment equal to Total less Interest, and an Ending Balance equal to Starting less Principal. Annual roll-up columns use SUMIF for cash lines and INDEX/MATCH for balance snapshots. - On the D&A & Debt Schedules tab, build the Capital Lease schedule: inputs from Inputs & Assumptions (In-Use flag `>0`, Principal, Term Remaining, Asset Life, Interest Rate, Annual Escalator, Payment); a monthly schedule with Starting Balance rolling from Principal, a Total Payment equal to `MIN(Starting Balance, Payment × (1+Escalator)^(year−1))` where year comes from `ROUNDUP(COUNTA month index /12,0)`, an Interest Payment of rate/12 × Starting Balance (zeroed at payoff, with month 1 hard-coded to 0), a Principal Payment equal to Total less Interest, an Ending Balance, and a Straight-line Depreciation row equal to Principal / Term Remaining. Annual roll-ups mirror the debt block. - On the Pro Forma tab, insert a "Cash Collections" row directly beneath Total Revenue that pulls monthly collections from the Cash Collection & WCLOC monthly Total Monthly Collections row via INDEX/MATCH on the period key, falling back to Total Revenue in month 1, and adds Other Revenue; roll it up to the annual/TTM/quarter columns using the same SUMIF/SUMIFS pattern used by the other IS lines. - On the Pro Forma tab, extend the P&L below EBITDA with new rows: Depreciation & Amortization (linking to Total D&A on the new schedule tab), Net Interest Expense (Facility Debt interest + Capital Lease interest), WCLOC Interest Expense (pulled via INDEX/MATCH from the WCLOC schedule, with month 1 = 0), Other Expense (Income) (holds prior-period value from Adjusted Financials and flows forward), Net Income (EBITDA less the four items above), and NOPAT (`Net Income × Acquirer % Equity × (1−tax) + (Acquirer Mgmt Fee + Acquirer Overhead) × (1−tax)`, referencing the tax rate on Inputs & Assumptions and the Acquirer Overhead line below). - On the Pro Forma tab, add three opex aggregate rows below NOPAT: Operating Expenses (sum of the below-Revenue cost stack rows 53–61 plus Acquirer + Other Mgmt Fees on rows 72–73), Opex + Interest (Operating Expenses plus Net Interest Expense plus WCLOC Interest Expense), and Opex + Interest + DPP (Operating Expenses less the three debt principal-payment rows in the Facility Levered cash-flow section below). - On the Pro Forma tab, hard-code the historical/TTM Acquirer % Equity in the CC97 annual-roll-up column to 0 so post-close ownership scenarios don't backfill history. - On the Pro Forma tab, build the "Cash Flows" section starting with a "Levered Facility Distributable Cash Flows" block: pull Facility Levered Cash from the WCLOC tab's Net Distributable Cash Flow row via INDEX/MATCH (fallback to the sheet-internal Facility Levered Cash calc), then add-back rows for Facility Debt Principal, Facility Debt Interest (both from the D&A & Debt Schedules tab), WCLOC Principal, and WCLOC Interest (both from the WCLOC tab, sign-flipped), and sum to a UL Facility Distributable Cash Flows total. - On the Pro Forma tab, build the Unlevered cash-flow block: EBITDA, ADD WCLOC Draw (from WCLOC tab), ADD Developer WC Contribution (from WCLOC tab), LESS Rent Expense if Cap Lease (Capital Lease Total Payment on the D&A tab), LESS CapEx (HLOOKUP against the CapEx tiers on Inputs & Assumptions rows 64–67, defaulting to the year-5 rate, divided by 12), and LESS Δ in Working Capital (hard-coded to 0 monthly). Then present three parallel presentations: "UL Facility Cash (Old Calc)" = sum of the block; "UL Facility Cash (New Calc)" = the UL total from the Levered Distributable block above; and "UL Facility Cash (Flow Through)" = CHOOSE driven by a selector cell at B157 picking between old and new; place the selector defaults (1 old, 2 new) in cells B129/B131/B133 and B153/B155/B157 in the label column. - On the Pro Forma tab, follow the UL block with the UL AT Acquirer Cash waterfall: Acquirer Distributions (UL Flow-Through × Acquirer % Equity), LESS Acquirer Taxes on Facility Earnings (`MIN(−(NI + Net Interest)×Acquirer%×tax, 0)`), ADD Acquirer Mgmt Fee, LESS Acquirer Overhead (monthly = `−IF(Pre-Close, 0, Acquirer Overhead assumption on Inputs & Assumptions G49)/12`), LESS Acquirer Taxes on Mgmt Fee Profit (`MIN(−(Fee+Overhead)×tax, 0)`), summed to UL AT Acquirer Cash. - On the Pro Forma tab, build the parallel "Facility Levered" cash-flow block: EBITDA, ADD WCLOC Draw, ADD Developer WC Contribution, LESS three debt-principal rows (Facility Debt, Cap Lease, WCLOC), LESS three interest rows (Facility Debt, Cap Lease, WCLOC), LESS Δ in Working Capital (= UL Δ in WC). Present the same three-way choice (Old Calc = block sum; New Calc = the WCLOC Net Distributable pull; Flow-Through = CHOOSE via B157), then run the same Acquirer Distributions/Taxes/Mgmt Fee/Overhead/Taxes-on-Fee stack down to Facility Levered AT Acquirer Cash. - On the Pro Forma tab, build the "IOI" section: a header row that dynamically shows either the Consolidated or Equity variant based on the Consolidated/Equity switch on Inputs & Assumptions E10, then IOI Pre-Overhead, LESS Overhead (= Acquirer Overhead), and IOI Post-Overhead. Underneath, build the Consolidated IOI computation (EBITDA gated by Acquirer%≠0, ADD Acquirer Mgmt Fee, LESS D&A, summing to IOI [C] with pre-close periods forced to 0) and the Equity IOI computation (Net Income gated by Acquirer%, LESS Non-Controlling Income = `−NI × (1−Acquirer%)`, ADD Acquirer Mgmt Fee, summing to IOI [E]). - On the Pro Forma tab, build the "E-NCI" section directly mirroring the IOI section: dynamic label/switch on Inputs & Assumptions E10, E-NCI Pre-Overhead + LESS Overhead + E-NCI Post-Overhead. Underneath, Consolidated E-NCI (EBITDAM, LESS Other Mgmt Fee, LESS NCI = `−NI × (1−Acquirer%)`, summing to E-NCI [C] with pre-close periods forced to 0), and Equity Pre-Overhead E-NCI (Net Income, LESS Non-Controlling Income, ADD Acquirer Mgmt Fee, summing to E-NCI [E]). - On the Cash Collection & WCLOC tab, add the Cash Collections build at the top of the sheet: Surgical Revenue (INDEX/MATCH from Pro Forma row 47 by period), LESS Bad Debt (INDEX/MATCH from Pro Forma row 59), Net Patient Revenue = the difference, feeding the existing Collections Timing grid. - On the Cash Collection & WCLOC tab, add the Total Monthly Collections row that applies the in-month + six-month lag collection-percentage timing grid to Net Patient Revenue (In-Month × current NPR, plus month-1 timing × prior-month NPR, plus month-2 timing × two-months-prior NPR, etc., out through six months). - On the Cash Collection & WCLOC tab, build the "Cash before Working Capital / Cash from Operating Activities" block: Cash Collections (= Total Monthly Collections), Other Revenue (INDEX/MATCH from Pro Forma row 48), Interest Expense (−1× INDEX/MATCH of Pro Forma Net Interest Expense row 77), WCLOC Interest Expense (`MIN(−(prior beginning balance + prior draw) × rate/12, 0)`), Operating Expenses including interest (−1× INDEX/MATCH of Pro Forma Operating Expenses row 84), summed to Net Cash from Operating Activities. - On the Cash Collection & WCLOC tab, add the Cash from Investing Activities block: Purchase of Equipment (−1× INDEX/MATCH of the monthly CapEx row on the new D&A & Debt Schedules tab), summed to Net Cash from Investing Activities. - On the Cash Collection & WCLOC tab, add the Cash from Financing Activities block: Working Capital Equity Contribution (blank placeholder), Developer WC Contribution (fires in the payout month per Inputs & Assumptions I93/I94), Existing Facility Debt Principal Payments (−1× INDEX/MATCH of the Facility Debt Principal row on the D&A & Debt Schedules tab), summed to Net Cash from Financing Activities. Then compute Net Change in Cash before WCLOC as the sum of the three activity totals. - On the Cash Collection & WCLOC tab, build the WCLOC revolver section: a REFERENCE - PAYMENT TYPE row that flags "Interest-Only" until the term-month cutoff then switches to "Principal & Interest"; a Max Draw metric equal to the max of Beginning WCLOC Balance across the horizon (this is what feeds the new Maximum Draw line on Inputs & Assumptions); Beginning WCLOC Balance (rolls from prior Ending: Prior + Draw + Repayment); Cash from Working Capital Draw (fires whenever net change in cash before WCLOC turns negative and cash reserves are insufficient); Principal Repayment (0 during Interest-Only, otherwise `−(WCLOC Payment + WCLOC Interest)`); and Net Cash after WCLOC = Net Change in Cash before WCLOC + Draw + Repayment + prior Ending Cash Balance. - On the Cash Collection & WCLOC tab, build the Net Cash Distributions section: Beginning Cash Balance (rolls from prior Final Cash Balance + this month's Net Cash after WCLOC); Ending Cash Balance Before Distributions; a 30-Day Operating Expense Reserve (`−AVERAGEIF` of Opex + Interest + DPP row 86 on Pro Forma for the current year); Net Distributable Cash Flow = `MAX(Ending Cash + Reserve, 0)`; Final Cash Balance = Ending less Distributable. - On the Cash Collection & WCLOC tab, add the Existing Facility Debt input block at the bottom of the sheet (Principal / Months / Interest Rate / Payment via PMT / Term Month) pulled from Inputs & Assumptions rows 91–95 so the sheet-local WCLOC interest and payment-type calculations have their driver values. | H15: 552a9578-aaf8-453b-8f58-e85a1ed40315
A16: a0b42bc7 | B16: APPROVE to generating_prompt. | C16: wangche2532@gmail.com | D16: 8208 | E16: 7699 | F16: Clear content: Forecast, Unit Economics | G16: - On `Unit Economics`, add two helper drivers below the recurring churn/growth block — Average Customer Lifetime (1 / (monthly churn / churn-period months)) and, below the transaction block, Average # Repeat Transactions per year (12 / transaction period) and Average # of Lifetime Transactions (1 / (transaction churn / transaction-period months) / transaction-period months) — each wrapped in IFERROR to zero. - On `Unit Economics`, add the LTV discount-K factors immediately under the Discount Rate: K for recurring = (1 − recurring churn / churn-period) × (1 − discount rate) and K for transaction = (1 − transaction churn / transaction-period) × (1 − discount rate), both wrapped in IFERROR to 1. - On `Unit Economics`, add an Acquisition and Retention Costs input block containing Customer Acquisition Cost (already present), plus two net-new hardcoded per-unit costs: Cost of Retention and Expansion (recurring) of 5 and Cost of Repeat and Expansion (transaction) of 0. - On `Unit Economics`, add the LTV summary lines: LTV-recurring using the perpetuity-with-growth form D68×(1/(1−K_rec)+growth×K_rec/(1−K_rec)²) minus recurring discounts; LTV-one-time = one-time gross margin discounted back D30 months at the monthly discount rate; LTV-transaction using the same perpetuity-with-growth form on transaction gross margin less repeat cost, divided by transaction period and less transaction discounts; total LTV summed across the three; LTV / CAC = LTV ÷ |CAC|; and CAC Payback = |CAC| ÷ sum of the three per-period gross-margin-less-cost lines. - On `Unit Economics`, add the "Details for LTV calculations and Cash Flows per month" section (rows 55–70): SUMIFS pivots of Total Revenues and Total Cost of Sales by stream (Recurring, One time, Transaction) keyed off the E-column stream labels, then Gross Margin per stream = revenue − cost% × revenue, and finally Gross Margin less Cost of Retention/Repeat per stream (recurring less retention cost, transaction less repeat cost, one-time unchanged). - On `Unit Economics`, lay out the monthly Timescale header row spanning months 0 through 47 (D76 = 0, each successive column = prior + 1) with a final "N month total" label column, plus four timing driver rows underneath: Recurring Billing-cycle counter (MOD trigger against recurring billing period), Recurring Renewal/Churn counter (MOD trigger against recurring churn period), Repeat/Churn counter for transaction (MOD trigger against transaction period, zero-guarded), and a Transactions New-and-Repeat indicator (1 at month 0 then a MOD pulse every ROUND(12/repeat-per-year) months). - On `Unit Economics`, add three per-period Retention curves: Recurring retention = 1 × (1 − monthly churn)^renewal-counter; One-time retention held flat at 1 across the horizon; Transaction retention = 1 × (1 − transaction churn)^transaction-counter. - On `Unit Economics`, build the per-month Revenues-net-of-churn rows for each stream: recurring revenue steps up on each renewal cycle applying linear monthly growth (1 + annual-growth/(12×churn-period))^renewal-count and multiplied by retention (else carries prior column); one-time revenue fires only in month D30 and multiplies by retention; transaction revenue applies growth-and-retention every period the transaction flag = 1, seeded from D61 at month 0. - On `Unit Economics`, mirror the same three-stream logic to build per-month Cost-of-Sales rows (cost% × revenue driver, with the same billing/timing switches) and per-month Discount rows (recurring discount spread evenly over the billing period, one-time discount = 0, transaction discount applied at month 0). - On `Unit Economics`, build the per-month Billings-net-of-churn rows for each stream (recurring billings fire on each new billing cycle = revenue × billing months, less recurring discount at t=0; one-time billings = one-time revenue; transaction billings = transaction revenue less transaction discount at t=0). - On `Unit Economics`, build the per-month Acquisition-and-Retention-Costs rows: Acquisition Cost = −|CAC| at month 0 only; Retention Cost = −|retention cost| × recurring retention on each renewal cycle; Repeat Acquisition Cost = −|repeat cost| × transaction retention × transaction flag. - On `Unit Economics`, add the roll-up rows below the per-stream schedules: Billings-net-of-churn (sum of the three billing streams), Net Revenues net-of-churn (sum of the three revenue streams), Cost of Sales net-of-churn (sum of the three cost streams), and Acquisition-and-Retention-Costs net-of-churn (negative sum of the three cost lines), each with a right-side horizon total. - On `Unit Economics`, add the Gross Margin and Cash Flow analytical stack: Net Gross Margin per period as an array SUMPRODUCT of (revenue−cost−discount) × retention across streams; Cumulative Gross Margin; discounted versions of both using (1 + discount rate/12)^month; Billings-less-Cost-of-Sales per stream × retention plus a total; Net Cash Flow per period = billings − cost of sales + acquisition/retention costs; Cumulative Net Cash Flow; and discounted versions of both. - On `Unit Economics`, add the LTV Analysis pair at the bottom: % of LTV realized per period = discounted per-period gross margin ÷ total LTV, and % of LTV realized cumulative = discounted cumulative gross margin ÷ total LTV. - On `Forecast`, extend the header block above the existing date row with a Calendar/Index stack (rows 5–11): Month # in Model (starts at 1, +1 across), Fiscal Year (nested-IF anchored on Get Started fiscal-year-end using OFFSET −12 to roll years), Quarter in Fiscal Year (nested IF grouping Month#-in-Fiscal-Year into Q1–Q4), Quarter/Year concatenation, Month text (TEXT(date,"mmmm")), Month # in Fiscal Year (MOD offset against fiscal-year-end month), and Year of Operations (1 in first column, then carry forward). - On `Forecast`, extend the quarterly and annual summary columns (BH–CB) so every new monthly row automatically rolls into them via SUMIFS keyed on the new Fiscal Year and Quarter index rows (annual columns use one-key SUMIFS on Fiscal Year only), and pull the quarter/year headers themselves via INDEX/MATCH on the monthly index. - On `Forecast`, add the GROWTH assumption block (rows 14–20) driving new-customer volumes: Baseline growth rate seeded from Get Started growth rate then compounded each month by (1 + Get Started monthly change in growth rate); New Users seeded from Get Started starting users at the growth-start date, then prior × (1 + this-month growth rate); Seasonality Impact = new users × INDEX(Get Started seasonality table, MATCH on month name); Manual Input row (carried forward from prior column, defaulting to 0); and total New Users = MAX(0, baseline + seasonality + manual). - On `Forecast`, add the UNIT ECONOMICS lookup block (rows 23–28) pulling the four Unit Economics per-unit horizon streams — Billings, Net Revenues, Cost of Sales, and Acquisition-and-Retention Expenses — column-by-column from the corresponding Unit Economics per-period rows via IFERROR wrappers. - On `Forecast`, build the PREBUILT FORECAST cohort engine as four stacked 47-row cohort blocks (Billings rows 33–80, Net Revenues 81–128, Cost of Sales 129–176, Acquisition-and-Retention Costs 177–224). Each block has a header row that sums the cohorts below it; each cohort row is labeled with its origination month/index in columns B and D and pulls its cohort size in column E via INDEX against the New Users total row; the monthly cells use an array formula IF(cohort_start ≤ column month#, cohort_size × INDEX(matching per-unit stream row, column month# − cohort start + 1), 0) so each cohort ages through the per-unit curve starting from its origination month. | H16: a0b42bc7-af28-40a5-80c2-7a103169a005
A17: 41fbe12c | B17: APPROVE to generating_prompt. | C17: apathy@uchicago.edu | D17: 8187 | E17: 14756 | F17: Cleared DCF, Unused LLC DCF, Returns and Metrics, 2. Financial & Valuation Sum, 4. Assumptions, Appendix, Pipeline Extract, OSP Pipeline Extract, Valuation. | G17: - Build out the `Appendix` tab from empty by adding the deal‑name header pulling from Inputs & Assumptions F6, the tab‑name label "Appendix", the "Revenue Bridge" section header, and the print/formatting toggle row ("Formatting", "Print", "<<< flip this to make all fonts black for printing"). - Extend the `Valuation` tab's Key Metrics block (column H, rows 6–11) so that UL AT Cash Multiple pulls from the DCF invested‑capital multiple, IYC and FYC (IOI) pull the initial‑year and following‑year totals from the Pipeline Extract, UL IRR pulls the current‑price IRR from the DCF, and IOI/E‑NCI Ratio and EVA Variance pull from the Returns and Metrics tab. - Build the `4. Assumptions` tab from empty as a Modeled Assumptions summary: header pulling deal name from Inputs & Assumptions F6, a year row starting with =YEAR('Inputs & Assumptions'!F12) and stepping +1 across columns E–I, and rows pulling Profit Split to MSO, OSP Ownership in MSO, Physician Volume Growth (with % Growth), Professional Revenue per Pod MD Added, Ancillary Revenue per Pod MD Added, Revenue Growth (with % Growth), Professional/DME/Drugs/Fluoro./MRI/PT/X‑Ray revenue synergies, Initial Synergy Costs, SCA Taxes, and CapEx from Inputs & Assumptions and Practice Pro Forma columns L–Q, with a "Notes and Comments" column populated as "Arrowlytics" for the synergy rows. - Populate the `OSP Pipeline Extract` tab from empty with a single-row extract that pulls Facility/Transaction fields (Transaction, City, State, Close Date, Model Owner, Specialty, # Docs, # Shareholders, Revenue, Comp, SCA % of Comp) from Inputs & Assumptions and Historical Financials, Returns/Synergies fields (TTM & FY Rev/MD, TTM & FY Comp/SH, IYC/FYC IOI from Valuation H7/H8, Capital – Cash / WC / Debt Assumed from Valuation column F, IRR % from DCF V21, Synergy Revenue and Synergy Costs summed from Inputs & Assumptions column N, and # Partners/Shareholders Added summed from Inputs & Assumptions row 64) — including the two DO NOT ADJUST / instruction banner rows. - Build out the `Pipeline Extract` tab from empty with the instruction/banner rows (rows 1–3), a full row‑6 header schema across Facility Detail, Internal Transaction Detail, Operating Platform, Timeline, Financial Metrics, De Novo Pre‑Opening Expenses, and Monthly E‑NCI/IOI section groupings, and a single deal row (row 7) linking every field to Inputs & Assumptions, Historical Financials, Valuation, DCF, MSO Pro Forma, Practice Pro Forma, Returns and Metrics, and the Financial & Valuation Summary — including E‑NCI/IOI multiples defined as Capital/AS7 and Capital/BC7, EBITDA CAGR pull, and hardcoded zeros for Mgmt Fee, Capital Lease, Internal Deal Costs, and External Deal Costs (all 0) and N/A for De Novo pre‑opening lines. - Add the monthly E‑NCI and IOI extraction grid (columns BH–DC) on `Pipeline Extract`: build a "Months of Ownership" scalar =12-MONTH(BH4)+1 anchored on EOMONTH of the close date, a 24‑month rolling EOMONTH date strip for E‑NCI starting at the close date, a parallel 24‑month strip for IOI starting again at close date (column CF), a YEAR row above each date, hardcoded month numbers 1–24 in row 6, and INDEX/MATCH pulls of the annual E‑NCI (MSO Pro Forma row 42 + Practice Pro Forma row 115) and IOI (row 41 + row 114) totals divided by 12 (or by Months of Ownership in the partial first year). - Build out the `2. Financial & Valuation Sum` Financial Summary block (rows 5–65): header/title rows, a FYE column strip pulling MSO Pro Forma J6:Q6, and stacked P&L sections for Volume/Physicians, Practice P&L (Professional, Capitated, DME/Drugs/Fluoro/MRI/PT/X‑Ray ancillary lines with Total Ancillary, Total Practice Revenue, Practice Expenses, Practice Pre‑Physician Comp EBITDA, MSO Profit Split, MSO Profit, Expenses Reimbursed, Practice Transfer to MSO) and MSO P&L (Practice Transfer Revenue, MRI Leasing Revenue, Total MSO Revenue, Expenses Reimbursed, MSO Local Expenses, MSO EBITDA, D&A, Net Interest Expense, MSO Pre‑Physician Comp NI, IOI, E‑NCI, SCA Ownership of MSO = 'Inputs & Assumptions'!$F$20 − $L$10), each with % Growth / % Margin / per‑Physician sub-rows, a five‑year CAGR column O (ROUND(POWER(N/I,1/5)-1,3)), and a Checks column Q that ties each subtotal back to the Practice or MSO Pro Forma engine. - Build the Key Metrics Summary sub-block on `2. Financial & Valuation Sum` (rows 67–80): Total Revenue per Physician (sum of the per‑physician professional, capitated, and ancillary rows), UL Distributions per Physician and Levered Distributions per Physician (MSO + Practice Pro Forma row sums), Patient Visits per Physician (Practice Pro Forma row 70), and placeholder MRI Clicks / PT Visits / X‑Rays per Physician rows, each with a five‑year CAGR and a % Growth row. - Build the DCF Sensitivity Analysis on `2. Financial & Valuation Sum` (rows 82–93) mirroring the DCF tab: Purchase Price / E‑NCI matrix on left, Purchase Price / Y‑P E‑NCI matrix on right, with perpetuity growth rate strip stepping ±0.5% around a hardcoded 0 center for both blocks, and each row's discount rate label reading from DCF E44:I48 sensitivity outputs then divided by K62 (yr P E‑NCI) for the multiples table. - Build the Purchase Price Sensitivity Analysis on `2. Financial & Valuation Sum` (rows 95–115): "At‑LOI vs Post‑Dil" column and a five‑case sensitivity ("10% Discount / 5% Discount / Current / 5% Prem / 10% Prem") applied to Equity Purchase (×90%/95%/100%/105%/110%), holding Cash Contribution and Debt Assumed constant, then rolling to Purchase Price, Purchase Price / Y‑P E‑NCI, Equity Investment / Physician Owner (÷H9), and an IRR row linked to DCF and array‑formula sensitivity cells. - Build the `Returns and Metrics` OUTPUT A Investment Dashboard (rows 5–15): UL AT Cash Multiple from Valuation H6, SCA UL AT Cash Flow CAGR label built from year column headers with a ROUND(POWER(Q9/M9,1/4)-1,3) CAGR, IOI CAGR row, IOI-to-E‑NCI Ratio =AVERAGE(N9:O9)/AVERAGE(N15:O15) with hurdle text "1.0x - 2.0x", and Levered IRR pulling DCF V32. - Build `Returns and Metrics` OUTPUT B1 IOI and OUTPUT B2 E‑NCI columns (rows 5–15): year strip from MSO Pro Forma row 6, Practice IOI row 114 + MSO IOI row 41 for OUTPUT B1 with Total IOI sum, and Practice E‑NCI row 115 + MSO E‑NCI row 42 for OUTPUT B2 with Total E‑NCI sum. - Build `Returns and Metrics` OUTPUT C Economic Value Add (rows 18–37): UL EVA Calculation summing SCA PT Distributions (avg from MSO row 77 + Practice row 150), SCA Management Fee (avg from row 81 + row 154), −Overhead (avg from row 82 + row 155), and −Capital Charge; Capital Charge Calculation as Capital Outlay (=Valuation!F36) × 2% (hardcoded 0.02); EVA Threshold Test = EVA − 2% of Capital Outlay to yield Variance; and a footnote referencing the second two years of full ownership. - Build `Returns and Metrics` OUTPUT D Operating Results block (rows 18–32): year strip, PC & MSO Levered PT Distributions with sub‑splits (MD Share @1 = 1 − 'Inputs & Assumptions'!$F$22, SCA Share @ = 'Inputs & Assumptions'!G22, Sponsor A Share = 1 − M22 − M21) summing the corresponding MSO Pro Forma rows 95/98/101/103 and Practice Pro Forma rows 168/171/174/176, SCA Unlevered AT Cash Flow (row 86 + row 159), SCA Unlevered AT Cash Multiple = Valuation!$F$65/SCA UL AT CF, SCA E‑NCI (row 42 + row 115), and SCA Effective Multiple. - Build `Returns and Metrics` OUTPUT F Valuation & Invested Capital Summary (rows 34–48): Cash Contributions Scenarios matrix pulling MSO EBITDA (Valuation!$H$24) × Multiple (Valuation!$D$6) − Debt (Valuation!$H$27) + Cash (Valuation!$H$29 with a ×2 alternate case), computing Post Money Equity Value, SCA Ownership Post Money = O41/O42, Additional % SCA to Purchase = Valuation!$D$10 − O43, SCA Money for Additional %, Total SCA Capital Outlay, Total SCA Ownership, and Sponsor Ownership Less Partner B % = O47 − 'Inputs & Assumptions'!$L$10. - Build `Returns and Metrics` Sources & Uses of Capital block (rows 42–46): Sources = SCA Cash (Valuation H61+H62) + SCA Debt Liability (Valuation H64); Uses = Cash Contribution (H61) + Equity Purchase (H62) + Debt Assumption (H64), with Total Sources / Total Uses subtotals. - Build `Returns and Metrics` OUTPUT G Physician Detail table shell (rows 54–72): column headers Physician Name / Specialty / Ownership % / Age / TTM NPR/Case / TTM Volume / TTM Revenue / TTM Distributions / Liquidity and a repeating footnote about ownership‑percent ties. - Extend the `DCF` tab: build the assumptions header (Effective Valuation Date pulling Inputs & Assumptions F12, Discount Rate 0.1, Perpetuity Growth Rate 0.03) and the Present Value of Cash Flows Calculation block — year date strip from Inputs & Assumptions F12+1 stepping annually, Total SCA AT UL Cash Flows from Practice (Practice Pro Forma row 159) and MSO (MSO Pro Forma row 86) with total row and terminal‑year =O17*(1+$F$8); Stub Period = YEARFRAC(F6, date) capped at 1, Discount Period on half‑year convention (I19/2 then +1s), Present Value Factor 1/(1+F7)^period, and AT Operating Cash Flow at Present Value. - Build the `DCF` Enterprise Value and Multiples block (rows 28–37): PV of Cash Flows = SUM(I24:O24), PV of Reversionary Value = P24/(F7−F8), Enterprise Value = sum, Net Debt/Excess Cash = −(Valuation!H64 − Valuation!H61), Equity Value, Implied Transaction Multiples row of EV / (MSO NCI + Practice NCI) for each projected year, and UL AT Cash Multiple = Valuation!$F$65/AVERAGE($K$17:$L$17). - Build the `DCF` Sensitivity Analysis (rows 39–48) as a two‑variable data table on Enterprise Value indexed by Discount Rate (row axis stepping ±1% around center 0.1) and Perpetuity Growth Rate (column axis stepping ±0.5% around 0.03), plus a parallel EBITDA‑NCI multiple table dividing the EV outputs by MSO row 42 + Practice row 115. - Build the `DCF` IRR sensitivity engine (rows 17–34, columns U–PN): daily/annual date strip anchored at Effective Valuation Date, cash‑flow rows for "10% Discount / 5% Discount / Current Price / 5% Premium / 10% Premium" that shift Valuation!$H$63 (equity outlay) by ±5%/10%, X = W − Valuation!$H$64 debt, followed by annual UL cash flows across Y:AD tied to I17:N17, and XIRR(cash flow strip, date strip) in column V for each scenario, plus DCF Check row =XIRR(-G33, cash flows) with status flag ("OK"/"CHECK" if V25 ≈ F7). Add PC Only and MSO Only IRR variants using Valuation!H49/H53/H55 and Valuation!H29/H33/H35 for outlay and Practice Pro Forma row 159 / MSO Pro Forma row 86 for cash flows. - Build the `DCF` Levered IRR block (rows 31–34) with Current Price / PC Only / MSO Only rows using the same W outlay values but replacing UL cash flows with MSO Pro Forma row 112 + Practice Pro Forma row 185 (Levered PT distributions), plus PC‑only and MSO‑only variants. - Build the `DCF` IRR/ROIC returns tables (rows 50–56 and 99–108): five‑price sensitivity of Upfront Capital Outlay (=-X19..X23), IRR (=V19..V23), and ROIC per year computed as K60/I52 where K60 = MSO Pro Forma M117 + Practice Pro Forma M190 (After‑Tax Operating Income) across projection years; label column with 10% Discount / 5% Discount / Current Price / 5% Premium / 10% Premium. - Build the `DCF` Present Value of Invested Capital / Earn Out block (rows 63–97): Cost of Capital = 0.1, Upfront Consideration = Valuation!$F$65, Earn Out Payment = MIN(Multiple × EBITDA over Threshold, Max Earn Out) with EBITDA Threshold/Target scaffold (hardcoded 0/0 for Y1 then 10/15 for years 2‑6), Earn Out Multiple = Max/(Target−Threshold), Invested Capital and Cumulative Invested Capital rows, half‑year‑convention discount periods, PV factors 1/(1+$E$66)^period, and Return on Invested Capital = K60/K95. - Build the `DCF` Returns Table – Earn Out Structure (rows 110–119): five‑price sensitivity replicating the upfront IRR/ROIC table but with Invested Capital = P78 (cumulative), IRR = X74, and ROIC row values pulling K97:P97; use hardcoded initial capital outlay column K115:K119 (142800 / 153000 / 163200 / 173400 / 183600) and a 5‑year ROIC grid populated with 0.1 / 0.2 test values. - Build the parallel `Unused LLC DCF` tab from a near‑empty shell as a stand‑alone LLC valuation: DCF Assumptions (Income Tax Rate from Inputs & Assumptions F42, CapEx = "Management Estimates", Working Capital = Inputs & Assumptions F43 × Δ Revenue, Discount Rate 0.1, Perpetuity Growth Rate 0), year date strip, LLC P&L (Total Revenue from MSO Pro Forma row 12, EBITDA from MSO Pro Forma row 20 with % Growth and % Margin), SCA E‑NCI = EBIT × Ownership Stake ('Inputs & Assumptions'!$F$20). - Build the `Unused LLC DCF` LLC Cash Flows (rows 28–52): EBIT = EBITDA − D&A (MSO Pro Forma rows 24+25), Income Tax Expense at $I$6, After‑Tax Operating Income, Add D&A, Less CapEx (MSO Pro Forma row 64) and Less WC Changes (row 65) — with terminal‑year CapEx = −D&A and WC = −$G$8×ΔRevenue — After‑Tax Operating Cash Flow, × Ownership Stake row, and SCA Cash Flows from Specialty Practice. - Build the `Unused LLC DCF` PV/EV block (rows 54–72): Stub Period, Discount Period (half‑year convention), Present Value Factor at $R$7, PV of AT Operating Cash Flow (with K59 = K52×K57×K54 for stub period), PV of Cash Flows summed, PV of Reversionary Value = Q59/(R7−R8), Enterprise Value, Net Debt / Excess Cash, Equity Value, and Implied Transaction Multiples (EV/Revenue and EV/EBITDA‑NCI). - Build the `Unused LLC DCF` two‑variable Sensitivity Analysis for Enterprise Value @ 51% Ownership (rows 74–83) with Discount Rate axis stepping ±1% around 0.1 and Perpetuity Growth Rate axis stepping ±0.5% around 0, and a parallel Y‑P EBITDA‑NCI Multiple table dividing outputs by $L$24. - Build the `Unused LLC DCF` IRR engine (columns U–PL, rows 19–38): daily half‑year date strip from R6, EBITDA cash flow row seeded from PV block (V20:AB20 =K52*K54 … Q52) then grown by (1+$R$8), +CF/−CF rows netting to Net CF, XIRR against date strip, IRR check row, ROIC Type toggle "Upfront" vs Earn‑Out. - Build the `Unused LLC DCF` Invested Capital / Earn Out block (rows 93–116) with Cost of Capital 0.1, Upfront Consideration = Valuation!F65, EBITDA Threshold/Target scaffold hardcoded 0/0 for Y1 then 10/15 for Y2‑6, Maximum Earn Out Payment, Earn Out Multiple, EBITDA Over Threshold, Invested Capital and Cumulative rows, half‑year‑convention PV factors at $E$95, and NPV of Invested Capital. - Build the `Unused LLC DCF` ROIC and IRR Returns Tables (rows 118–148): Return on Invested Capital = K40/K124, an Upfront‑payment five‑price returns table using Valuation!$F$65 anchor with hardcoded outlay grid 142800 / 153000 / 163200 / 173400 / 183600 and 0.1 IRR/ROIC placeholder grid, plus an Earn Out Structure returns table with 0.1/0.2 ROIC placeholder grid, and a ROIC Type toggle that switches the summary block between the two tables via IF($H$85="Upfront",…). | H17: 41fbe12c-7c20-463d-96e8-4ae8700d1c0d
A18: 7b4c773f | B18: APPROVE to generating_prompt. | C18: apathy@uchicago.edu | D18: 7637 | E18: 6881 | F18: Cleared DCF & IRR, Draw Schedule. | G18: - On the **Draw Schedule** tab, layer a "Details" input header block above the pre-existing S-Curve Strength anchor: pull Construction Start and Construction End dates from the I&A timeline, compute Construction Duration as DATEDIF of the two dates in months, and label the S-Curve Strength driver (existing value 4). - Below the Details block on **Draw Schedule**, build a Project Cost Item table that pulls the four project-cost line items (labels, cost, LTC%) by direct reference from the I&A capex block, then compute Project Cost as the SUM of the four costs and blended LTC as SUMPRODUCT of LTC × Cost divided by total Project Cost. - Add a Cedarbrook portion sub-block on **Draw Schedule**: pull the Cedarbrook ownership % from I&A, compute Cedarbrook Portion of Project Cost as total Project Cost × ownership %, and Cedarbrook Equity as that portion × (1 − blended LTC). - Build the monthly Draw Schedule grid on **Draw Schedule** spanning 30 columns: a date row starting at Construction Start and stepping via EOMONTH, a Construction Month counter (starting at the existing anchor value 1 and incrementing +1), and a Total column that SUMs the monthly cells. - On the same grid, populate the "Construction Draw" row using a normal-distribution S-curve: for each month, gate the cell with AND(month ≥ start_month, month ≤ end_month) and compute the incremental S-curve share as (NORM.DIST(m − start+1, duration/2, duration/strength, TRUE) − NORM.DIST(m − start, duration/2, duration/strength, TRUE)) / (1 − 2·NORM.DIST(0, duration/2, duration/strength, TRUE)) × total Project Cost. - Add a "Debt" row on **Draw Schedule** that pulls blended LTC into column F and spreads it across months as LTC × monthly Construction Draw; add an "Equity" row that uses (1 − LTC) as the anchor and spreads similarly; both rows sum across in column E. - Add a "Cumulative Draw" row on **Draw Schedule** that running-sums the monthly Construction Draw across the grid and returns MAX of the row in column E. - Add an "Output (for DCF)" block at the bottom of **Draw Schedule** with two rows: Cedarbrook Equity Draw (Unlevered) = Cedarbrook ownership × monthly Construction Draw (spreads the full construction draw at the Cedarbrook %), and Cedarbrook Equity Draw (Levered) = Cedarbrook ownership × monthly Equity row (spreads only the equity slice at the Cedarbrook %); each sums to column E. Add two IRR readback cells that link to the Unlevered and Levered Current IRRs on the DCF & IRR tab. - On the **DCF & IRR** tab, build a DCF Assumptions header block: title, Income Tax Rate (pulled from I&A), a "See Build" tag for Capex, Working Capital as % of revenue set to 0.10, First Patient date pulled from I&A, Discount Rate set to 0.10, and Perpetuity Growth Rate set to 0. - Build the annual timeline for the Unlevered DCF on **DCF & IRR**: a year-number row =YEAR of the date row, a date row starting at First Patient and stepping by EDATE(prior,12), and a Pre-Ops/period-index row that tags column F "Pre-Ops" and starts the operating counter at 1 in column G stepping +1. - Populate the Unlevered cash-flow strip on **DCF & IRR**: Total Revenue linked to Pro Forma!R/CB/CC/CD/CE/CF row 43, Cedarbrook AT Unlevered Cash linked to Pro Forma!R44 in Pre-Ops and to Cedarbrook Cash Flow row 29 in operating years, Working Capital Δ computed as −(current-year Revenue − prior-year Revenue) × WC% × Cedarbrook ownership from I&A, and post-WC unlevered cash as the SUM of the two. - Add discounting mechanics to the Unlevered DCF on **DCF & IRR**: Terminal Value in the final operating column as post-WC cash × (1+g)/(r−g); Year Fraction row using MIN(YEARFRAC(First Patient, year-end), 1); Discount Period as half of Year Fraction in the first operating column and +1 each year thereafter; Present Value Factor as 0 when tagged Pre-Ops else 1/(1+r)^period; PV of Cash Flows = post-WC cash × PV factor; PV of TV = TV × final PV factor; AT UL Cash at PV = SUM of the two. - Add the enterprise-to-equity roll on **DCF & IRR**: Enterprise Value (Cedarbrook Portion) = SUM of AT UL Cash at PV across the timeline; Less Cedarbrook Debt linked to I&A!F60; Equity Value (Cedarbrook Portion) = EV − Debt. - Build the Unlevered IRR strip on **DCF & IRR** across ~430 monthly columns (F:PT): a monthly-then-annual date row that steps via EOMONTH during construction (using the row-39 flag to detect month-zero) and via DATE(YEAR+1,6,30) thereafter; a labeling row that tags construction columns "Constrx" and annual columns =YEAR of the date; a "Current" cash-flow row that pulls −Draw Schedule Cedarbrook Equity Draw (Unlevered) during construction and switches to SUMIFS of annual post-WC unlevered cash by year (with post-forecast years grown at perpetuity growth g); a DCF-Check row = −Enterprise Value spread the same way, with a check cell comparing its XIRR to the input discount rate; five sensitivity rows at 90%/95%/current/105%/110% of the Current cash flow; an "At Phase B" row = Current; and an XIRR column E for each row using the date row as its dates. - Repeat the Levered DCF block on **DCF & IRR** (rows 46–64) with the same year timeline, tax and WC logic, and discounting mechanics, but pulling Cedarbrook AT Levered Cash from Cedarbrook Cash Flow row 54 (with 0 in Pre-Ops) and rolling directly to Equity Value (no debt subtraction). - Build the Levered IRR strip on **DCF & IRR** (rows 66–73) mirroring the Unlevered IRR strip but pulling −Draw Schedule Cedarbrook Equity Draw (Levered) during construction and using the same 90/95/current/105/110/AtPhaseB fan and XIRR column. - Convert the pre-existing hard-coded sensitivity grid on **DCF & IRR** (rows 80–84 × cols E–I) into a live two-variable data table: add a Capital Investment header row and Perpetuity Growth Rate header row; wire the Perpetuity axis (row 79) around center 0 in ±0.5% steps and the Discount Rate axis (column D) around center 0.10 in ±1% steps; place the DCF anchor formula in D79 = Enterprise Value and convert cell E80 into a TABLE(Perpetuity, Discount) data table computing EV across the grid. - Add a companion sensitivity block on **DCF & IRR** (rows 86–93) that divides each cell of the EV sensitivity by Pro Forma!CD82 (Year-3 E-NCI) to express the sensitivity as a multiple, using the same axis references. - Build the ROIC schedule at the bottom of **DCF & IRR** (rows 95–106): pull a 9-year year strip starting from the DCF's first operating year (row 15) incrementing +1; pull NOPAT (Cedarbrook Share) from Pro Forma!CB75:CF75 for years 1–5 and grow years 6–9 at perpetuity growth rate g; build a Purchase Price sensitivity table with five rows keyed off center price = −(I&A!F38 + I&A!G38) at 90/95/100/105/110% and columns for each year, where each cell is SUMIF of NOPAT for that year divided by −Purchase Price, with row labels linked to the corresponding Unlevered IRR sensitivity labels. | H18: 7b4c773f-02c0-42cf-a37b-04b6773b86c0
A19: 62d0dff1 | B19: APPROVE to generating_prompt. | C19: wangche2532@gmail.com | D19: 7131 | E19: 5587 | F19: Delete tabs: DCF & IRR, Valuation Assumptions | G19: - On a new `Valuation Assumptions` tab, build the Transaction Inputs block: hardcode Developer EBITDA Multiple 10, Physician EBITDA Multiple 7, and Acquirer Mgmt Fee Buyout 0; compute Multiple on Existing Fees as the buyout divided by TTM adjusted management fees from Adjusted Financials (with an IFERROR "N/A"); add Internal deal costs 180000 and External deal costs 600000 with a Total = sum. - Below that, build a two-column Valuation walk with headers "Unlevered" and "Facility Levered". For each column, pull TTM Adjusted EBITDA from Adjusted Financials twice, multiply by the Developer and Physician multiples respectively to compute a Developer Enterprise Value and a Physician Enterprise Value. - Add a blended-EV block: pull Developer Equity Sold and Physician Equity Sold from Inputs & Assumptions (J−K rows for each holder), compute Blended Enterprise Value as the equity-weighted average of the Developer and Physician EVs, and back out an implied Seller Multiple as Blended EV / TTM EBITDA. - Add the debt bridge: under Unlevered, force Existing Facility Debt and Existing Capital Leases to 0; under Facility Levered, pull those two values from Inputs & Assumptions. Equity Value = Blended EV − existing debt − existing leases. - Add the acquirer cash outlay stack: pull Acquirer Equity Purchase % from Inputs & Assumptions; compute Acquirer Equity Purchase = Equity Value × %, plus Acquirer Portion Mgmt Fee Buyout and Acquirer Deal Costs from the inputs block above; add an Acquirer Pro Rata WCLOC Assumption = Inputs & Assumptions WCLOC × Acquirer % (placed above the line in Unlevered, below the line in Facility Levered, with the other column zeroed) and sum to Acquirer Cash Outlay. - Add the total-capital block: under Unlevered set Acquirer Pro Rata Debt Assumption to 0; under Facility Levered compute it as Acquirer % × (existing debt + leases). Total Capital Outlay = Cash Outlay + Debt Assumption + the offsetting WCLOC line, so both columns reconcile to a comparable total. - On a new `DCF & IRR` tab, build the DCF Assumptions header: pull Income Tax Rate from Inputs & Assumptions, mark Capital Expenditures as "See Build", hardcode Working Capital % of Revenue 0.10, pull Close Date from Inputs & Assumptions, hardcode Discount Rate 0.10 and Perpetuity Growth Rate 0. - Build the Unlevered DCF projection strip across the Pro Forma calendar years: pull period-end dates from Pro Forma row 4, add a Close/Pre-Close/Proj. flag comparing each year to the close-date year, pull Total Revenue from Pro Forma row 49 and Acquirer AT Unlevered Cash from Pro Forma row 140, compute Working Capital investment as −Δrevenue × WC% × Acquirer %, and sum to Acquirer AT Unlevered Cash post-WC. - Add the Unlevered discounting mechanics: Terminal Value in the final period = post-WC cash × (1+g)/(WACC−g); Year Fraction = 0 if pre-close, else MIN(YEARFRAC(close, Dec-31), 1); Discount Period = 0 pre-close, half the year fraction in the close period, then prior period + 0.5 in the first proj. year and +1 thereafter; Present Value Factor = 1/(1+r)^period; PV of Cash Flows = post-WC × PV factor; PV of TV in the terminal column; sum to AT UL Cash at Present Value. - Add the Unlevered valuation output: Enterprise Value = sum of AT UL PVs across all columns; Less Acquirer Debt pulled from the Facility Levered debt line on the Valuation Assumptions tab; Equity Value = EV − debt. - Build the Unlevered IRR schedule with six scenarios labeled 10% Discount, 5% Discount, Current, 5% Premium, 10% Premium, and At LOI. Create a horizontal date strip starting at the close date, then a mid-close date computed as (Dec-31 − close)/2 + close − 1, then successive June-30 dates for many years extending out to column OQ (~400 columns); the header row is YEAR() of each date. Seed the Current row at −(Valuation Assumptions Unlevered Equity Purchase + Mgmt Fee Buyout + WCLOC assumption); seed 10%/5% Discount and 5%/10% Premium as ±multipliers on the Current seed (0.9, 0.95, 1.05, 1.1); seed At LOI at Current and DCF-check at −EV. For every subsequent column, pull the AT UL post-WC cash for that year via SUMIFS on the projection strip if within the projection horizon, else grow the prior column by (1+g). Compute IRR in an anchor column as XIRR of the full row against the date row. Add a DCF Check flag comparing the Current IRR to the discount rate. - Repeat the entire construction for the Levered DCF: same structure but pull Acquirer AT Levered Cash from Pro Forma row 164, drop the Less Acquirer Debt line (Equity Value = sum of Levered PVs directly), seed the Current IRR scenario at −(Valuation Assumptions Facility Levered Equity Purchase + Mgmt Fee Buyout) with no WCLOC term, and reuse the same 0.9/0.95/1.05/1.1 seeds and the identical multi-hundred-column date/cash-flow extension out to column OQ for XIRR. - Add a DCF Sensitivity block: a 5×5 Excel Data Table with row inputs stepping Discount Rate by ±0.5% around a 0.10 center (two down, two up) and column inputs stepping Perpetuity Growth Rate by ±1% around 0 (two below, two above), driving the Unlevered Enterprise Value output. Add a parallel table below it that divides each sensitivity cell by Pro Forma acquirer EBITDA (row 186) to express the sensitivity as an EV/E-NCI multiple. - Add the ROIC block: pull NOPAT (Acquirer Share) from Pro Forma row 82 across the projection years and extend beyond the last projected year by (1+g); build a purchase-price column linked to the six IRR scenario seeds above; compute ROIC for each scenario × year as SUMIF of NOPAT by year divided by −purchase price. | H19: 62d0dff1-ef18-40ae-879c-f7dd0fc7a67e
A20: 443385cc | B20: APPROVE to generating_prompt. | C20: wangche2532@gmail.com | D20: 5573 | E20: 7623 | F20: Clear content: Pro Forma!A1:CZ111 | G20: - Build the Volume & Contribution driver strip in rows 26–31: pull organic case growth, organic NPR/case growth, organic supplies/case growth, and organic SWB/case growth from the assumptions growth grid via SUMIFS keyed on the month-count header, and pull inorganic NPR/case growth from the assumptions inorganic block filtered to "ON" scenarios. - Build the Base Case block in rows 7–14: seed the ADJ TTM anchor column with Adjusted Financials pulls for Base Cases, Base Revenue, Base Supplies, and Base SWB, and set the anchor month equal to the TTM/12; in each forward month, grow Base Cases by the organic case growth driver and grow per-case NPR/supplies/SWB by their respective organic growth drivers plus inorganic NPR growth, then multiply each per-case metric by Base Cases to derive Base Revenue, Base Supplies, and Base SWB dollars. - Build the Decremental block in rows 16–19 and Incremental block in rows 21–24: seed both with 0 in the anchor column, and in each monthly column pull cases/revenue/supplies/SWB from the assumptions add/lose-block filtered to "ON" scenarios, splitting negative values into Decremental and positive values into Incremental via signed SUMIFS on the month-count header. - Build the Total row set in rows 33–36: sum Base Cases with net incremental/decremental cases to get Total Cases, and add Base + Decremental + Incremental for Total Revenue, Total Supplies, and Total SWB. - Build the Case Ramp adjustment block in rows 38–43: pull the "Working Days" and "Seasonality" toggle labels from the assumptions inputs, compute an ADJ: Working Days factor via a VLOOKUP of the month-end date against the Physician Inputs working-day table divided by the average monthly base (zeroing out when the toggle is off), compute an ADJ: Seasonality factor via an HLOOKUP of the month number against the Physician Inputs seasonality row (zeroing out when the toggle is off), and pull a Case Ramp factor via INDEX/MATCH of the month-count header against the assumptions ramp block; multiply Total Cases by (1 + working days) × (1 + seasonality) × (1 + case ramp) to produce Total Adjusted Cases. - Build the P&L revenue block in rows 45–49: set Surgical Cases equal to Total Adjusted Cases; seed anchor-column Surgical Revenue, Other Revenue, and Total Revenue from Adjusted Financials/12; in each forward month calculate Surgical Revenue as Surgical Cases × NPR/Case KPI, roll Other Revenue forward by the prior month grown by the Other Revenue growth driver, and sum to Total Revenue. - Build the operating-cost block in rows 53–61: seed anchor-column Supplies, SWB, Variable Direct, Variable Indirect, Rent, and Fixed from Adjusted Financials/12 and set RBO Fee and Integration Expenses to 0; in each forward month drive Supplies, SWB, and Variable Direct off Surgical Cases × their respective per-case KPI (with SWB overridden to hold at the anchor value while the period counter is ≤ the assumptions SWB-hold threshold), roll Variable Indirect, Rent, and Fixed forward off the prior month grown by their growth drivers (with Rent forced to 0 when the assumptions Rent treatment equals "Capital"), calculate Bad Debt as Surgical Revenue × Bad Debt %, calculate RBO Fee as 0 during Pre-Close periods and otherwise as the assumptions RBO rate × Surgical Cases, and set Integration Expenses to the assumptions Integration expense hardcode while the period counter is ≤ the assumptions Integration cutoff (0 otherwise). - Build the EBITDAM row in row 62 as Total Revenue less the sum of Supplies, SWB, Variable Direct, Variable Indirect, Rent, Fixed, Bad Debt, RBO Fee, and Integration Expenses. - Build the Management Fee Scenarios selector block in rows 64–70: pull the three scenario labels and their base % of NPR-BD, Acquirer % of Fee, and Active Scenario index from the assumptions Mgmt Fee block; use CHOOSE against the Active Scenario to select the applicable % of NPR-BD; compute Scenario 1 as % of NPR-BD × (Surgical Revenue − Bad Debt) zeroed during Pre-Close, Scenario 2 as MIN of Scenario 1 and a compounded fee cap (assumptions cap × (1 + escalator)^year less cumulative fees already paid in that year via SUMIFS on the year row), and Scenario 3 as the assumptions fixed fee × (1 + escalator)^year / 12; use CHOOSE against the Active Scenario to pick the active Mgmt Fee. - Build the fee split and EBITDA rows in rows 72–74: split the active Mgmt Fee into Acquirer Mgmt Fee (active fee × Acquirer %) and Other Mgmt Fee (active fee × (1 − Acquirer %), overridden during Pre-Close to a hardcoded anchor of 0), and calculate EBITDA as EBITDAM less both mgmt fees. - Build the KPIs block in rows 88–100: compute NPR/Case, Supplies/Case, and SWB/Case as Total Revenue/Supplies/SWB divided by Total Cases; compute Variable Direct/Case, Variable Indirect/Case, Rent/Case, and Fixed/Case using Surgical Cases as the denominator (with Variable Direct/Case seeded from the anchor and grown forward by the Variable Direct growth driver plus a Year-1 step-down from the assumptions); pull Acquirer/MD/Other % Equity from the assumptions equity block using Pre-Close vs. post-close columns; and drive Bad Debt % as the anchor Bad Debt/Revenue ratio during Pre-Close and the assumptions Bad Debt % otherwise. - Build the Growth summary block in rows 103–111: for each monthly column compute Volume growth as Total Adjusted Cases vs. prior month, NPR/Case, Supplies/Case, SWB/Case, and Variable Direct/Case as their KPI vs. prior month, and pull Other Revenue, Variable Indirect, Rent, and Fixed growth from the assumptions growth grid via SUMIFS keyed on the month-count header. - Build the ADJ TTM anchor column (column CC) for the P&L, cost, and KPI rows: pull row-level TTM values for Surgical Cases, Surgical Revenue, Other Revenue, Supplies, SWB, Variable Direct, Variable Indirect, Rent, Fixed, Bad Debt, and Other Mgmt Fee from Adjusted Financials; hardcode RBO Fee, Integration Expenses, and each Mgmt Fee Scenario at 0; and derive Total Revenue as the sum of Surgical + Other, EBITDAM as Total Revenue less the operating cost stack, EBITDA as EBITDAM less mgmt fees, and the KPI/ratio rows from the same TTM cells. - Build the annual rollup columns (CD:CH, Years 1–5) for each P&L, cost, mgmt-fee, and KPI row by SUMIFS-ing the monthly strip against the Year header row for dollar lines, computing subtotals (Total Revenue, EBITDAM, EBITDA) as sums of their components, and computing KPI rows as the annual dollar ratios; add a CAGRs column (CI) computing 5-year CAGR as (Year 5 / ADJ TTM)^(1/5) − 1 wrapped in IFERROR returning "-". - Build the historical/plan reference columns CM:CT for the same P&L, cost, and KPI rows: pull the two historical years (CM, CN) from Adjusted Financials columns E and F; compute the close year (CO) as the sum of the YTD-to-Close and Close-Dec stub columns plus a linked pre-close pull; and compute forward plan years (CP:CT) via SUMIF against the Year header row for dollar lines, with subtotals summed from components and KPI rows computed as annual ratios. - Build the stub-period columns CW:CY for the same P&L, cost, and KPI rows: pull the current-year pre-close reference (CW) from Adjusted Financials column I; compute the YTD-to-Close stub (CX) as SUMIFS of the monthly strip filtered to "Pre-Close" periods in the close-year; compute the Close-Dec stub (CY) as SUMIFS of the monthly strip filtered to post-close periods (period counter > 0) in the close-year; and roll subtotals from their components. Include a hardcoded 301356.1 seeded into the Year-1 close-year cell for each of the three Mgmt Fee Scenario rows and the active-scenario row. | H20: 443385cc-42c6-486b-ac8e-fd8724d99160
... A51: 3d458c2a | B51: APPROVE to generating_prompt. | C51: apathy@uchicago.edu | D51: 131 | E51: 6602 | F51: Cleared Dynamo Deal Import, Dynamo Physician Import, Key Metrics Box. | G51: - On the **Key Metrics Box** tab, lay out a 2-block header/value grid titled "Key Metrics" with paired label-and-value columns: left block links Syndication Date, Accounting Treatment, UL AT Cash Multiple, EVA Variance, # of ORs, and Facility Sq. Ft. to their sources on I&A, 4. Returns & Metrics, and I&A respectively; right block links First Patient Date, UL AT IRR, IYC (IOI), FYC (IOI), # of Syndicated Physicians, and Volume Year One to 2. Financial & Valuation Sum, Pipeline Extract, Physician Outputs, and Pro Forma. All values are pulled by direct cell reference — no new hardcodes beyond the label text. - On the **Dynamo Physician Import** tab, build the header row across 21 columns: Salutation, First name, Last name, Name, Ownership in, Ownership type, Specialty, Contact type, Pre-Close, Post-Close, Commitment Agreement Status, TTM NPR/Case, TTM Volume, TTM Revenue, TTM Distributions, Liquidity, Run-rate NPR/Case, Run-rate Volume, Run-rate Revenue, Run-rate Distributions, Age. - Populate the physician detail rows (rows 2–8) on **Dynamo Physician Import**: hardcode Salutation as "Dr." for every row; hardcode Contact type as "Physician" for every row; link Ownership in to the I&A deal-name cell (absolute reference) for every row; for row 2, link First name / Last name / Specialty / Run-rate NPR-Case / Run-rate Volume / Run-rate Revenue to the corresponding I&A physician detail cells and build Name as concatenation of Salutation + " " + First name + " " + Last name; hardcode Ownership type as "Physician Equity" for rows 2–3 and "Employed" for rows 4–8; hardcode Commitment Agreement Status as "Not Requested" for row 2, "Requested" for row 3, and "N/A" for rows 4–8. - On the **Dynamo Deal Import** tab, lay out the deal-metadata header row across columns A–CE: Name, Accounting, DOA Approval Required, TTM Financials As Of, Last model import, Sign Date, Cedarbrook Close / Fund Date, Syndication Close Date, Construction Start Date, First Patient Date, Cedarbrook Ownership %, Cedarbrook Ownership in Practice, Cedarbrook Ownership in MSO, Equity, Management fee buyout, Total Purchase Price, Debt Assumption, Capital Lease, Cash Contribution to MSO, Cash Contribution to Practice, Total Cedarbrook Capital, Construction Cost, Equipment Cost, Working Capital Line of Credit, Legal/Other Cost, Total Project Cost, IY E-NCI, FY E-NCI, FY E-NCI Multiple, Fac Level AT CF, UL AT CF, UL AT CF Multiple, UL AT IRR, TTM EBITDA Multiple, EVA Variance, 5-YR EBITDA CAGR, IYC (IOI), FYC (IOI), FY IOI Multiple, Pre-Opening Net Income, Cedarbrook Development Fee Revenue, Pre-Opening IOI, EBITDA TTM, EBITDA Year 1, EBITDA Year 2, Facility Distributions TTM, Facility Distributions Year 1, Facility Distributions Year 2, Distributions per 1% TTM, Distributions per 1% Year 1, Distributions per 1% Year 2, # of Shareholders TTM/Y1/Y2/Y3, # of Total MDs TTM/Y1/Y2/Y3, Practice Revenue TTM/Y1/Y2/Y3, Practice Compensation TTM/Y1/Y2/Y3, MSO Compensation TTM/Y1/Y2/Y3, MSO OSP Pre-Tax Cash Flow TTM/Y1/Y2/Y3, Total Comp as % of Practice Revenue TTM/Y1/Y2/Y3, and OH as a % of Practice Revenue TTM/Y1/Y2/Y3. - On row 2 of **Dynamo Deal Import**, wire the deal-level identifiers and dates by linking Name, Accounting, and each date field (Sign, Cedarbrook Close, Syndication Close, Construction Start, First Patient) to the corresponding I&A cells; set DOA Approval Required to the I&A control cell and set Last model import to `=NOW()`. Wire Cedarbrook Ownership %, Equity, Management fee buyout (blank), Total Purchase Price, Debt Assumption, Capital Lease, Cash Contribution amounts, Total Cedarbrook Capital, Construction Cost, Equipment Cost, Working Capital Line of Credit, Legal/Other Cost, and Total Project Cost each to their I&A source cells. - On row 2 of **Dynamo Deal Import**, populate the returns block: IY E-NCI and FY E-NCI use SUMIF against the Pro Forma year header row (S1:BZ1) against Pro Forma row 82 (E-NCI), keyed off YEAR(First Patient Date) and YEAR(First Patient Date)+1; FY E-NCI Multiple = Total Cedarbrook Capital / FY E-NCI; Fac Level AT CF and UL AT CF pull from Development Earnings K44 and K52; UL AT CF Multiple = Total Cedarbrook Capital / UL AT CF; UL AT IRR pulls from DCF & IRR E39; EVA Variance pulls from 4. Returns & Metrics H34; IYC (IOI) and FYC (IOI) use the same SUMIF pattern against Pro Forma row 104; FY IOI Multiple = Total Cedarbrook Capital / FYC. - On row 2 of **Dynamo Deal Import**, populate the pre-opening and EBITDA/distribution block: Pre-Opening Net Income = Pro Forma R73; Cedarbrook Development Fee Revenue = Pro Forma R61 + Pro Forma CB61; Pre-Opening IOI = Pro Forma R104; EBITDA Year 1 and Year 2 = Pro Forma CB65 and CC65; Facility Distributions Year 1 and Year 2 = Cedarbrook Cash Flow BN38 and BO38; Distributions per 1% Year 1 and Year 2 = Facility Distributions × 0.01. - On row 2 of **Dynamo Deal Import**, build the 24-column annual E-NCI time series (CF2:DC2) by pointing at Pro Forma row 82 columns S–AP in sequence, and the 24-column annual IOI time series (DD2:EA2) by pointing at Pro Forma row 104 columns S–AP in sequence; drive the CG1:EA1 header labels off column CF1 with a running `=prev+1` chain (with column DD1 as a second anchor). - On row 2 of **Dynamo Deal Import**, build the ORC Needed flag in EB2 as an IF/OR that returns "Yes" when Management services agreement fee < 250000, Margin % < 0.25, or any of the first nine OM option columns (EG2:EO2) begins with "Option X" (LEFT of length 8); otherwise "No". - On row 2 of **Dynamo Deal Import**, wire the ORC economics: Management services agreement fee = Inputs D11; Total services costs = Summary Output D32; Margin % = Summary Output D34; Total partnership expense = Summary Output D29. - On row 2 of **Dynamo Deal Import**, build the three OM cost-detail blocks (columns EG:FA "OM", FB:FV "OM Future Cost", GW:GQ "OM Cedarbrook Cost") as IFS formulas that return the corresponding Summary Output column C value (for current OM), column F value (for future and Cedarbrook cost blocks), or blank when I&A G20 = "OFF"; map each of the 21 service categories (PAS and Claims Clearinghouse, HR, Supply Chain, Revenue Cycle, Coding, Clinical Reporting, Accounting, Treasury, Tax, Credentialing, Risk Management, Managed Care, Clinical Support, Sales, Legal, Regulatory Compliance, Website, Cedarbrook Insight, Operations, Finance, IT) to its assigned Summary Output row. - On row 2 of **Dynamo Deal Import**, wire the OM status and DOA columns: Last OM Update = IF(I&A G21="","",I&A G21); OM Status = I&A G22; DOA – Initial = I&A D33; DOA – Final = I&A D34. | H51: 3d458c2a-cfe5-4a22-9f35-1c48780f5a38

Sheet Agent runs
A1: Task | B1: Run created (UTC) | C1: Status | D1: Input tokens | E1: Output tokens | F1: Duration ms | G1: Empty context | H1: Model | I1: Message | J1: Error | K1: Task ID
A2: 018939a8 | B2: 2026-09-01T14:30:41.528Z | C2: completed | D2: 58289 | E2: 3491 | G2: FALSE | I2: Claude workbook agent completed | K2: 018939a8-5f2a-46e7-9f5b-309a20147f37
A3: 018939a8 | B3: 2026-09-01T22:55:52.83Z | C3: completed | D3: 87390 | E3: 3542 | G3: FALSE | I3: Claude workbook agent completed | K3: 018939a8-5f2a-46e7-9f5b-309a20147f37
A4: 0e3f0394 | B4: 2026-09-01T15:18:09.45Z | C4: completed | D4: 5390 | E4: 1 | G4: TRUE | I4: Claude workbook agent completed | K4: 0e3f0394-b3e2-4e6c-836e-704eff6c48e2
A5: 0e3f0394 | B5: 2026-09-01T21:57:14.007Z | C5: completed | D5: 231844 | E5: 8360 | G5: FALSE | I5: Claude workbook agent completed | K5: 0e3f0394-b3e2-4e6c-836e-704eff6c48e2
A6: 15a0ebf7 | B6: 2026-08-31T18:35:40.673Z | C6: completed | D6: 5411 | E6: 1 | G6: TRUE | I6: Claude workbook agent completed | K6: 15a0ebf7-8354-4e97-bdfd-764a03bef9ee
A7: 15a0ebf7 | B7: 2026-09-01T21:57:19.931Z | C7: completed | D7: 902266 | E7: 16002 | G7: FALSE | I7: Claude workbook agent completed | K7: 15a0ebf7-8354-4e97-bdfd-764a03bef9ee
A8: 1998a617 | B8: 2026-08-31T15:47:36.494Z | C8: completed | D8: 5437 | E8: 4 | G8: TRUE | I8: Claude workbook agent completed | K8: 1998a617-9037-46d2-912b-adfdb4441444
A9: 1998a617 | B9: 2026-09-01T21:57:17.411Z | C9: completed | D9: 590320 | E9: 10687 | G9: FALSE | I9: Claude workbook agent completed | K9: 1998a617-9037-46d2-912b-adfdb4441444
A10: 1ef09f14 | B10: 2026-09-01T15:19:06.934Z | C10: completed | D10: 5380 | E10: 1 | G10: TRUE | I10: Claude workbook agent completed | K10: 1ef09f14-3119-434f-b561-884e196c6caa
A11: 1ef09f14 | B11: 2026-09-01T21:57:14.837Z | C11: completed | D11: 80859 | E11: 5771 | G11: FALSE | I11: Claude workbook agent completed | K11: 1ef09f14-3119-434f-b561-884e196c6caa
A12: 21d534e3 | B12: 2026-09-01T15:19:42.585Z | C12: completed | D12: 5383 | E12: 7 | G12: TRUE | I12: Claude workbook agent completed | K12: 21d534e3-8c09-46e5-8a5d-b5c55c8522a2
A13: 21d534e3 | B13: 2026-09-01T21:57:12.444Z | C13: completed | D13: 617199 | E13: 14519 | G13: FALSE | I13: Claude workbook agent completed | K13: 21d534e3-8c09-46e5-8a5d-b5c55c8522a2
... A101: fdfd6024 | B101: 2026-09-01T23:19:02.062Z | C101: completed | D101: 101233 | E101: 6225 | G101: FALSE | I101: Claude workbook agent completed | K101: fdfd6024-51d6-49c8-93c8-39d033b1bd8d

Sheet Transitions
A1: Task | B1: At (UTC) | C1: From | D1: To | E1: Event | F1: Triggered by | G1: Task ID
A2: 018939a8 | B2: 2026-08-31T13:25:35.052Z | C2: NONE | D2: needs_decomp | E2: CLONED | F2: system@tsip.ai | G2: 018939a8-5f2a-46e7-9f5b-309a20147f37
A3: 018939a8 | B3: 2026-08-31T13:25:45.512Z | C3: needs_decomp | D3: needs_decomp | E3: POOL_CLAIM | F3: apathy@uchicago.edu | G3: 018939a8-5f2a-46e7-9f5b-309a20147f37
A4: 018939a8 | B4: 2026-09-01T14:30:25.317Z | C4: needs_decomp | D4: needs_decomp | E4: AUTO_POOL | F4: apathy@uchicago.edu | G4: 018939a8-5f2a-46e7-9f5b-309a20147f37
A5: 018939a8 | B5: 2026-09-01T14:30:25.352Z | C5: needs_decomp | D5: decomp_complexity_check | E5: SUBMIT_DECOMP | F5: apathy@uchicago.edu | G5: 018939a8-5f2a-46e7-9f5b-309a20147f37
A6: 018939a8 | B6: 2026-09-01T14:30:31.99Z | C6: decomp_complexity_check | D6: decomp_complexity_check | E6: FIELDS_WRITE | F6: system@tsip.ai | G6: 018939a8-5f2a-46e7-9f5b-309a20147f37
A7: 018939a8 | B7: 2026-09-01T14:30:32.844Z | C7: decomp_complexity_check | D7: generating_outline | E7: COMPLEXITY_CHECK_DONE | F7: system@tsip.ai | G7: 018939a8-5f2a-46e7-9f5b-309a20147f37
A8: 018939a8 | B8: 2026-09-01T14:31:39.54Z | C8: generating_outline | D8: generating_outline | E8: FIELDS_WRITE | F8: system@tsip.ai | G8: 018939a8-5f2a-46e7-9f5b-309a20147f37
A9: 018939a8 | B9: 2026-09-01T14:31:40.823Z | C9: generating_outline | D9: decomp_review | E9: SUBMIT_TASK_OUTLINE | F9: system@tsip.ai | G9: 018939a8-5f2a-46e7-9f5b-309a20147f37
A10: 018939a8 | B10: 2026-09-01T22:55:45.592Z | C10: decomp_review | D10: generating_outline | E10: ADMIN_OVERRIDE | F10: ali@meridian.ai | G10: 018939a8-5f2a-46e7-9f5b-309a20147f37
A11: 018939a8 | B11: 2026-09-01T22:56:53.843Z | C11: generating_outline | D11: generating_outline | E11: FIELDS_WRITE | F11: system@tsip.ai | G11: 018939a8-5f2a-46e7-9f5b-309a20147f37
A12: 018939a8 | B12: 2026-09-01T22:56:55.103Z | C12: generating_outline | D12: decomp_review | E12: SUBMIT_TASK_OUTLINE | F12: system@tsip.ai | G12: 018939a8-5f2a-46e7-9f5b-309a20147f37
... A466: fdfd6024 | B466: 2026-09-01T23:21:00.955Z | C466: generating_outline | D466: decomp_review | E466: SUBMIT_TASK_OUTLINE | F466: system@tsip.ai | G466: fdfd6024-51d6-49c8-93c8-39d033b1bd8d

Sheet Method
A1: How this was built
A2: 1. Queue: tsip_tasks joined to tsip_project_versions, project_id = sheets, status = decomp_review, archived_at is null. 45 rows at 23:40 UTC on 2026-09-01.
A3: 2. Outline, transition description and unique-formula count come from the latest tsip_attempts row per task (metadata.task_outline, transition_description, decomp_unique_formula_count).
A4: 3. Input/output workbook pair comes from tsip_attempts.messages annotated field_id = input_workbook / output_workbook, joined to tsip_files for name, size and content hash.
A5: 4. Agent runs are tsip_model_run_progress rows with job_type = modal_claude_agent. Under 10,000 input tokens = empty context (the two populations are ~5.4k and >=60k with nothing between).
A6: 5. History is tsip_state_transitions per task; the human decomper is the SUBMIT_DECOMP actor, admin overrides are ADMIN_OVERRIDE events.
A7: 6. "Bucket in 09-01 triage" is the bucket each task had in decomp/decomp_review_triage.csv earlier today (A1 no outline, A2 looping, B thin, C truncated, D thin transition).
A8: 7. Diagnosis and quality flags: I read all 39 stored outlines end to end. Flags are limited to generator noise (summary bullets above the build steps), stray fragments, and low-formula mechanical builds.
A9: 8. Decomper too-easy prior is hardcoded from decomp/sota_priors.md (60-day SOTA outcomes). It is a prior, not a verdict on any single task.
A11: Reading the recommendation
A12: APPROVE: outline present and coherent. Send to generating_prompt. Release in batches of about 20; releasing 133 at once earlier today produced a 10.5% prompt-generation failure rate.
A13: Regenerate: small workbook that failed twice. One more attempt is cheap.
A14: HOLD: workbook over 4MB, failed every attempt, and no >4MB task in this queue has ever loaded. Re-running burns a slot and returns another empty outline. Needs an engineering fix to the outline agent (workbook ingestion / size limit) or a hand-written outline.
